Workbook

Sheet InnovYes_Pivot
A3: Innov_Decision | B3: (Multiple Items)
A5: Row Labels | B5: Count of ID
A6: No | B6: 185
A7: Available to consumers (has been launched on the market) | B7: 2
A8: Undergoing clinical trials | B8: 3
A9: Unsure | B9: 3
A10: (blank) | B10: 177
A11: No_by_Default | B11: 75
A12: (blank) | B12: 75
A13: Unsure | B13: 1
A14: Unsure | B14: 1
A15: Yes | B15: 120
A16: Approved by FDA and scheduled to be launched | B16: 22
A17: Approved by FDA but not scheduled to be launched | B17: 11
... A22: Grand Total | B22: 381

Sheet Phase_Review
A2: Row Labels | B2: Approved by FDA and scheduled to be launched | C2: Approved by FDA but not scheduled to be launched | D2: Available to consumers (has been launched on the market) | E2: FDA application submission and/or FDA testing | F2: Undergoing clinical trials | G2: Unsure | H2: (blank) | I2: Grand Total | J2: conflict check | M2: Note: No conflicts amongst - Innov = YES responses, only some Unsure for Phase
A3: AIWFIE0020150928eb9s0002w | G3: 1 | I3: 1 | J3: =IF(SUM(G3:H3)>1, "Review", IF(MAX(B3:F3) =I3, "None", "Review")) -> Review
A4: AIWINE0020150619eb6k000s1 | E4: 1 | I4: 1 | J4: =IF(SUM(G4:H4)>1, "Review", IF(MAX(B4:F4) =I4, "None", "Review")) -> None
A5: AMHL000020150513eb5d00005 | F5: 1 | I5: 1 | J5: =IF(SUM(G5:H5)>1, "Review", IF(MAX(B5:F5) =I5, "None", "Review")) -> None
A6: APRS000020150819eb8j00030 | B6: 1 | I6: 1 | J6: =IF(SUM(G6:H6)>1, "Review", IF(MAX(B6:F6) =I6, "None", "Review")) -> None
A7: ATEHEA0020150512eb5c00001 | B7: 1 | I7: 1 | J7: =IF(SUM(G7:H7)>1, "Review", IF(MAX(B7:F7) =I7, "None", "Review")) -> None
A8: ATPHAB0020150317eb3h0002t | C8: 1 | I8: 1 | J8: =IF(SUM(G8:H8)>1, "Review", IF(MAX(B8:F8) =I8, "None", "Review")) -> None
A9: ATPHAB0020150514eb5e0005o | E9: 1 | I9: 1 | J9: =IF(SUM(G9:H9)>1, "Review", IF(MAX(B9:F9) =I9, "None", "Review")) -> None
A10: ATPHAB0020151212ebcc0000d | B10: 1 | I10: 1 | J10: =IF(SUM(G10:H10)>1, "Review", IF(MAX(B10:F10) =I10, "None", "Review")) -> None
A11: ATPHAM0020150115eb1e000eq | B11: 1 | I11: 1 | J11: =IF(SUM(G11:H11)>1, "Review", IF(MAX(B11:F11) =I11, "None", "Review")) -> None
A12: ATPHAM0020150303eb320005r | G12: 1 | I12: 1 | J12: =IF(SUM(G12:H12)>1, "Review", IF(MAX(B12:F12) =I12, "None", "Review")) -> Review
A13: ATPHAM0020150501eb4u0000r | C13: 1 | I13: 1 | J13: =IF(SUM(G13:H13)>1, "Review", IF(MAX(B13:F13) =I13, "None", "Review")) -> None
A14: ATPHAM0020150518eb5d0003g | F14: 1 | I14: 1 | J14: =IF(SUM(G14:H14)>1, "Review", IF(MAX(B14:F14) =I14, "None", "Review")) -> None
A15: ATPHAM0020150529eb5r000bt | B15: 1 | I15: 1 | J15: =IF(SUM(G15:H15)>1, "Review", IF(MAX(B15:F15) =I15, "None", "Review")) -> None
A16: ATPHAM0020150701eb6u0009g | G16: 1 | I16: 1 | J16: =IF(SUM(G16:H16)>1, "Review", IF(MAX(B16:F16) =I16, "None", "Review")) -> Review
A17: ATPHAM0020151009eba80008e | F17: 1 | I17: 1 | J17: =IF(SUM(G17:H17)>1, "Review", IF(MAX(B17:F17) =I17, "None", "Review")) -> None
A18: ATPHAM0020151112ebba0005o | D18: 1 | I18: 1 | J18: =IF(SUM(G18:H18)>1, "Review", IF(MAX(B18:F18) =I18, "None", "Review")) -> None
A19: ATPHAM0020151215ebce0000h | F19: 1 | I19: 1 | J19: =IF(SUM(G19:H19)>1, "Review", IF(MAX(B19:F19) =I19, "None", "Review")) -> None
A20: ATTOPN0020150823eb8l00006 | C20: 1 | I20: 1 | J20: =IF(SUM(G20:H20)>1, "Review", IF(MAX(B20:F20) =I20, "None", "Review")) -> None
A21: BHLD000020150518eb5d00011 | E21: 1 | I21: 1 | J21: =IF(SUM(G21:H21)>1, "Review", IF(MAX(B21:F21) =I21, "None", "Review")) -> None
A22: BHLD000020151023eban0003h | F22: 1 | I22: 1 | J22: =IF(SUM(G22:H22)>1, "Review", IF(MAX(B22:F22) =I22, "None", "Review")) -> None
A23: BIOELSE020150123eb1g00013 | E23: 1 | I23: 1 | J23: =IF(SUM(G23:H23)>1, "Review", IF(MAX(B23:F23) =I23, "None", "Review")) -> None
A24: BIOELSE020150522eb5e0000f | D24: 1 | I24: 1 | J24: =IF(SUM(G24:H24)>1, "Review", IF(MAX(B24:F24) =I24, "None", "Review")) -> None
A25: BIOELSE020150831eb8o0000e | F25: 1 | I25: 1 | J25: =IF(SUM(G25:H25)>1, "Review", IF(MAX(B25:F25) =I25, "None", "Review")) -> None
A26: BIWK000020150619eb6o000wo | G26: 1 | I26: 1 | J26: =IF(SUM(G26:H26)>1, "Review", IF(MAX(B26:F26) =I26, "None", "Review")) -> Review
A27: BIWK000020151216ebcg0004y | E27: 1 | I27: 1 | J27: =IF(SUM(G27:H27)>1, "Review", IF(MAX(B27:F27) =I27, "None", "Review")) -> None
A28: BOSBJO0020150319eb3j0008e | E28: 1 | I28: 1 | J28: =IF(SUM(G28:H28)>1, "Review", IF(MAX(B28:F28) =I28, "None", "Review")) -> None
A29: BOSBJO0020150508eb580002u | E29: 1 | I29: 1 | J29: =IF(SUM(G29:H29)>1, "Review", IF(MAX(B29:F29) =I29, "None", "Review")) -> None
A30: BSFLVO0020151030ebau0005m | J30: =IF(SUM(G30:H30)>1, "Review", IF(MAX(B30:F30) =I30, "None", "Review")) -> None
A31: BWR0000020150227eb2r0000g | E31: 1 | I31: 1 | J31: =IF(SUM(G31:H31)>1, "Review", IF(MAX(B31:F31) =I31, "None", "Review")) -> None
A32: BWR0000020150305eb350006b | B32: 1 | I32: 1 | J32: =IF(SUM(G32:H32)>1, "Review", IF(MAX(B32:F32) =I32, "None", "Review")) -> None
A33: BWR0000020150730eb7u000b3 | D33: 1 | I33: 1 | J33: =IF(SUM(G33:H33)>1, "Review", IF(MAX(B33:F33) =I33, "None", "Review")) -> None
A34: BWR0000020151019ebaj000g3 | B34: 1 | I34: 1 | J34: =IF(SUM(G34:H34)>1, "Review", IF(MAX(B34:F34) =I34, "None", "Review")) -> None
A35: BWR0000020151030ebau0000k | B35: 1 | I35: 1 | J35: =IF(SUM(G35:H35)>1, "Review", IF(MAX(B35:F35) =I35, "None", "Review")) -> None
A36: CCT0000020150520eb5i0000a | F36: 1 | I36: 1 | J36: =IF(SUM(G36:H36)>1, "Review", IF(MAX(B36:F36) =I36, "None", "Review")) -> None
A37: CLADV00020150605eb6100003 | F37: 1 | I37: 1 | J37: =IF(SUM(G37:H37)>1, "Review", IF(MAX(B37:F37) =I37, "None", "Review")) -> None
A38: CTRW000020150109eb1c0000i | F38: 1 | I38: 1 | J38: =IF(SUM(G38:H38)>1, "Review", IF(MAX(B38:F38) =I38, "None", "Review")) -> None
A39: DJDN000020150105eb15001u2 | B39: 1 | I39: 1 | J39: =IF(SUM(G39:H39)>1, "Review", IF(MAX(B39:F39) =I39, "None", "Review")) -> None
A40: DJDN000020150108eb18000zc | E40: 1 | I40: 1 | J40: =IF(SUM(G40:H40)>1, "Review", IF(MAX(B40:F40) =I40, "None", "Review")) -> None
A41: DJDN000020150108eb18001mg | G41: 1 | I41: 1 | J41: =IF(SUM(G41:H41)>1, "Review", IF(MAX(B41:F41) =I41, "None", "Review")) -> Review
A42: DJDN000020150311eb3b004c0 | E42: 1 | I42: 1 | J42: =IF(SUM(G42:H42)>1, "Review", IF(MAX(B42:F42) =I42, "None", "Review")) -> None
A43: DJDN000020150430eb4u002md | C43: 1 | I43: 1 | J43: =IF(SUM(G43:H43)>1, "Review", IF(MAX(B43:F43) =I43, "None", "Review")) -> None
A44: DJDN000020150604eb64003sw | C44: 1 | I44: 1 | J44: =IF(SUM(G44:H44)>1, "Review", IF(MAX(B44:F44) =I44, "None", "Review")) -> None
A45: DJDN000020150609eb69001qd | D45: 1 | I45: 1 | J45: =IF(SUM(G45:H45)>1, "Review", IF(MAX(B45:F45) =I45, "None", "Review")) -> None
A46: DJDN000020150615eb6f003t8 | F46: 1 | I46: 1 | J46: =IF(SUM(G46:H46)>1, "Review", IF(MAX(B46:F46) =I46, "None", "Review")) -> None
A47: DJDN000020150702eb72001pv | D47: 1 | I47: 1 | J47: =IF(SUM(G47:H47)>1, "Review", IF(MAX(B47:F47) =I47, "None", "Review")) -> None
A48: DJDN000020150728eb7s001k1 | G48: 1 | I48: 1 | J48: =IF(SUM(G48:H48)>1, "Review", IF(MAX(B48:F48) =I48, "None", "Review")) -> Review
A49: DJDN000020150728eb7s002si | B49: 1 | I49: 1 | J49: =IF(SUM(G49:H49)>1, "Review", IF(MAX(B49:F49) =I49, "None", "Review")) -> None
A50: DJDN000020150812eb8c001oy | F50: 1 | I50: 1 | J50: =IF(SUM(G50:H50)>1, "Review", IF(MAX(B50:F50) =I50, "None", "Review")) -> None
A51: DJDN000020150930eb9u001fg | F51: 1 | I51: 1 | J51: =IF(SUM(G51:H51)>1, "Review", IF(MAX(B51:F51) =I51, "None", "Review")) -> None
A52: DJDN000020151001eba1002ac | E52: 1 | I52: 1 | J52: =IF(SUM(G52:H52)>1, "Review", IF(MAX(B52:F52) =I52, "None", "Review")) -> None
A53: DJDN000020151119ebbj003f3 | E53: 1 | I53: 1 | J53: =IF(SUM(G53:H53)>1, "Review", IF(MAX(B53:F53) =I53, "None", "Review")) -> None
A54: DJDN000020151124ebbo0048a | F54: 1 | I54: 1 | J54: =IF(SUM(G54:H54)>1, "Review", IF(MAX(B54:F54) =I54, "None", "Review")) -> None
A55: DRGW000020150109eb1g0003u | G55: 1 | I55: 1 | J55: =IF(SUM(G55:H55)>1, "Review", IF(MAX(B55:F55) =I55, "None", "Review")) -> Review
A56: DRGW000020150529eb650005a | B56: 1 | I56: 1 | J56: =IF(SUM(G56:H56)>1, "Review", IF(MAX(B56:F56) =I56, "None", "Review")) -> None
A57: DRIDY00020150623eb6n00002 | D57: 1 | I57: 1 | J57: =IF(SUM(G57:H57)>1, "Review", IF(MAX(B57:F57) =I57, "None", "Review")) -> None
A58: DTMNTR0020150616eb6f0004l | G58: 1 | I58: 1 | J58: =IF(SUM(G58:H58)>1, "Review", IF(MAX(B58:F58) =I58, "None", "Review")) -> Review
A59: ENPNEW0020150130eb1u00044 | B59: 1 | I59: 1 | J59: =IF(SUM(G59:H59)>1, "Review", IF(MAX(B59:F59) =I59, "None", "Review")) -> None
A60: ENPNEW0020150914eb9e00078 | D60: 1 | I60: 1 | J60: =IF(SUM(G60:H60)>1, "Review", IF(MAX(B60:F60) =I60, "None", "Review")) -> None
A61: FBCOM00020151027ebar000xh | D61: 1 | I61: 1 | J61: =IF(SUM(G61:H61)>1, "Review", IF(MAX(B61:F61) =I61, "None", "Review")) -> None
A62: FNWIR00020150618eb6i000mc | B62: 1 | I62: 1 | J62: =IF(SUM(G62:H62)>1, "Review", IF(MAX(B62:F62) =I62, "None", "Review")) -> None
A63: FREG000020151222ebcm00023 | G63: 1 | I63: 1 | J63: =IF(SUM(G63:H63)>1, "Review", IF(MAX(B63:F63) =I63, "None", "Review")) -> Review
A64: GLOMCP0020150730eb7u004vk | J64: =IF(SUM(G64:H64)>1, "Review", IF(MAX(B64:F64) =I64, "None", "Review")) -> None
A65: GRAY000020150901eb910002v | E65: 1 | I65: 1 | J65: =IF(SUM(G65:H65)>1, "Review", IF(MAX(B65:F65) =I65, "None", "Review")) -> None
A66: HAMW000020150109eb1g004bm | J66: =IF(SUM(G66:H66)>1, "Review", IF(MAX(B66:F66) =I66, "None", "Review")) -> None
A67: HAMW000020150508eb5f0049t | G67: 1 | I67: 1 | J67: =IF(SUM(G67:H67)>1, "Review", IF(MAX(B67:F67) =I67, "None", "Review")) -> Review
A68: HAMW000020150529eb6500135 | F68: 1 | I68: 1 | J68: =IF(SUM(G68:H68)>1, "Review", IF(MAX(B68:F68) =I68, "None", "Review")) -> None
A69: HNASNI0020150805eb85000rx | C69: 1 | I69: 1 | J69: =IF(SUM(G69:H69)>1, "Review", IF(MAX(B69:F69) =I69, "None", "Review")) -> None
A70: HNFRDSNT20150502eb35000qq | D70: 1 | I70: 1 | J70: =IF(SUM(G70:H70)>1, "Review", IF(MAX(B70:F70) =I70, "None", "Review")) -> None
A71: HOU0000020150623eb6k00027 | F71: 1 | I71: 1 | J71: =IF(SUM(G71:H71)>1, "Review", IF(MAX(B71:F71) =I71, "None", "Review")) -> None
A72: HUGNEN0020150914eb9e001xh | B72: 1 | I72: 1 | J72: =IF(SUM(G72:H72)>1, "Review", IF(MAX(B72:F72) =I72, "None", "Review")) -> None
A73: INVDAI0020150429eb4t0001g | F73: 1 | I73: 1 | J73: =IF(SUM(G73:H73)>1, "Review", IF(MAX(B73:F73) =I73, "None", "Review")) -> None
A74: JOENG00020150227eb34003c0 | G74: 1 | I74: 1 | J74: =IF(SUM(G74:H74)>1, "Review", IF(MAX(B74:F74) =I74, "None", "Review")) -> Review
A75: JOENG00020150313eb3i0002v | D75: 1 | I75: 1 | J75: =IF(SUM(G75:H75)>1, "Review", IF(MAX(B75:F75) =I75, "None", "Review")) -> None
A76: JOENG00020150313eb3i000k8 | D76: 1 | I76: 1 | J76: =IF(SUM(G76:H76)>1, "Review", IF(MAX(B76:F76) =I76, "None", "Review")) -> None
A77: JOENG00020151102ebb2001ss | E77: 1 | I77: 1 | J77: =IF(SUM(G77:H77)>1, "Review", IF(MAX(B77:F77) =I77, "None", "Review")) -> None
A78: JORTI00020150626eb6q0008i | E78: 1 | I78: 1 | J78: =IF(SUM(G78:H78)>1, "Review", IF(MAX(B78:F78) =I78, "None", "Review")) -> None
A79: KHALEJ0020151106ebb50005q | B79: 1 | I79: 1 | J79: =IF(SUM(G79:H79)>1, "Review", IF(MAX(B79:F79) =I79, "None", "Review")) -> None
A80: KUWNA00020151215ebce000b8 | D80: 1 | I80: 1 | J80: =IF(SUM(G80:H80)>1, "Review", IF(MAX(B80:F80) =I80, "None", "Review")) -> None
A81: LBA0000020150702eb7200qb9 | B81: 1 | I81: 1 | J81: =IF(SUM(G81:H81)>1, "Review", IF(MAX(B81:F81) =I81, "None", "Review")) -> None
A82: LBA0000020150720eb7k00jll | E82: 1 | I82: 1 | J82: =IF(SUM(G82:H82)>1, "Review", IF(MAX(B82:F82) =I82, "None", "Review")) -> None
A83: LBA0000020151208ebc800rby | C83: 1 | I83: 1 | J83: =IF(SUM(G83:H83)>1, "Review", IF(MAX(B83:F83) =I83, "None", "Review")) -> None
A84: MDST000020150529eb67000iw | F84: 1 | I84: 1 | J84: =IF(SUM(G84:H84)>1, "Review", IF(MAX(B84:F84) =I84, "None", "Review")) -> None
A85: MDST000020151120ebbk0001r | D85: 1 | I85: 1 | J85: =IF(SUM(G85:H85)>1, "Review", IF(MAX(B85:F85) =I85, "None", "Review")) -> None
A86: MENAFI0020150527eb5q0002t | B86: 1 | I86: 1 | J86: =IF(SUM(G86:H86)>1, "Review", IF(MAX(B86:F86) =I86, "None", "Review")) -> None
A87: MENAFI0020151028ebas0000b | F87: 1 | I87: 1 | J87: =IF(SUM(G87:H87)>1, "Review", IF(MAX(B87:F87) =I87, "None", "Review")) -> None
A88: MHWK000020150612eb6f0001v | D88: 1 | I88: 1 | J88: =IF(SUM(G88:H88)>1, "Review", IF(MAX(B88:F88) =I88, "None", "Review")) -> None
A89: MLFRDDN020151029ebas00007 | D89: 1 | I89: 1 | J89: =IF(SUM(G89:H89)>1, "Review", IF(MAX(B89:F89) =I89, "None", "Review")) -> None
A90: MPRMPR0020150401eb3v00006 | C90: 1 | I90: 1 | J90: =IF(SUM(G90:H90)>1, "Review", IF(MAX(B90:F90) =I90, "None", "Review")) -> None
A91: MPRMPR0020150903eb9200006 | F91: 1 | I91: 1 | J91: =IF(SUM(G91:H91)>1, "Review", IF(MAX(B91:F91) =I91, "None", "Review")) -> None
A92: MTEU000020150618eb6i000dz | B92: 1 | I92: 1 | J92: =IF(SUM(G92:H92)>1, "Review", IF(MAX(B92:F92) =I92, "None", "Review")) -> None
A93: MTEU000020151001eb9u0002t | F93: 1 | I93: 1 | J93: =IF(SUM(G93:H93)>1, "Review", IF(MAX(B93:F93) =I93, "None", "Review")) -> None
A94: MTPW000020150330eb3u0066b | F94: 1 | I94: 1 | J94: =IF(SUM(G94:H94)>1, "Review", IF(MAX(B94:F94) =I94, "None", "Review")) -> None
A95: NANLEB0020150807eb85000q2 | D95: 1 | I95: 1 | J95: =IF(SUM(G95:H95)>1, "Review", IF(MAX(B95:F95) =I95, "None", "Review")) -> None
A96: NJDE000020150819eb8j00037 | B96: 1 | I96: 1 | J96: =IF(SUM(G96:H96)>1, "Review", IF(MAX(B96:F96) =I96, "None", "Review")) -> None
A97: PCWI000020150815eb8f0002y | G97: 1 | I97: 1 | J97: =IF(SUM(G97:H97)>1, "Review", IF(MAX(B97:F97) =I97, "None", "Review")) -> Review
A98: PHBW000020150612eb6f00037 | D98: 1 | I98: 1 | J98: =IF(SUM(G98:H98)>1, "Review", IF(MAX(B98:F98) =I98, "None", "Review")) -> None
A99: PHBW000020150709eb7900005 | F99: 1 | I99: 1 | J99: =IF(SUM(G99:H99)>1, "Review", IF(MAX(B99:F99) =I99, "None", "Review")) -> None
A100: PHBW000020150716eb7g0000t | F100: 1 | I100: 1 | J100: =IF(SUM(G100:H100)>1, "Review", IF(MAX(B100:F100) =I100, "None", "Review")) -> None
A101: PHBW000020151102ebb200089 | F101: 1 | I101: 1 | J101: =IF(SUM(G101:H101)>1, "Review", IF(MAX(B101:F101) =I101, "None", "Review")) -> None
...

Sheet InnovYes_Review
A1: Row Labels | B1: No | C1: No_by_Default | D1: Unsure | E1: Yes | F1: (blank) | G1: Grand Total | H1: Max of Responses | I1: Conflict??
A2: AIWFIE0020150928eb9s0002w | E2: 1 | G2: 1 | H2: =IF(G2=1, 0, MAX(B2:F2)) -> 0 | I2: =IF(G2=1, 0, MAX(B2:F2)-G2) -> 0
A3: AIWINE0020150619eb6k000s1 | E3: 3 | G3: 3 | H3: =IF(G3=1, 0, MAX(B3:F3)) -> 3 | I3: =IF(G3=1, 0, MAX(B3:F3)-G3) -> 0
A4: ALRAQNEG20151001eb9u0002u | B4: 1 | G4: 1 | H4: =IF(G4=1, 0, MAX(B4:F4)) -> 0 | I4: =IF(G4=1, 0, MAX(B4:F4)-G4) -> 0
A5: AMHL000020150313eb3d0000a | C5: 1 | G5: 1 | H5: =IF(G5=1, 0, MAX(B5:F5)) -> 0 | I5: =IF(G5=1, 0, MAX(B5:F5)-G5) -> 0
A6: AMHL000020150513eb5d00005 | E6: 1 | G6: 1 | H6: =IF(G6=1, 0, MAX(B6:F6)) -> 0 | I6: =IF(G6=1, 0, MAX(B6:F6)-G6) -> 0
A7: APRS000020150401eb41008qa | B7: 2 | G7: 2 | H7: =IF(G7=1, 0, MAX(B7:F7)) -> 2 | I7: =IF(G7=1, 0, MAX(B7:F7)-G7) -> 0
A8: APRS000020150513eb5d00d72 | B8: 1 | G8: 1 | H8: =IF(G8=1, 0, MAX(B8:F8)) -> 0 | I8: =IF(G8=1, 0, MAX(B8:F8)-G8) -> 0
A9: APRS000020150819eb8j00030 | E9: 1 | G9: 1 | H9: =IF(G9=1, 0, MAX(B9:F9)) -> 0 | I9: =IF(G9=1, 0, MAX(B9:F9)-G9) -> 0
A10: APRS000020150916eb9g00and | B10: 1 | G10: 1 | H10: =IF(G10=1, 0, MAX(B10:F10)) -> 0 | I10: =IF(G10=1, 0, MAX(B10:F10)-G10) -> 0
A11: APRS000020151116ebbg00a3k | B11: 1 | G11: 1 | H11: =IF(G11=1, 0, MAX(B11:F11)) -> 0 | I11: =IF(G11=1, 0, MAX(B11:F11)-G11) -> 0
A12: APRS000020151119ebbj00acv | B12: 1 | G12: 1 | H12: =IF(G12=1, 0, MAX(B12:F12)) -> 0 | I12: =IF(G12=1, 0, MAX(B12:F12)-G12) -> 0
A13: ATEHEA0020150512eb5c00001 | E13: 1 | G13: 1 | H13: =IF(G13=1, 0, MAX(B13:F13)) -> 0 | I13: =IF(G13=1, 0, MAX(B13:F13)-G13) -> 0
A14: ATPATN0020150601eb610000g | B14: 1 | G14: 1 | H14: =IF(G14=1, 0, MAX(B14:F14)) -> 0 | I14: =IF(G14=1, 0, MAX(B14:F14)-G14) -> 0
A15: ATPHAB0020150119eb1j00006 | C15: 1 | G15: 1 | H15: =IF(G15=1, 0, MAX(B15:F15)) -> 0 | I15: =IF(G15=1, 0, MAX(B15:F15)-G15) -> 0
A16: ATPHAB0020150317eb3h0002t | E16: 1 | G16: 1 | H16: =IF(G16=1, 0, MAX(B16:F16)) -> 0 | I16: =IF(G16=1, 0, MAX(B16:F16)-G16) -> 0
A17: ATPHAB0020150514eb5e0005o | E17: 1 | G17: 1 | H17: =IF(G17=1, 0, MAX(B17:F17)) -> 0 | I17: =IF(G17=1, 0, MAX(B17:F17)-G17) -> 0
A18: ATPHAB0020151019ebaj00036 | B18: 3 | G18: 3 | H18: =IF(G18=1, 0, MAX(B18:F18)) -> 3 | I18: =IF(G18=1, 0, MAX(B18:F18)-G18) -> 0
A19: ATPHAB0020151212ebcc0000d | E19: 2 | G19: 2 | H19: =IF(G19=1, 0, MAX(B19:F19)) -> 2 | I19: =IF(G19=1, 0, MAX(B19:F19)-G19) -> 0
A20: ATPHAM0020150110eb18000bc | B20: 1 | G20: 1 | H20: =IF(G20=1, 0, MAX(B20:F20)) -> 0 | I20: =IF(G20=1, 0, MAX(B20:F20)-G20) -> 0
A21: ATPHAM0020150115eb1c0008g | B21: 1 | G21: 1 | H21: =IF(G21=1, 0, MAX(B21:F21)) -> 0 | I21: =IF(G21=1, 0, MAX(B21:F21)-G21) -> 0
A22: ATPHAM0020150115eb1e000eq | E22: 2 | G22: 2 | H22: =IF(G22=1, 0, MAX(B22:F22)) -> 2 | I22: =IF(G22=1, 0, MAX(B22:F22)-G22) -> 0
A23: ATPHAM0020150121eb1l000e1 | B23: 1 | G23: 1 | H23: =IF(G23=1, 0, MAX(B23:F23)) -> 0 | I23: =IF(G23=1, 0, MAX(B23:F23)-G23) -> 0
A24: ATPHAM0020150204eb220003q | C24: 1 | G24: 1 | H24: =IF(G24=1, 0, MAX(B24:F24)) -> 0 | I24: =IF(G24=1, 0, MAX(B24:F24)-G24) -> 0
A25: ATPHAM0020150205eb24000gz | C25: 1 | G25: 1 | H25: =IF(G25=1, 0, MAX(B25:F25)) -> 0 | I25: =IF(G25=1, 0, MAX(B25:F25)-G25) -> 0
A26: ATPHAM0020150206eb24000eq | B26: 2 | G26: 2 | H26: =IF(G26=1, 0, MAX(B26:F26)) -> 2 | I26: =IF(G26=1, 0, MAX(B26:F26)-G26) -> 0
A27: ATPHAM0020150303eb320005r | E27: 1 | G27: 1 | H27: =IF(G27=1, 0, MAX(B27:F27)) -> 0 | I27: =IF(G27=1, 0, MAX(B27:F27)-G27) -> 0
A28: ATPHAM0020150423eb4k00065 | C28: 2 | G28: 2 | H28: =IF(G28=1, 0, MAX(B28:F28)) -> 2 | I28: =IF(G28=1, 0, MAX(B28:F28)-G28) -> 0
A29: ATPHAM0020150501eb4u0000r | E29: 1 | G29: 1 | H29: =IF(G29=1, 0, MAX(B29:F29)) -> 0 | I29: =IF(G29=1, 0, MAX(B29:F29)-G29) -> 0
A30: ATPHAM0020150515eb5e0007f | B30: 3 | G30: 3 | H30: =IF(G30=1, 0, MAX(B30:F30)) -> 3 | I30: =IF(G30=1, 0, MAX(B30:F30)-G30) -> 0
A31: ATPHAM0020150518eb5d0003g | E31: 2 | G31: 2 | H31: =IF(G31=1, 0, MAX(B31:F31)) -> 2 | I31: =IF(G31=1, 0, MAX(B31:F31)-G31) -> 0
A32: ATPHAM0020150521eb5j0003c | B32: 1 | G32: 1 | H32: =IF(G32=1, 0, MAX(B32:F32)) -> 0 | I32: =IF(G32=1, 0, MAX(B32:F32)-G32) -> 0
A33: ATPHAM0020150527eb5q0006d | C33: 1 | G33: 1 | H33: =IF(G33=1, 0, MAX(B33:F33)) -> 0 | I33: =IF(G33=1, 0, MAX(B33:F33)-G33) -> 0
A34: ATPHAM0020150529eb5r000bt | E34: 1 | G34: 1 | H34: =IF(G34=1, 0, MAX(B34:F34)) -> 0 | I34: =IF(G34=1, 0, MAX(B34:F34)-G34) -> 0
A35: ATPHAM0020150602eb5t00030 | B35: 3 | G35: 3 | H35: =IF(G35=1, 0, MAX(B35:F35)) -> 3 | I35: =IF(G35=1, 0, MAX(B35:F35)-G35) -> 0
A36: ATPHAM0020150627eb6o00098 | C36: 1 | G36: 1 | H36: =IF(G36=1, 0, MAX(B36:F36)) -> 0 | I36: =IF(G36=1, 0, MAX(B36:F36)-G36) -> 0
A37: ATPHAM0020150627eb6p00093 | B37: 1 | G37: 1 | H37: =IF(G37=1, 0, MAX(B37:F37)) -> 0 | I37: =IF(G37=1, 0, MAX(B37:F37)-G37) -> 0
A38: ATPHAM0020150701eb6u0009g | E38: 1 | G38: 1 | H38: =IF(G38=1, 0, MAX(B38:F38)) -> 0 | I38: =IF(G38=1, 0, MAX(B38:F38)-G38) -> 0
A39: ATPHAM0020150724eb7n0006d | B39: 1 | G39: 1 | H39: =IF(G39=1, 0, MAX(B39:F39)) -> 0 | I39: =IF(G39=1, 0, MAX(B39:F39)-G39) -> 0
A40: ATPHAM0020150725eb7o0005u | C40: 1 | G40: 1 | H40: =IF(G40=1, 0, MAX(B40:F40)) -> 0 | I40: =IF(G40=1, 0, MAX(B40:F40)-G40) -> 0
A41: ATPHAM0020150806eb8500065 | C41: 1 | G41: 1 | H41: =IF(G41=1, 0, MAX(B41:F41)) -> 0 | I41: =IF(G41=1, 0, MAX(B41:F41)-G41) -> 0
A42: ATPHAM0020150807eb850002u | B42: 1 | G42: 1 | H42: =IF(G42=1, 0, MAX(B42:F42)) -> 0 | I42: =IF(G42=1, 0, MAX(B42:F42)-G42) -> 0
A43: ATPHAM0020150831eb8u000bn | B43: 2 | G43: 2 | H43: =IF(G43=1, 0, MAX(B43:F43)) -> 2 | I43: =IF(G43=1, 0, MAX(B43:F43)-G43) -> 0
A44: ATPHAM0020150902eb910008k | B44: 1 | G44: 1 | H44: =IF(G44=1, 0, MAX(B44:F44)) -> 0 | I44: =IF(G44=1, 0, MAX(B44:F44)-G44) -> 0
A45: ATPHAM0020150930eb9u000el | B45: 1 | G45: 1 | H45: =IF(G45=1, 0, MAX(B45:F45)) -> 0 | I45: =IF(G45=1, 0, MAX(B45:F45)-G45) -> 0
A46: ATPHAM0020151008eba800090 | B46: 2 | G46: 2 | H46: =IF(G46=1, 0, MAX(B46:F46)) -> 2 | I46: =IF(G46=1, 0, MAX(B46:F46)-G46) -> 0
A47: ATPHAM0020151009eba80002e | C47: 1 | G47: 1 | H47: =IF(G47=1, 0, MAX(B47:F47)) -> 0 | I47: =IF(G47=1, 0, MAX(B47:F47)-G47) -> 0
A48: ATPHAM0020151009eba80008e | E48: 1 | G48: 1 | H48: =IF(G48=1, 0, MAX(B48:F48)) -> 0 | I48: =IF(G48=1, 0, MAX(B48:F48)-G48) -> 0
A49: ATPHAM0020151023ebal000bg | B49: 1 | G49: 1 | H49: =IF(G49=1, 0, MAX(B49:F49)) -> 0 | I49: =IF(G49=1, 0, MAX(B49:F49)-G49) -> 0
A50: ATPHAM0020151030ebat0006f | B50: 3 | G50: 3 | H50: =IF(G50=1, 0, MAX(B50:F50)) -> 3 | I50: =IF(G50=1, 0, MAX(B50:F50)-G50) -> 0
A51: ATPHAM0020151031ebas0008k | C51: 1 | G51: 1 | H51: =IF(G51=1, 0, MAX(B51:F51)) -> 0 | I51: =IF(G51=1, 0, MAX(B51:F51)-G51) -> 0
A52: ATPHAM0020151112ebba0005o | E52: 3 | G52: 3 | H52: =IF(G52=1, 0, MAX(B52:F52)) -> 3 | I52: =IF(G52=1, 0, MAX(B52:F52)-G52) -> 0
A53: ATPHAM0020151112ebbb0000b | B53: 1 | G53: 1 | H53: =IF(G53=1, 0, MAX(B53:F53)) -> 0 | I53: =IF(G53=1, 0, MAX(B53:F53)-G53) -> 0
A54: ATPHAM0020151120ebbj000ec | B54: 1 | G54: 1 | H54: =IF(G54=1, 0, MAX(B54:F54)) -> 0 | I54: =IF(G54=1, 0, MAX(B54:F54)-G54) -> 0
A55: ATPHAM0020151125ebbo0002v | C55: 1 | G55: 1 | H55: =IF(G55=1, 0, MAX(B55:F55)) -> 0 | I55: =IF(G55=1, 0, MAX(B55:F55)-G55) -> 0
A56: ATPHAM0020151215ebce0000h | E56: 1 | G56: 1 | H56: =IF(G56=1, 0, MAX(B56:F56)) -> 0 | I56: =IF(G56=1, 0, MAX(B56:F56)-G56) -> 0
A57: ATPHAM0020151218ebch00039 | B57: 2 | G57: 2 | H57: =IF(G57=1, 0, MAX(B57:F57)) -> 2 | I57: =IF(G57=1, 0, MAX(B57:F57)-G57) -> 0
A58: ATTOPN0020150823eb8l00006 | E58: 1 | G58: 1 | H58: =IF(G58=1, 0, MAX(B58:F58)) -> 0 | I58: =IF(G58=1, 0, MAX(B58:F58)-G58) -> 0
A59: BBPUB00020151112ebbc000ea | B59: 1 | G59: 1 | H59: =IF(G59=1, 0, MAX(B59:F59)) -> 0 | I59: =IF(G59=1, 0, MAX(B59:F59)-G59) -> 0
A60: BHLD000020150518eb5d00011 | E60: 4 | G60: 4 | H60: =IF(G60=1, 0, MAX(B60:F60)) -> 4 | I60: =IF(G60=1, 0, MAX(B60:F60)-G60) -> 0
A61: BHLD000020151023eban0003h | E61: 3 | G61: 3 | H61: =IF(G61=1, 0, MAX(B61:F61)) -> 3 | I61: =IF(G61=1, 0, MAX(B61:F61)-G61) -> 0
A62: BIOELSE020150123eb1g00013 | E62: 1 | G62: 1 | H62: =IF(G62=1, 0, MAX(B62:F62)) -> 0 | I62: =IF(G62=1, 0, MAX(B62:F62)-G62) -> 0
A63: BIOELSE020150407eb3q0000p | B63: 2 | G63: 2 | H63: =IF(G63=1, 0, MAX(B63:F63)) -> 2 | I63: =IF(G63=1, 0, MAX(B63:F63)-G63) -> 0
A64: BIOELSE020150522eb5e0000f | E64: 1 | G64: 1 | H64: =IF(G64=1, 0, MAX(B64:F64)) -> 0 | I64: =IF(G64=1, 0, MAX(B64:F64)-G64) -> 0
A65: BIOELSE020150708eb720000e | C65: 1 | G65: 1 | H65: =IF(G65=1, 0, MAX(B65:F65)) -> 0 | I65: =IF(G65=1, 0, MAX(B65:F65)-G65) -> 0
A66: BIOELSE020150818eb8a00007 | C66: 1 | G66: 1 | H66: =IF(G66=1, 0, MAX(B66:F66)) -> 0 | I66: =IF(G66=1, 0, MAX(B66:F66)-G66) -> 0
A67: BIOELSE020150831eb8o0000e | E67: 2 | G67: 2 | H67: =IF(G67=1, 0, MAX(B67:F67)) -> 2 | I67: =IF(G67=1, 0, MAX(B67:F67)-G67) -> 0
A68: BIOELSE020150903eb8s0001l | B68: 2 | G68: 2 | H68: =IF(G68=1, 0, MAX(B68:F68)) -> 2 | I68: =IF(G68=1, 0, MAX(B68:F68)-G68) -> 0
A69: BIOELSE020150916eb9900019 | B69: 1 | G69: 1 | H69: =IF(G69=1, 0, MAX(B69:F69)) -> 0 | I69: =IF(G69=1, 0, MAX(B69:F69)-G69) -> 0
A70: BIOELSE020150916eb990001u | C70: 1 | G70: 1 | H70: =IF(G70=1, 0, MAX(B70:F70)) -> 0 | I70: =IF(G70=1, 0, MAX(B70:F70)-G70) -> 0
A71: BIOELSE020150930eb9p0000u | B71: 2 | D71: 1 | G71: 3 | H71: =IF(G71=1, 0, MAX(B71:F71)) -> 2 | I71: =IF(G71=1, 0, MAX(B71:F71)-G71) -> -1
A72: BIOELSE020151007eb9u00011 | C72: 1 | G72: 1 | H72: =IF(G72=1, 0, MAX(B72:F72)) -> 0 | I72: =IF(G72=1, 0, MAX(B72:F72)-G72) -> 0
A73: BIOELSE020151117ebb90001r | B73: 3 | E73: 1 | G73: 4 | H73: =IF(G73=1, 0, MAX(B73:F73)) -> 3 | I73: =IF(G73=1, 0, MAX(B73:F73)-G73) -> -1
A74: BIOELSE020160107ebcn0000e | C74: 1 | G74: 1 | H74: =IF(G74=1, 0, MAX(B74:F74)) -> 0 | I74: =IF(G74=1, 0, MAX(B74:F74)-G74) -> 0
A75: BIWK000020150109eb1e001cc | B75: 1 | G75: 1 | H75: =IF(G75=1, 0, MAX(B75:F75)) -> 0 | I75: =IF(G75=1, 0, MAX(B75:F75)-G75) -> 0
A76: BIWK000020150116eb1l000go | B76: 1 | G76: 1 | H76: =IF(G76=1, 0, MAX(B76:F76)) -> 0 | I76: =IF(G76=1, 0, MAX(B76:F76)-G76) -> 0
A77: BIWK000020150213eb2i0014r | C77: 1 | G77: 1 | H77: =IF(G77=1, 0, MAX(B77:F77)) -> 0 | I77: =IF(G77=1, 0, MAX(B77:F77)-G77) -> 0
A78: BIWK000020150306eb3b000hh | B78: 1 | G78: 1 | H78: =IF(G78=1, 0, MAX(B78:F78)) -> 0 | I78: =IF(G78=1, 0, MAX(B78:F78)-G78) -> 0
A79: BIWK000020150417eb4m000ps | B79: 2 | G79: 2 | H79: =IF(G79=1, 0, MAX(B79:F79)) -> 2 | I79: =IF(G79=1, 0, MAX(B79:F79)-G79) -> 0
A80: BIWK000020150515eb5k000no | C80: 2 | G80: 2 | H80: =IF(G80=1, 0, MAX(B80:F80)) -> 2 | I80: =IF(G80=1, 0, MAX(B80:F80)-G80) -> 0
A81: BIWK000020150529eb63000tm | B81: 1 | G81: 1 | H81: =IF(G81=1, 0, MAX(B81:F81)) -> 0 | I81: =IF(G81=1, 0, MAX(B81:F81)-G81) -> 0
A82: BIWK000020150612eb6h00021 | B82: 1 | G82: 1 | H82: =IF(G82=1, 0, MAX(B82:F82)) -> 0 | I82: =IF(G82=1, 0, MAX(B82:F82)-G82) -> 0
A83: BIWK000020150612eb6h0006s | B83: 3 | E83: 1 | G83: 4 | H83: =IF(G83=1, 0, MAX(B83:F83)) -> 3 | I83: =IF(G83=1, 0, MAX(B83:F83)-G83) -> -1
A84: BIWK000020150619eb6o000wo | E84: 1 | G84: 1 | H84: =IF(G84=1, 0, MAX(B84:F84)) -> 0 | I84: =IF(G84=1, 0, MAX(B84:F84)-G84) -> 0
A85: BIWK000020150703eb730008f | B85: 1 | G85: 1 | H85: =IF(G85=1, 0, MAX(B85:F85)) -> 0 | I85: =IF(G85=1, 0, MAX(B85:F85)-G85) -> 0
A86: BIWK000020150709eb79000na | B86: 1 | G86: 1 | H86: =IF(G86=1, 0, MAX(B86:F86)) -> 0 | I86: =IF(G86=1, 0, MAX(B86:F86)-G86) -> 0
A87: BIWK000020150909eb99000fr | B87: 1 | G87: 1 | H87: =IF(G87=1, 0, MAX(B87:F87)) -> 0 | I87: =IF(G87=1, 0, MAX(B87:F87)-G87) -> 0
A88: BIWK000020151216ebcg0004y | E88: 2 | G88: 2 | H88: =IF(G88=1, 0, MAX(B88:F88)) -> 2 | I88: =IF(G88=1, 0, MAX(B88:F88)-G88) -> 0
A89: BNZNGA0020150326eb3q0005m | B89: 3 | G89: 3 | H89: =IF(G89=1, 0, MAX(B89:F89)) -> 3 | I89: =IF(G89=1, 0, MAX(B89:F89)-G89) -> 0
A90: BNZNGA0020150610eb6a000jh | D90: 1 | G90: 1 | H90: =IF(G90=1, 0, MAX(B90:F90)) -> 0 | I90: =IF(G90=1, 0, MAX(B90:F90)-G90) -> 0
A91: BOSBJO0020150319eb3j0008e | E91: 1 | G91: 1 | H91: =IF(G91=1, 0, MAX(B91:F91)) -> 0 | I91: =IF(G91=1, 0, MAX(B91:F91)-G91) -> 0
A92: BOSBJO0020150508eb580002u | E92: 1 | G92: 1 | H92: =IF(G92=1, 0, MAX(B92:F92)) -> 0 | I92: =IF(G92=1, 0, MAX(B92:F92)-G92) -> 0
A93: BOSBJO0020151002eba20008e | B93: 1 | G93: 1 | H93: =IF(G93=1, 0, MAX(B93:F93)) -> 0 | I93: =IF(G93=1, 0, MAX(B93:F93)-G93) -> 0
A94: BSFLVO0020151030ebau0005m | E94: 1 | G94: 1 | H94: =IF(G94=1, 0, MAX(B94:F94)) -> 0 | I94: =IF(G94=1, 0, MAX(B94:F94)-G94) -> 0
A95: BTBW000020150206eb290001v | B95: 1 | G95: 1 | H95: =IF(G95=1, 0, MAX(B95:F95)) -> 0 | I95: =IF(G95=1, 0, MAX(B95:F95)-G95) -> 0
A96: BTBW000020150921eb9l0000h | B96: 1 | E96: 1 | G96: 2 | H96: =IF(G96=1, 0, MAX(B96:F96)) -> 1 | I96: =IF(G96=1, 0, MAX(B96:F96)-G96) -> -1
A97: BUSWRD0020150821eb8l0028m | C97: 1 | G97: 1 | H97: =IF(G97=1, 0, MAX(B97:F97)) -> 0 | I97: =IF(G97=1, 0, MAX(B97:F97)-G97) -> 0
A98: BWR0000020150112eb1c0005a | C98: 1 | G98: 1 | H98: =IF(G98=1, 0, MAX(B98:F98)) -> 0 | I98: =IF(G98=1, 0, MAX(B98:F98)-G98) -> 0
A99: BWR0000020150217eb2h00047 | B99: 1 | G99: 1 | H99: =IF(G99=1, 0, MAX(B99:F99)) -> 0 | I99: =IF(G99=1, 0, MAX(B99:F99)-G99) -> 0
A100: BWR0000020150227eb2r0000g | H100: =IF(G100=1, 0, MAX(B100:F100)) -> 0 | I100: =IF(G100=1, 0, MAX(B100:F100)-G100) -> 0
...

Sheet InnovYes_Full
A1: Unnamed: 0 | B1: Timestamp | C1: ID | D1: Phase Decision | E1: Innov_Decision | F1: Innov_Conflict | G1: Labeling_Freq | H1: Allocation_Freq | I1: Allocation_Freq.y | J1: allocated_labellers | K1: labeler_allocated_once | L1: labeler_default | M1: innovationYes | N1: Phase | O1: Drugname | P1: Companyname | Q1: new2market | R1: new2company | S1: defaultlabel | T1: body | U1: company_codes | V1: company_codes_about | W1: publisher_name | X1: region_codes | Y1: region_of_origin | Z1: snippet | AA1: source_code | AB1: source_name | AC1: subject_code_ns | AD1: subject_codes | AE1: title | AF1: titlebody | AG1: word_count
A2: 1 | B2: 43670.492 | C2: AIWFIE0020150928eb9s0002w | D2: Keep-reviewed | E2: Keep | F2: =VLOOKUP(C2,InnovYes_Review!$A$2:$I$415,9,FALSE) -> 0 | G2: 1 | H2: 1 | I2: 1 | J2: McDonaldSarah | K2: McDonaldSarah | M2: Yes | N2: Approved by FDA but not scheduled to be launched | O2: Elepsia XR | P2: SPARC | Q2: Unsure | R2: Unsure | S2: No | T2: SPARC had earlier received a final approval from US FDA in March 2015 for this product and was evaluating several marketing partners for commercialisation. However, SPARC has now received a CRL from the US FDA rescinding its earlier approval, citing that the compliance status of the manufacturing facility was not acceptable on the date of approval. Elepsia XR is to be manufactured at Sun Pharmaceutical Industries Ltd (SPIL)'s Halol facility. SPIL is working with US FDA in resolving the cGMP deviations at the facility and has taken several corrective measures. | U2: ['snphin', 'spadrn', 'usfda', 'snphin', 'snphin', 'spadrn', 'spadrn', 'usfda', 'usfda'] | V2: ['usfda', 'spadrn', 'snphin'] | W2: India Express Mumbai Limited | X2: ,usa,namz, | Y2: ASIA INDIA SASIAZ | Z2: SPARC had earlier received a final approval from US FDA in March 2015 for this product Sun Pharma Advanced Research Company (SPARC) announced that the US Food and Drug Administration (US FDA) has issued a Complete Response letter (CRL) to its New Drug Application (NDA) for Elepsia XR (Levetiracetam extended-release tablets 1000 mg and 1500 mg). | AA2: AIWFIE | AB2: Financial Express | AC2: TRUE | AD2: ['cappro', 'c22', 'c13', 'ccat', 'ncat', 'nfact', 'nfcpin'] | AE2: US FDA reverses NDA nod for Sun Pharma‚Äôs anti epileptic drug | AF2: US FDA reverses NDA nod for Sun Pharma‚Äôs anti epileptic drugSPARC had earlier received a final approval from US FDA in March 2015 for this product and was evaluating several marketing partners for commercialisation. However, SPARC has now received a CRL from the US FDA rescinding its earlier approval, citing that the compliance status of the manufacturing facility was not acceptable on the date of approval. Elepsia XR is to be manufactured at Sun Pharmaceutical Industries Ltd (SPIL)'s Halol facility. SPIL is working with US FDA in resolving the cGMP deviations at the facility and has taken several corrective measures. | AG2: 166
A3: 2 | B3: 43670.498 | C3: AIWINE0020150619eb6k000s1 | D3: Keep | E3: Keep | F3: =VLOOKUP(C3,InnovYes_Review!$A$2:$I$415,9,FALSE) -> 0 | G3: 3 | H3: 2 | J3: CohenSamantha_KorkmazGizem | M3: Yes | N3: FDA application submission and/or FDA testing | O3: a generic version of Copaxone | P3: Natco | Q3: Yes | R3: No | S3: No | T3: Last year, the US Supreme Court had denied Teva's application for an injunction seeking to prevent the launch of a generic version of Copaxone. The pharma companies involved in the generic forms of Copaxone are Novartis' Sandoz, Momenta Pharmaceuticals, Mylan and Natco Pharma. As per available estimates, the annual sales of Copaxone is about $4.3 billion worldwide and account for more than half of Teva's profit. In 2003, Natco began research to develop a generic version of Copaxone in order to make a cost-effective version of the drug available to patients in India. Later, Natco developed a process for producing copolymer-1 and filed patent applications covering its process. A senior official of Natco said that the firm has submitted all the information to FDA with regard to the generic version of Copaxone, used in the treatment of relapsing-remitting multiple sclerosis. "We have done everything from our side. Once approval comes, we are ready to launch the product. We manufacture the drug and Mylan will market it," the official said. Mylan chief executive officer Heather Bresch, in a separate statement, said: "We have stated all along that the '808 patent on Copaxone is invalid... We continue to remain very confident and look forward to bringing our product to market upon approval from the US Food and Drug Administration." Bresch further said the ruling underscores concerns of Teva's ongoing financial prospects as the Copaxone franchise has historically been its largest and most significant revenue driver. With inputs from Financial Express & PTI The pharma companies involved in the generic forms of Copaxone are Novartis‚Äô Sandoz, Momenta Pharmaceuticals, Mylan and Natco Pharma. | U3: ['mmnpha', 'natpbo', 'mmnpha', 'natpbo', 'natpbo', 'sndoz', 'supus', 'usfda', 'usfda', 'teviy', 'usfda'] | V3: ['usfda', 'teviy', 'natpbo', 'mmnpha'] | W3: India Express Mumbai Limited | X3: ,usa,namz, | Y3: ASIA INDIA SASIAZ | Z3: In a relief to Natco Pharma, the US court of appeals has invalidated Teva's Copaxone patent. This may help generic pharma companies to launch one of the top-selling multiple sclerosis drugs, Copaxone. "The US Court of Appeals for Federal Circuit has again found Teva's US 808 patent for Copaxone to be invalid as indefinite. The company awaits approval from the US Food and Drug Administration (USFDA) to launch the product," said Natco in a filing to the exchanges. | AA3: AIWINE | AB3: Indian Express | AC3: TRUE | AD3: ['cappro', 'c12', 'c133', 'cgymtr', 'cinprp', 'c22', 'c13', 'ccat', 'ncat', 'nfact', 'nfcpex', 'nfcpin'] | AE3: Relief for Natco: US court junks Teva‚Äôs patent on Copaxone | AF3: Relief for Natco: US court junks Teva‚Äôs patent on CopaxoneLast year, the US Supreme Court had denied Teva's application for an injunction seeking to prevent the launch of a generic version of Copaxone. The pharma companies involved in the generic forms of Copaxone are Novartis' Sandoz, Momenta Pharmaceuticals, Mylan and Natco Pharma. As per available estimates, the annual sales of Copaxone is about $4.3 billion worldwide and account for more than half of Teva's profit. In 2003, Natco began research to develop a generic version of Copaxone in order to make a cost-effective version of the drug available to patients in India. Later, Natco developed a process for producing copolymer-1 and filed patent applications covering its process. A senior official of Natco said that the firm has submitted all the information to FDA with regard to the generic version of Copaxone, used in the treatment of relapsing-remitting multiple sclerosis. "We have done everything from our side. Once approval comes, we are ready to launch the product. We manufacture the drug and Mylan will market it," the official said. Mylan chief executive officer Heather Bresch, in a separate statement, said: "We have stated all along that the '808 patent on Copaxone is invalid... We continue to remain very confident and look forward to bringing our product to market upon approval from the US Food and Drug Administration." Bresch further said the ruling underscores concerns of Teva's ongoing financial prospects as the Copaxone franchise has historically been its largest and most significant revenue driver. With inputs from Financial Express & PTI The pharma companies involved in the generic forms of Copaxone are Novartis‚Äô Sandoz, Momenta Pharmaceuticals, Mylan and Natco Pharma. | AG3: 372
A4: 3 | B4: 43670.5 | C4: AIWINE0020150619eb6k000s1 | D4: Throw | E4: Throw | F4: =VLOOKUP(C4,InnovYes_Review!$A$2:$I$415,9,FALSE) -> 0 | G4: 3 | H4: 2 | J4: CohenSamantha_KorkmazGizem | M4: Yes | N4: FDA application submission and/or FDA testing | P4: Novartis, Sandoz, Momenta Pharmaceuticals, Mylan, Natco Pharma | Q4: No | R4: Yes | S4: No | T4: Last year, the US Supreme Court had denied Teva's application for an injunction seeking to prevent the launch of a generic version of Copaxone. The pharma companies involved in the generic forms of Copaxone are Novartis' Sandoz, Momenta Pharmaceuticals, Mylan and Natco Pharma. As per available estimates, the annual sales of Copaxone is about $4.3 billion worldwide and account for more than half of Teva's profit. In 2003, Natco began research to develop a generic version of Copaxone in order to make a cost-effective version of the drug available to patients in India. Later, Natco developed a process for producing copolymer-1 and filed patent applications covering its process. A senior official of Natco said that the firm has submitted all the information to FDA with regard to the generic version of Copaxone, used in the treatment of relapsing-remitting multiple sclerosis. "We have done everything from our side. Once approval comes, we are ready to launch the product. We manufacture the drug and Mylan will market it," the official said. Mylan chief executive officer Heather Bresch, in a separate statement, said: "We have stated all along that the '808 patent on Copaxone is invalid... We continue to remain very confident and look forward to bringing our product to market upon approval from the US Food and Drug Administration." Bresch further said the ruling underscores concerns of Teva's ongoing financial prospects as the Copaxone franchise has historically been its largest and most significant revenue driver. With inputs from Financial Express & PTI The pharma companies involved in the generic forms of Copaxone are Novartis‚Äô Sandoz, Momenta Pharmaceuticals, Mylan and Natco Pharma. | U4: ['mmnpha', 'natpbo', 'mmnpha', 'natpbo', 'natpbo', 'sndoz', 'supus', 'usfda', 'usfda', 'teviy', 'usfda'] | V4: ['usfda', 'teviy', 'natpbo', 'mmnpha'] | W4: India Express Mumbai Limited | X4: ,usa,namz, | Y4: ASIA INDIA SASIAZ | Z4: In a relief to Natco Pharma, the US court of appeals has invalidated Teva's Copaxone patent. This may help generic pharma companies to launch one of the top-selling multiple sclerosis drugs, Copaxone. "The US Court of Appeals for Federal Circuit has again found Teva's US 808 patent for Copaxone to be invalid as indefinite. The company awaits approval from the US Food and Drug Administration (USFDA) to launch the product," said Natco in a filing to the exchanges. | AA4: AIWINE | AB4: Indian Express | AC4: TRUE | AD4: ['cappro', 'c12', 'c133', 'cgymtr', 'cinprp', 'c22', 'c13', 'ccat', 'ncat', 'nfact', 'nfcpex', 'nfcpin'] | AE4: Relief for Natco: US court junks Teva‚Äôs patent on Copaxone | AF4: Relief for Natco: US court junks Teva‚Äôs patent on CopaxoneLast year, the US Supreme Court had denied Teva's application for an injunction seeking to prevent the launch of a generic version of Copaxone. The pharma companies involved in the generic forms of Copaxone are Novartis' Sandoz, Momenta Pharmaceuticals, Mylan and Natco Pharma. As per available estimates, the annual sales of Copaxone is about $4.3 billion worldwide and account for more than half of Teva's profit. In 2003, Natco began research to develop a generic version of Copaxone in order to make a cost-effective version of the drug available to patients in India. Later, Natco developed a process for producing copolymer-1 and filed patent applications covering its process. A senior official of Natco said that the firm has submitted all the information to FDA with regard to the generic version of Copaxone, used in the treatment of relapsing-remitting multiple sclerosis. "We have done everything from our side. Once approval comes, we are ready to launch the product. We manufacture the drug and Mylan will market it," the official said. Mylan chief executive officer Heather Bresch, in a separate statement, said: "We have stated all along that the '808 patent on Copaxone is invalid... We continue to remain very confident and look forward to bringing our product to market upon approval from the US Food and Drug Administration." Bresch further said the ruling underscores concerns of Teva's ongoing financial prospects as the Copaxone franchise has historically been its largest and most significant revenue driver. With inputs from Financial Express & PTI The pharma companies involved in the generic forms of Copaxone are Novartis‚Äô Sandoz, Momenta Pharmaceuticals, Mylan and Natco Pharma. | AG4: 372
A5: 4 | B5: 43670.499 | C5: AIWINE0020150619eb6k000s1 | D5: Throw | E5: Throw | F5: =VLOOKUP(C5,InnovYes_Review!$A$2:$I$415,9,FALSE) -> 0 | G5: 3 | H5: 2 | J5: CohenSamantha_KorkmazGizem | M5: Yes | N5: Available to consumers (has been launched on the market) | O5: Copaxone | P5: Teva | Q5: No | R5: Yes | S5: No | T5: Last year, the US Supreme Court had denied Teva's application for an injunction seeking to prevent the launch of a generic version of Copaxone. The pharma companies involved in the generic forms of Copaxone are Novartis' Sandoz, Momenta Pharmaceuticals, Mylan and Natco Pharma. As per available estimates, the annual sales of Copaxone is about $4.3 billion worldwide and account for more than half of Teva's profit. In 2003, Natco began research to develop a generic version of Copaxone in order to make a cost-effective version of the drug available to patients in India. Later, Natco developed a process for producing copolymer-1 and filed patent applications covering its process. A senior official of Natco said that the firm has submitted all the information to FDA with regard to the generic version of Copaxone, used in the treatment of relapsing-remitting multiple sclerosis. "We have done everything from our side. Once approval comes, we are ready to launch the product. We manufacture the drug and Mylan will market it," the official said. Mylan chief executive officer Heather Bresch, in a separate statement, said: "We have stated all along that the '808 patent on Copaxone is invalid... We continue to remain very confident and look forward to bringing our product to market upon approval from the US Food and Drug Administration." Bresch further said the ruling underscores concerns of Teva's ongoing financial prospects as the Copaxone franchise has historically been its largest and most significant revenue driver. With inputs from Financial Express & PTI The pharma companies involved in the generic forms of Copaxone are Novartis‚Äô Sandoz, Momenta Pharmaceuticals, Mylan and Natco Pharma. | U5: ['mmnpha', 'natpbo', 'mmnpha', 'natpbo', 'natpbo', 'sndoz', 'supus', 'usfda', 'usfda', 'teviy', 'usfda'] | V5: ['usfda', 'teviy', 'natpbo', 'mmnpha'] | W5: India Express Mumbai Limited | X5: ,usa,namz, | Y5: ASIA INDIA SASIAZ | Z5: In a relief to Natco Pharma, the US court of appeals has invalidated Teva's Copaxone patent. This may help generic pharma companies to launch one of the top-selling multiple sclerosis drugs, Copaxone. "The US Court of Appeals for Federal Circuit has again found Teva's US 808 patent for Copaxone to be invalid as indefinite. The company awaits approval from the US Food and Drug Administration (USFDA) to launch the product," said Natco in a filing to the exchanges. | AA5: AIWINE | AB5: Indian Express | AC5: TRUE | AD5: ['cappro', 'c12', 'c133', 'cgymtr', 'cinprp', 'c22', 'c13', 'ccat', 'ncat', 'nfact', 'nfcpex', 'nfcpin'] | AE5: Relief for Natco: US court junks Teva‚Äôs patent on Copaxone | AF5: Relief for Natco: US court junks Teva‚Äôs patent on CopaxoneLast year, the US Supreme Court had denied Teva's application for an injunction seeking to prevent the launch of a generic version of Copaxone. The pharma companies involved in the generic forms of Copaxone are Novartis' Sandoz, Momenta Pharmaceuticals, Mylan and Natco Pharma. As per available estimates, the annual sales of Copaxone is about $4.3 billion worldwide and account for more than half of Teva's profit. In 2003, Natco began research to develop a generic version of Copaxone in order to make a cost-effective version of the drug available to patients in India. Later, Natco developed a process for producing copolymer-1 and filed patent applications covering its process. A senior official of Natco said that the firm has submitted all the information to FDA with regard to the generic version of Copaxone, used in the treatment of relapsing-remitting multiple sclerosis. "We have done everything from our side. Once approval comes, we are ready to launch the product. We manufacture the drug and Mylan will market it," the official said. Mylan chief executive officer Heather Bresch, in a separate statement, said: "We have stated all along that the '808 patent on Copaxone is invalid... We continue to remain very confident and look forward to bringing our product to market upon approval from the US Food and Drug Administration." Bresch further said the ruling underscores concerns of Teva's ongoing financial prospects as the Copaxone franchise has historically been its largest and most significant revenue driver. With inputs from Financial Express & PTI The pharma companies involved in the generic forms of Copaxone are Novartis‚Äô Sandoz, Momenta Pharmaceuticals, Mylan and Natco Pharma. | AG5: 372
A6: 5 | B6: 43670.476 | C6: ALRAQNEG20151001eb9u0002u | D6: None | E6: Keep | F6: =VLOOKUP(C6,InnovYes_Review!$A$2:$I$415,9,FALSE) -> 0 | G6: 1 | H6: 2 | J6: Extra2_KattampallilNeil | M6: No | S6: No | T6: The company said it was "evaluating several marketing partners for commercialisation. However SPARC has now received a CRL (complete response letter) from the USFDA rescinding its earlier approval, citing that the compliance status of the manufacturing facility was not acceptable on the date of approval." | U6: ['snphin', 'spadrn', 'usfda', 'snphin', 'spadrn', 'spadrn', 'usfda', 'usfda'] | V6: ['usfda', 'spadrn', 'snphin'] | W6: All Iraq News Agency | X6: ,usa,india,asiaz,bric,devgcoz,dvpcoz,indsubz,namz,sasiaz, | Y6: ASIA GULFST IRAQ MEASTZ WASIAZ | Z6: After the US Food and Drug Administration (US FDA) revoked an approval granted to the company, citing production quality problems at its manufacturing site, stocks of Dilip Shanghvi-led Sun Pharma and its arm SPARC ( Sun Pharma Advanced Research Company) fell on Monday. SPARC had won the final approval for releasing a drug, Elepsia XR, from the US FDA in March. | AA6: ALRAQNEG | AB6: All Iraq News Agency | AC6: TRUE | AD6: ['cappro', 'c13', 'c22', 'ccat', 'ncat', 'nfact', 'nfcpin'] | AE6: India : US FDA revokes approval granted to SPARC, SUN PHARMA | AF6: India : US FDA revokes approval granted to SPARC, SUN PHARMAThe company said it was "evaluating several marketing partners for commercialisation. However SPARC has now received a CRL (complete response letter) from the USFDA rescinding its earlier approval, citing that the compliance status of the manufacturing facility was not acceptable on the date of approval." | AG6: 116
A7: 504 | C7: AMHL000020150313eb3d0000a | D7: None | E7: Keep | F7: =VLOOKUP(C7,InnovYes_Review!$A$2:$I$415,9,FALSE) -> 0 | G7: 1 | H7: 1 | I7: 1 | J7: PristavecTeja | K7: PristavecTeja | L7: PristavecTeja | M7: No_by_Default | S7: Yes | T7: The report found significant variation in predicted survival rates: * Pancreatectomy predicted survival rates ranged from 81% to 100%, with a quality benchmark of 91.3%; * Esophagectomy predicted survival rates ranged from 88% to 98%, with a quality benchmark of 91.7%; * Aortic valve replacement predicted survival rates ranged from 92% to 97%, with a quality benchmark of 95.6%; and * Abdominal aortic aneurysm repair predicted survival rates ranged from 86% to 99%, with a quality benchmark of 97.3%. Harvard School of Public Health Professor Ashish Jha said, "When it comes to major surgery, it's hard to think of an outcome more important than whether you live or die," adding, "It's amazing there is such variability in mortality from these common surgeries, and patients should know that." Leapfrog spokesperson Erica Mobley said the data show that a patient's choice of hospital "can mean the difference between life and death," noting hospitals with lower survival rates could learn from high-performing hospitals. Mobley added, "Hospitals need to be following best practices for the performance of these procedures" and making sure surgeons and staff are well-trained and well-equipped to handle these types of surgeries. Leapfrog warned that while the numbers can provide a helpful guide for patients deciding where to undergo a procedure, the data should be used with caution because survival rates also vary significantly based on the operating physician (Begley, Reuters, 3/12). -- compiled by Clare Rizer | U7: ['lpfrgp', 'lpfrgp'] | V7: ['lpfrgp'] | W7: The Advisory Board Company/American Health Line | X7: ,usa,namz, | Y7: NAMZ USA | Z7: The survival chances for high-risk surgeries can vary by up to 23% depending on the hospital a patient chooses, according to a new analysis from The Leapfrog Group, Reuters reports. For the report, Leapfrog gathered 2013 data from 1,500 hospitals on four high-risk surgeries: pancreatectomy, esophagectomy, replacement of the heart's aortic valve and abdominal aortic aneurysm repair. The organization analyzed the mortality rates for the procedures performed and then tailored the numbers to determine a "predicted survival" estimate for each procedure at any given facility. | AA7: AMHL | AB7: American Health Line | AC7: FALSE | AD7: ['nabst', 'ncat'] | AE7: Analysis: Chance of Survival in High-Risk Surgeries Varies Widely by Hospital | AF7: Analysis: Chance of Survival in High-Risk Surgeries Varies Widely by HospitalThe report found significant variation in predicted survival rates: * Pancreatectomy predicted survival rates ranged from 81% to 100%, with a quality benchmark of 91.3%; * Esophagectomy predicted survival rates ranged from 88% to 98%, with a quality benchmark of 91.7%; * Aortic valve replacement predicted survival rates ranged from 92% to 97%, with a quality benchmark of 95.6%; and * Abdominal aortic aneurysm repair predicted survival rates ranged from 86% to 99%, with a quality benchmark of 97.3%. Harvard School of Public Health Professor Ashish Jha said, "When it comes to major surgery, it's hard to think of an outcome more important than whether you live or die," adding, "It's amazing there is such variability in mortality from these common surgeries, and patients should know that." Leapfrog spokesperson Erica Mobley said the data show that a patient's choice of hospital "can mean the difference between life and death," noting hospitals with lower survival rates could learn from high-performing hospitals. Mobley added, "Hospitals need to be following best practices for the performance of these procedures" and making sure surgeons and staff are well-trained and well-equipped to handle these types of surgeries. Leapfrog warned that while the numbers can provide a helpful guide for patients deciding where to undergo a procedure, the data should be used with caution because survival rates also vary significantly based on the operating physician (Begley, Reuters, 3/12). -- compiled by Clare Rizer | AG7: 343
A8: 6 | B8: 43670.482 | C8: AMHL000020150513eb5d00005 | D8: Keep | E8: Keep | F8: =VLOOKUP(C8,InnovYes_Review!$A$2:$I$415,9,FALSE) -> 0 | G8: 1 | H8: 1 | I8: 1 | J8: SawhneyRaghav | K8: SawhneyRaghav | M8: Yes | N8: Undergoing clinical trials | O8: Cimavax | P8: Center for Molecular Immunology | Q8: Yes | R8: Unsure | S8: No | T8: In December 2014, President Obama began to restore diplomatic ties with Cuba (Miller, "Morning Mix," Washington Post, 5/12). Obama has lifted some trade restrictions against medical and research equipment. However, Congress would need to lift the trade embargo against Cuba -- which has been in place for 55 years -- in order to increase collaborative research between the two countries, according to Wired. CDC: Two-Thirds of Individuals With Cancer Live at Least Five Years > Details of Lung Cancer Vaccine The lung cancer vaccine, called Cimavax, was developed more than 25 years ago by Cuba's Center for Molecular Immunology. Cuba's Ministry of Health then released it to the public at no cost in 2011, with each shot of the vaccine costing the government about $1 (Wired, 5/11). Cimavax does not cure or prevent lung cancer ("Morning Mix," Washington Post, 5/12). Rather than combatting tumors directly, it works to keep tumors from metastasizing and growing, which can make a late-stage growth more manageable. A 2008 Phase II trial of Cimavax found that individuals with lung cancer who received the medication lived four to six months longer on average than those who did not. Agreement Details As part of the agreement, CMI agreed to provide Roswell Park with all documentation about Cimavax necessary for an FDA application. Roswell Park CEO Candace Johnson said she would like to receive approval to begin testing the vaccine in the U.S. in the next six to eight months and begin clinical trials in one year. Roswell Park officials said they intend to evaluate whether the vaccine could be used as a preventive measure. Cuba had not tested Cimavax's preventive capabilities mostly because of financial reasons, according to Wired (Wired, 5/11). -- compiled by Joshua Zeitlin | U8: ['cdcfui', 'cmpuht', 'rswlpk', 'rswlpk', 'usfda', 'wpostn', 'wpostn'] | V8: [] | W8: The Advisory Board Company/American Health Line | X8: ,cuba,usa,caribz,dvpcoz,lamz,namz, | Y8: NAMZ USA | Z8: New York-based Roswell Park Cancer Institute and Cuba's Center for Molecular Immunology last month finalized an agreement to bring a lung cancer vaccine to the U.S., setting it up for potential FDA approval, Wired reports (Patel, Wired, 5/11). BACKGROUND > | AA8: AMHL | AB8: American Health Line | AC8: TRUE | AD8: ['nabst', 'c13', 'gcancr', 'gimmu', 'glungc', 'cappro', 'chcpol', 'c22', 'ccat', 'gcat', 'ghea', 'gmed', 'gtrea', 'ncat', 'nfact', 'nfcpin'] | AE8: Normalizing Relations With Cuba Could Bring Lung Cancer Vaccine to U.S. | AF8: Normalizing Relations With Cuba Could Bring Lung Cancer Vaccine to U.S.In December 2014, President Obama began to restore diplomatic ties with Cuba (Miller, "Morning Mix," Washington Post, 5/12). Obama has lifted some trade restrictions against medical and research equipment. However, Congress would need to lift the trade embargo against Cuba -- which has been in place for 55 years -- in order to increase collaborative research between the two countries, according to Wired. CDC: Two-Thirds of Individuals With Cancer Live at Least Five Years > Details of Lung Cancer Vaccine The lung cancer vaccine, called Cimavax, was developed more than 25 years ago by Cuba's Center for Molecular Immunology. Cuba's Ministry of Health then released it to the public at no cost in 2011, with each shot of the vaccine costing the government about $1 (Wired, 5/11). Cimavax does not cure or prevent lung cancer ("Morning Mix," Washington Post, 5/12). Rather than combatting tumors directly, it works to keep tumors from metastasizing and growing, which can make a late-stage growth more manageable. A 2008 Phase II trial of Cimavax found that individuals with lung cancer who received the medication lived four to six months longer on average than those who did not. Agreement Details As part of the agreement, CMI agreed to provide Roswell Park with all documentation about Cimavax necessary for an FDA application. Roswell Park CEO Candace Johnson said she would like to receive approval to begin testing the vaccine in the U.S. in the next six to eight months and begin clinical trials in one year. Roswell Park officials said they intend to evaluate whether the vaccine could be used as a preventive measure. Cuba had not tested Cimavax's preventive capabilities mostly because of financial reasons, according to Wired (Wired, 5/11). -- compiled by Joshua Zeitlin | AG8: 350
A9: 7 | B9: 43670.582 | C9: APRS000020150401eb41008qa | D9: None | E9: Keep | F9: =VLOOKUP(C9,InnovYes_Review!$A$2:$I$415,9,FALSE) -> 0 | G9: 2 | H9: 2 | J9: NevilleQuinton_McDonaldSarah | M9: No | S9: No | T9: CLOSING MOST ACTIVE STOCKS NEW YORK (AP) ‚Äî Thursday's prices for NYSE listed most active stocks: SalesHighLowCloseChg AKSteel 62480 4.48 4.28 4.45+.04 AT&TInc 1.88 191398 33.23 32.82 33.13+.24 AbbVie 2.04f 82730 57.81 56.90 57.01‚Äî.09 Alcoa .12 229316 13.28 12.79 13.14+.14 Alibaban 197105 83.00 81.25 82.28‚Äî.08 Altria 2.08 89727 51.29 50.36 51.19+.89 Ambev .24e 223981 6.10 5.94 6.04+.12 AmExp 1.04 56372 79.77 78.57 79.70+.77 ArchDan 1.12f 58135 48.34 47.34 47.35‚Äî.08 Avon .24 63540 7.98 7.82 7.97+.12 Axaltan 124504 28.24 27.70 27.93‚Äî.71 BcoBrads .42e 76110 9.98 9.73 9.87+.28 BkofAm .20 492903 15.62 15.43 15.54+.13 BiPVixST 312181 25.52 24.97 25.06‚Äî.46 BarrickG .20 113083 12.11 11.71 11.88‚Äî.13 BostonSci 55462 17.83 17.54 17.72+.07 CBSB .60 94570 61.49 59.11 61.16+1.54 CNOFincl .24 110977 18.08 17.55 17.79+.66 CSX .64 92418 33.40 32.94 33.32‚Äî.13 CalifResn .04 77919 8.50 7.98 8.18+.23 CarMax 88765 75.40 71.97 74.73+6.34 Cemex .52t 80435 9.85 9.36 9.73+.29 ChesEng .35 319448 14.69 14.20 14.59+.24 Chimera .38f 76225 3.16 3.12 3.14 Citigroup .04 137424 52.22 51.59 51.86+.24 CitizFinn .40 60067 24.68 24.25 24.62+.26 CocaCola 1.32f 142674 40.87 40.48 40.68 ConocoPhil 2.92 58790 63.41 62.57 63.18+.16 ContlRess 70611 47.40 45.19 46.04+.38 Corning .48f 91026 22.44 22.07 22.32+.07 CSVInvNG 100667 7.94 7.03 7.11‚Äî.95 CSVLgNGs 413546 2.45 2.21 2.43+.26 CSVLgCrde 690598 2.52 2.25 2.45‚Äî.01 DeltaAir .36 152653 43.37 42.25 42.25‚Äî1.01 DenburyR .25 153411 7.85 7.31 7.84+.46 DBXEafeEq 1.37e 72214 30.31 30.15 30.28+.11 DxGldBull 201745 11.12 10.13 10.55‚Äî.35 DrxSCBear 92483 10.13 9.90 10.03‚Äî.08 DirGMBear .95e 59867 10.90 9.94 10.44+.39 DirDGldBr 73975 17.25 15.79 16.63+.53 DowChm 1.68 60468 48.39 47.53 48.24+.34 DuPont 1.88 87262 71.65 70.71 71.39+.41 EMCCp .46 158376 25.71 25.42 25.53+.06 EldorGldg .02e 60111 4.94 4.76 4.85‚Äî.11 EmersonEl 1.88 58899 56.26 55.50 55.54‚Äî.35 EnCanag .28 73290 11.59 11.18 11.47+.17 Exelon 1.24 72506 33.58 32.88 33.38+.53 ExxonMbl 2.76 111997 84.94 83.85 84.30‚Äî.16 FordM .60f 157587 16.04 15.85 16.03+.12 FrptMcM .20m 138747 19.07 18.74 19.00+.03 GenElec .92 286136 25.00 24.70 24.94+.10 GenMotors 1.20 163863 36.73 36.33 36.50‚Äî.24 Genworth 152103 7.94 7.29 7.76+.43 Goldcrpg .60 58759 19.19 18.52 18.85‚Äî.16 Hallibrtn .72 110919 44.32 43.49 43.96+.14 HewlettP .64 83904 31.75 31.22 31.40+.11 Hilton 70949 29.71 29.30 29.36+.08 HostHotls .80a 56946 20.58 20.21 20.49+.23 ICICIBks .15e 68141 10.77 10.59 10.69+.07 iShBrazil 1.38e 247466 33.37 32.63 33.24+.99 iShGerm .63e 55692 30.39 30.18 30.33+.23 iShJapan .15e 242135 12.74 12.63 12.69+.11 iSTaiwn .29e 72967 16.08 15.93 16.07+.33 iShSilver 55952 16.13 15.88 16.02‚Äî.21 iShChinaLC 1.04e 155255 45.77 45.34 45.66+.46 iShEMkts .88e 576820 41.34 40.90 41.24+.61 iSh20yrT 3.31e 60332 131.97 130.61 130.73‚Äî1.40 iSEafe 2.26e 154321 65.24 64.93 65.19+.56 iShR2K 1.59e 217897 125.26 124.29 124.65+.23 iShREst 2.70e 90132 80.08 79.07 79.84+.53 IntlGame .44 134257 17.93 17.73 17.77+.22 ItauUnibH .41e 188088 11.87 11.60 11.77+.32 JPMorgCh 1.60 124551 60.70 60.00 60.52+.57 JohnJn 2.80 59482 99.99 98.89 99.64+.49 Keycorp .26 79557 14.28 14.10 14.25+.09 KindMorg 1.80f 61729 42.00 41.56 41.72‚Äî.20 Kinrossg 125203 2.38 2.27 2.32‚Äî.04 LaredoPet 66017 14.34 13.60 14.30+.90 Lorillard 2.64f 111880 69.82 68.78 69.25+1.86 LumberLiq 114630 35.18 32.20 33.20+.19 MGM Rsts 94815 21.38 20.73 21.34+.46 Macys 1.25 98604 68.48 65.29 67.85+2.40 MarathnO .84 85537 27.28 26.39 27.07+.43 MVJrGold 100379 24.14 23.38 23.70‚Äî.39 MktVGold .12e 408875 19.35 18.76 18.99‚Äî.22 MVOilSvc .86e 83470 34.47 33.71 34.29+.32 MktVRus .64e 201098 18.43 17.98 18.40+.68 Masco .36 55658 26.74 25.95 26.62+.55 McDrmInt 62712 4.25 3.91 4.18+.24 McDnlds 3.40 65436 96.24 94.71 95.83‚Äî.46 Merck 1.80 75009 57.45 56.85 57.10+.24 MorgStan .40 60449 36.20 35.79 36.06+.09 MotrlaSolu 1.36 80587 67.46 61.15 62.51‚Äî4.16 NRGEgy .58f 58856 24.30 23.66 23.99+.39 Nabors .24 97096 14.62 13.90 14.07‚Äî.01 NBGreece 62925 1.25 1.22 1.23‚Äî.01 NewmtM .10 64496 22.91 22.15 22.34‚Äî.38 NobleCorp 1.50 72848 14.81 14.21 14.76+.31 NokiaCp .51e 80801 7.70 7.63 7.65+.10 OasisPet 76635 15.28 14.46 14.94+.25 Oracle .60f x110967 43.11 42.48 42.62‚Äî.17 PeabdyE .01m 106729 4.96 4.71 4.87+.12 Penney 200476 9.20 8.82 9.13+.23 PetrbrsA .85e 117912 6.82 6.50 6.80+.39 Petrobras .46e 439239 6.79 6.41 6.76+.41 Pfizer 1.12f 248144 34.63 34.22 34.38+.05 PUltVixST 188107 14.98 14.34 14.41‚Äî.59 PrUltCrude 261328 7.48 6.95 7.35‚Äî.03 ProctGam 2.57 60183 82.59 81.92 82.43+.11 ProUShSP 73094 21.55 21.23 21.34‚Äî.15 RegionsFn .20 191427 9.64 9.42 9.58+.12 RiteAid 487525 9.07 8.62 8.79+.22 S&P500ETF 3.94e 767134 206.98 205.40 206.44+.74 SpdrLehHY 2.81e 66759 39.15 39.09 39.15+.02 SpdrOGEx .69e 108836 51.09 49.56 50.81+.64 SandRdge 87992 1.83 1.75 1.82+.04 Schlmbrg 2f 60154 85.43 83.89 84.39+.11 SchwUSDiv 1.06e 71223 39.43 39.16 39.26+.07 Schwab .24 68010 30.09 29.66 30.01+.08 SeadrillLtd 92055 9.70 9.30 9.66+.31 SwstAirl .24 82644 43.82 42.69 42.86‚Äî.59 SwstnEngy 96623 24.12 22.72 24.04+1.18 Sprint 170932 4.87 4.72 4.85+.12 SPHlthC .90e 73503 72.32 71.64 71.99+.22 SPEngy 1.94e 137005 78.17 77.02 77.72+.16 SPDRFncl .41e 204868 24.25 24.03 24.21+.12 SPInds 1.07e 65588 55.76 55.25 55.43+.03 SPUtil 1.51e 110431 44.75 44.35 44.55+.08 Suncorg 1.12 81532 30.95 29.47 30.77+1.25 SunEdison 97821 25.86 24.90 25.15+.05 TaiwSemi .50e 123395 23.83 23.58 23.69+.46 TalismEg .27 64328 7.73 7.67 7.70+.02 Transocn 3 79321 15.05 14.44 14.99+.27 Twitter 132055 50.95 49.88 50.42‚Äî.05 UtdContl 73178 64.54 61.73 61.88‚Äî2.13 USNGas 89560 13.66 13.16 13.60+.50 USOilFd 348980 17.68 17.06 17.56‚Äî.02 ValeSA .60e 241634 5.79 5.45 5.76+.18 ValeSApf .60e 209042 4.96 4.57 4.94+.17 ValeroE 1.60f 130302 63.65 59.31 59.80‚Äî3.65 VangEmg 1.13e 80851 42.14 41.70 42.06+.64 VerizonCm 2.20 132244 49.60 48.86 49.47+.55 Vipshops 62844 29.44 28.50 29.11‚Äî.20 WalMart 1.96f 57620 81.32 80.55 80.73+.02 WeathfIntl 72069 13.13 12.66 12.91+.21 WellsFargo 1.40 132384 54.48 53.82 54.37+.43 WstnUnion .62f 88110 21.04 20.48 20.91+.35 WhitingPet 111110 33.56 31.62 32.81+.76 Xerox .28f 73654 12.84 12.68 12.77+.10 Yamanag .06 61317 3.87 3.67 3.74‚Äî.06 | U9: ['abvbba', 'almam', 'carmax', 'ccred', 'corn', 'csxc', 'dupnt', 'genwth', 'memcem', 'orcle', 'petbrs', 'pfiz', 'phelc', 'philm', 'soccor', 'twnit', 'wlmrt', 'xrxco', 'soccor', 'pfiz'] | V9: ['pfiz', 'soccor'] | W9: The Associated Press | X9: ,usa,namz, | Y9: NAMZ USA | AA9: APRS | AB9: Associated Press Newswires | AC9: FALSE | AD9: ['nrmf', 'ncat', 'nfact', 'nfce', 'niwe', 'ntab', 'm11', 'mcat'] | AE9: BC-150-actives-f | AF9: BC-150-actives-f CLOSING MOST ACTIVE STOCKS NEW YORK (AP) ‚Äî Thursday's prices for NYSE listed most active stocks: SalesHighLowCloseChg AKSteel 62480 4.48 4.28 4.45+.04 AT&TInc 1.88 191398 33.23 32.82 33.13+.24 AbbVie 2.04f 82730 57.81 56.90 57.01‚Äî.09 Alcoa .12 229316 13.28 12.79 13.14+.14 Alibaban 197105 83.00 81.25 82.28‚Äî.08 Altria 2.08 89727 51.29 50.36 51.19+.89 Ambev .24e 223981 6.10 5.94 6.04+.12 AmExp 1.04 56372 79.77 78.57 79.70+.77 ArchDan 1.12f 58135 48.34 47.34 47.35‚Äî.08 Avon .24 63540 7.98 7.82 7.97+.12 Axaltan 124504 28.24 27.70 27.93‚Äî.71 BcoBrads .42e 76110 9.98 9.73 9.87+.28 BkofAm .20 492903 15.62 15.43 15.54+.13 BiPVixST 312181 25.52 24.97 25.06‚Äî.46 BarrickG .20 113083 12.11 11.71 11.88‚Äî.13 BostonSci 55462 17.83 17.54 17.72+.07 CBSB .60 94570 61.49 59.11 61.16+1.54 CNOFincl .24 110977 18.08 17.55 17.79+.66 CSX .64 92418 33.40 32.94 33.32‚Äî.13 CalifResn .04 77919 8.50 7.98 8.18+.23 CarMax 88765 75.40 71.97 74.73+6.34 Cemex .52t 80435 9.85 9.36 9.73+.29 ChesEng .35 319448 14.69 14.20 14.59+.24 Chimera .38f 76225 3.16 3.12 3.14 Citigroup .04 137424 52.22 51.59 51.86+.24 CitizFinn .40 60067 24.68 24.25 24.62+.26 CocaCola 1.32f 142674 40.87 40.48 40.68 ConocoPhil 2.92 58790 63.41 62.57 63.18+.16 ContlRess 70611 47.40 45.19 46.04+.38 Corning .48f 91026 22.44 22.07 22.32+.07 CSVInvNG 100667 7.94 7.03 7.11‚Äî.95 CSVLgNGs 413546 2.45 2.21 2.43+.26 CSVLgCrde 690598 2.52 2.25 2.45‚Äî.01 DeltaAir .36 152653 43.37 42.25 42.25‚Äî1.01 DenburyR .25 153411 7.85 7.31 7.84+.46 DBXEafeEq 1.37e 72214 30.31 30.15 30.28+.11 DxGldBull 201745 11.12 10.13 10.55‚Äî.35 DrxSCBear 92483 10.13 9.90 10.03‚Äî.08 DirGMBear .95e 59867 10.90 9.94 10.44+.39 DirDGldBr 73975 17.25 15.79 16.63+.53 DowChm 1.68 60468 48.39 47.53 48.24+.34 DuPont 1.88 87262 71.65 70.71 71.39+.41 EMCCp .46 158376 25.71 25.42 25.53+.06 EldorGldg .02e 60111 4.94 4.76 4.85‚Äî.11 EmersonEl 1.88 58899 56.26 55.50 55.54‚Äî.35 EnCanag .28 73290 11.59 11.18 11.47+.17 Exelon 1.24 72506 33.58 32.88 33.38+.53 ExxonMbl 2.76 111997 84.94 83.85 84.30‚Äî.16 FordM .60f 157587 16.04 15.85 16.03+.12 FrptMcM .20m 138747 19.07 18.74 19.00+.03 GenElec .92 286136 25.00 24.70 24.94+.10 GenMotors 1.20 163863 36.73 36.33 36.50‚Äî.24 Genworth 152103 7.94 7.29 7.76+.43 Goldcrpg .60 58759 19.19 18.52 18.85‚Äî.16 Hallibrtn .72 110919 44.32 43.49 43.96+.14 HewlettP .64 83904 31.75 31.22 31.40+.11 Hilton 70949 29.71 29.30 29.36+.08 HostHotls .80a 56946 20.58 20.21 20.49+.23 ICICIBks .15e 68141 10.77 10.59 10.69+.07 iShBrazil 1.38e 247466 33.37 32.63 33.24+.99 iShGerm .63e 55692 30.39 30.18 30.33+.23 iShJapan .15e 242135 12.74 12.63 12.69+.11 iSTaiwn .29e 72967 16.08 15.93 16.07+.33 iShSilver 55952 16.13 15.88 16.02‚Äî.21 iShChinaLC 1.04e 155255 45.77 45.34 45.66+.46 iShEMkts .88e 576820 41.34 40.90 41.24+.61 iSh20yrT 3.31e 60332 131.97 130.61 130.73‚Äî1.40 iSEafe 2.26e 154321 65.24 64.93 65.19+.56 iShR2K 1.59e 217897 125.26 124.29 124.65+.23 iShREst 2.70e 90132 80.08 79.07 79.84+.53 IntlGame .44 134257 17.93 17.73 17.77+.22 ItauUnibH .41e 188088 11.87 11.60 11.77+.32 JPMorgCh 1.60 124551 60.70 60.00 60.52+.57 JohnJn 2.80 59482 99.99 98.89 99.64+.49 Keycorp .26 79557 14.28 14.10 14.25+.09 KindMorg 1.80f 61729 42.00 41.56 41.72‚Äî.20 Kinrossg 125203 2.38 2.27 2.32‚Äî.04 LaredoPet 66017 14.34 13.60 14.30+.90 Lorillard 2.64f 111880 69.82 68.78 69.25+1.86 LumberLiq 114630 35.18 32.20 33.20+.19 MGM Rsts 94815 21.38 20.73 21.34+.46 Macys 1.25 98604 68.48 65.29 67.85+2.40 MarathnO .84 85537 27.28 26.39 27.07+.43 MVJrGold 100379 24.14 23.38 23.70‚Äî.39 MktVGold .12e 408875 19.35 18.76 18.99‚Äî.22 MVOilSvc .86e 83470 34.47 33.71 34.29+.32 MktVRus .64e 201098 18.43 17.98 18.40+.68 Masco .36 55658 26.74 25.95 26.62+.55 McDrmInt 62712 4.25 3.91 4.18+.24 McDnlds 3.40 65436 96.24 94.71 95.83‚Äî.46 Merck 1.80 75009 57.45 56.85 57.10+.24 MorgStan .40 60449 36.20 35.79 36.06+.09 MotrlaSolu 1.36 80587 67.46 61.15 62.51‚Äî4.16 NRGEgy .58f 58856 24.30 23.66 23.99+.39 Nabors .24 97096 14.62 13.90 14.07‚Äî.01 NBGreece 62925 1.25 1.22 1.23‚Äî.01 NewmtM .10 64496 22.91 22.15 22.34‚Äî.38 NobleCorp 1.50 72848 14.81 14.21 14.76+.31 NokiaCp .51e 80801 7.70 7.63 7.65+.10 OasisPet 76635 15.28 14.46 14.94+.25 Oracle .60f x110967 43.11 42.48 42.62‚Äî.17 PeabdyE .01m 106729 4.96 4.71 4.87+.12 Penney 200476 9.20 8.82 9.13+.23 PetrbrsA .85e 117912 6.82 6.50 6.80+.39 Petrobras .46e 439239 6.79 6.41 6.76+.41 Pfizer 1.12f 248144 34.63 34.22 34.38+.05 PUltVixST 188107 14.98 14.34 14.41‚Äî.59 PrUltCrude 261328 7.48 6.95 7.35‚Äî.03 ProctGam 2.57 60183 82.59 81.92 82.43+.11 ProUShSP 73094 21.55 21.23 21.34‚Äî.15 RegionsFn .20 191427 9.64 9.42 9.58+.12 RiteAid 487525 9.07 8.62 8.79+.22 S&P500ETF 3.94e 767134 206.98 205.40 206.44+.74 SpdrLehHY 2.81e 66759 39.15 39.09 39.15+.02 SpdrOGEx .69e 108836 51.09 49.56 50.81+.64 SandRdge 87992 1.83 1.75 1.82+.04 Schlmbrg 2f 60154 85.43 83.89 84.39+.11 SchwUSDiv 1.06e 71223 39.43 39.16 39.26+.07 Schwab .24 68010 30.09 29.66 30.01+.08 SeadrillLtd 92055 9.70 9.30 9.66+.31 SwstAirl .24 82644 43.82 42.69 42.86‚Äî.59 SwstnEngy 96623 24.12 22.72 24.04+1.18 Sprint 170932 4.87 4.72 4.85+.12 SPHlthC .90e 73503 72.32 71.64 71.99+.22 SPEngy 1.94e 137005 78.17 77.02 77.72+.16 SPDRFncl .41e 204868 24.25 24.03 24.21+.12 SPInds 1.07e 65588 55.76 55.25 55.43+.03 SPUtil 1.51e 110431 44.75 44.35 44.55+.08 Suncorg 1.12 81532 30.95 29.47 30.77+1.25 SunEdison 97821 25.86 24.90 25.15+.05 TaiwSemi .50e 123395 23.83 23.58 23.69+.46 TalismEg .27 64328 7.73 7.67 7.70+.02 Transocn 3 79321 15.05 14.44 14.99+.27 Twitter 132055 50.95 49.88 50.42‚Äî.05 UtdContl 73178 64.54 61.73 61.88‚Äî2.13 USNGas 89560 13.66 13.16 13.60+.50 USOilFd 348980 17.68 17.06 17.56‚Äî.02 ValeSA .60e 241634 5.79 5.45 5.76+.18 ValeSApf .60e 209042 4.96 4.57 4.94+.17 ValeroE 1.60f 130302 63.65 59.31 59.80‚Äî3.65 VangEmg 1.13e 80851 42.14 41.70 42.06+.64 VerizonCm 2.20 132244 49.60 48.86 49.47+.55 Vipshops 62844 29.44 28.50 29.11‚Äî.20 WalMart 1.96f 57620 81.32 80.55 80.73+.02 WeathfIntl 72069 13.13 12.66 12.91+.21 WellsFargo 1.40 132384 54.48 53.82 54.37+.43 WstnUnion .62f 88110 21.04 20.48 20.91+.35 WhitingPet 111110 33.56 31.62 32.81+.76 Xerox .28f 73654 12.84 12.68 12.77+.10 Yamanag .06 61317 3.87 3.67 3.74‚Äî.06 | AG9: 1644
A10: 8 | B10: 43670.489 | C10: APRS000020150401eb41008qa | D10: Throw | E10: Throw | F10: =VLOOKUP(C10,InnovYes_Review!$A$2:$I$415,9,FALSE) -> 0 | G10: 2 | H10: 2 | J10: NevilleQuinton_McDonaldSarah | M10: No | S10: No | T10: CLOSING MOST ACTIVE STOCKS NEW YORK (AP) ‚Äî Thursday's prices for NYSE listed most active stocks: SalesHighLowCloseChg AKSteel 62480 4.48 4.28 4.45+.04 AT&TInc 1.88 191398 33.23 32.82 33.13+.24 AbbVie 2.04f 82730 57.81 56.90 57.01‚Äî.09 Alcoa .12 229316 13.28 12.79 13.14+.14 Alibaban 197105 83.00 81.25 82.28‚Äî.08 Altria 2.08 89727 51.29 50.36 51.19+.89 Ambev .24e 223981 6.10 5.94 6.04+.12 AmExp 1.04 56372 79.77 78.57 79.70+.77 ArchDan 1.12f 58135 48.34 47.34 47.35‚Äî.08 Avon .24 63540 7.98 7.82 7.97+.12 Axaltan 124504 28.24 27.70 27.93‚Äî.71 BcoBrads .42e 76110 9.98 9.73 9.87+.28 BkofAm .20 492903 15.62 15.43 15.54+.13 BiPVixST 312181 25.52 24.97 25.06‚Äî.46 BarrickG .20 113083 12.11 11.71 11.88‚Äî.13 BostonSci 55462 17.83 17.54 17.72+.07 CBSB .60 94570 61.49 59.11 61.16+1.54 CNOFincl .24 110977 18.08 17.55 17.79+.66 CSX .64 92418 33.40 32.94 33.32‚Äî.13 CalifResn .04 77919 8.50 7.98 8.18+.23 CarMax 88765 75.40 71.97 74.73+6.34 Cemex .52t 80435 9.85 9.36 9.73+.29 ChesEng .35 319448 14.69 14.20 14.59+.24 Chimera .38f 76225 3.16 3.12 3.14 Citigroup .04 137424 52.22 51.59 51.86+.24 CitizFinn .40 60067 24.68 24.25 24.62+.26 CocaCola 1.32f 142674 40.87 40.48 40.68 ConocoPhil 2.92 58790 63.41 62.57 63.18+.16 ContlRess 70611 47.40 45.19 46.04+.38 Corning .48f 91026 22.44 22.07 22.32+.07 CSVInvNG 100667 7.94 7.03 7.11‚Äî.95 CSVLgNGs 413546 2.45 2.21 2.43+.26 CSVLgCrde 690598 2.52 2.25 2.45‚Äî.01 DeltaAir .36 152653 43.37 42.25 42.25‚Äî1.01 DenburyR .25 153411 7.85 7.31 7.84+.46 DBXEafeEq 1.37e 72214 30.31 30.15 30.28+.11 DxGldBull 201745 11.12 10.13 10.55‚Äî.35 DrxSCBear 92483 10.13 9.90 10.03‚Äî.08 DirGMBear .95e 59867 10.90 9.94 10.44+.39 DirDGldBr 73975 17.25 15.79 16.63+.53 DowChm 1.68 60468 48.39 47.53 48.24+.34 DuPont 1.88 87262 71.65 70.71 71.39+.41 EMCCp .46 158376 25.71 25.42 25.53+.06 EldorGldg .02e 60111 4.94 4.76 4.85‚Äî.11 EmersonEl 1.88 58899 56.26 55.50 55.54‚Äî.35 EnCanag .28 73290 11.59 11.18 11.47+.17 Exelon 1.24 72506 33.58 32.88 33.38+.53 ExxonMbl 2.76 111997 84.94 83.85 84.30‚Äî.16 FordM .60f 157587 16.04 15.85 16.03+.12 FrptMcM .20m 138747 19.07 18.74 19.00+.03 GenElec .92 286136 25.00 24.70 24.94+.10 GenMotors 1.20 163863 36.73 36.33 36.50‚Äî.24 Genworth 152103 7.94 7.29 7.76+.43 Goldcrpg .60 58759 19.19 18.52 18.85‚Äî.16 Hallibrtn .72 110919 44.32 43.49 43.96+.14 HewlettP .64 83904 31.75 31.22 31.40+.11 Hilton 70949 29.71 29.30 29.36+.08 HostHotls .80a 56946 20.58 20.21 20.49+.23 ICICIBks .15e 68141 10.77 10.59 10.69+.07 iShBrazil 1.38e 247466 33.37 32.63 33.24+.99 iShGerm .63e 55692 30.39 30.18 30.33+.23 iShJapan .15e 242135 12.74 12.63 12.69+.11 iSTaiwn .29e 72967 16.08 15.93 16.07+.33 iShSilver 55952 16.13 15.88 16.02‚Äî.21 iShChinaLC 1.04e 155255 45.77 45.34 45.66+.46 iShEMkts .88e 576820 41.34 40.90 41.24+.61 iSh20yrT 3.31e 60332 131.97 130.61 130.73‚Äî1.40 iSEafe 2.26e 154321 65.24 64.93 65.19+.56 iShR2K 1.59e 217897 125.26 124.29 124.65+.23 iShREst 2.70e 90132 80.08 79.07 79.84+.53 IntlGame .44 134257 17.93 17.73 17.77+.22 ItauUnibH .41e 188088 11.87 11.60 11.77+.32 JPMorgCh 1.60 124551 60.70 60.00 60.52+.57 JohnJn 2.80 59482 99.99 98.89 99.64+.49 Keycorp .26 79557 14.28 14.10 14.25+.09 KindMorg 1.80f 61729 42.00 41.56 41.72‚Äî.20 Kinrossg 125203 2.38 2.27 2.32‚Äî.04 LaredoPet 66017 14.34 13.60 14.30+.90 Lorillard 2.64f 111880 69.82 68.78 69.25+1.86 LumberLiq 114630 35.18 32.20 33.20+.19 MGM Rsts 94815 21.38 20.73 21.34+.46 Macys 1.25 98604 68.48 65.29 67.85+2.40 MarathnO .84 85537 27.28 26.39 27.07+.43 MVJrGold 100379 24.14 23.38 23.70‚Äî.39 MktVGold .12e 408875 19.35 18.76 18.99‚Äî.22 MVOilSvc .86e 83470 34.47 33.71 34.29+.32 MktVRus .64e 201098 18.43 17.98 18.40+.68 Masco .36 55658 26.74 25.95 26.62+.55 McDrmInt 62712 4.25 3.91 4.18+.24 McDnlds 3.40 65436 96.24 94.71 95.83‚Äî.46 Merck 1.80 75009 57.45 56.85 57.10+.24 MorgStan .40 60449 36.20 35.79 36.06+.09 MotrlaSolu 1.36 80587 67.46 61.15 62.51‚Äî4.16 NRGEgy .58f 58856 24.30 23.66 23.99+.39 Nabors .24 97096 14.62 13.90 14.07‚Äî.01 NBGreece 62925 1.25 1.22 1.23‚Äî.01 NewmtM .10 64496 22.91 22.15 22.34‚Äî.38 NobleCorp 1.50 72848 14.81 14.21 14.76+.31 NokiaCp .51e 80801 7.70 7.63 7.65+.10 OasisPet 76635 15.28 14.46 14.94+.25 Oracle .60f x110967 43.11 42.48 42.62‚Äî.17 PeabdyE .01m 106729 4.96 4.71 4.87+.12 Penney 200476 9.20 8.82 9.13+.23 PetrbrsA .85e 117912 6.82 6.50 6.80+.39 Petrobras .46e 439239 6.79 6.41 6.76+.41 Pfizer 1.12f 248144 34.63 34.22 34.38+.05 PUltVixST 188107 14.98 14.34 14.41‚Äî.59 PrUltCrude 261328 7.48 6.95 7.35‚Äî.03 ProctGam 2.57 60183 82.59 81.92 82.43+.11 ProUShSP 73094 21.55 21.23 21.34‚Äî.15 RegionsFn .20 191427 9.64 9.42 9.58+.12 RiteAid 487525 9.07 8.62 8.79+.22 S&P500ETF 3.94e 767134 206.98 205.40 206.44+.74 SpdrLehHY 2.81e 66759 39.15 39.09 39.15+.02 SpdrOGEx .69e 108836 51.09 49.56 50.81+.64 SandRdge 87992 1.83 1.75 1.82+.04 Schlmbrg 2f 60154 85.43 83.89 84.39+.11 SchwUSDiv 1.06e 71223 39.43 39.16 39.26+.07 Schwab .24 68010 30.09 29.66 30.01+.08 SeadrillLtd 92055 9.70 9.30 9.66+.31 SwstAirl .24 82644 43.82 42.69 42.86‚Äî.59 SwstnEngy 96623 24.12 22.72 24.04+1.18 Sprint 170932 4.87 4.72 4.85+.12 SPHlthC .90e 73503 72.32 71.64 71.99+.22 SPEngy 1.94e 137005 78.17 77.02 77.72+.16 SPDRFncl .41e 204868 24.25 24.03 24.21+.12 SPInds 1.07e 65588 55.76 55.25 55.43+.03 SPUtil 1.51e 110431 44.75 44.35 44.55+.08 Suncorg 1.12 81532 30.95 29.47 30.77+1.25 SunEdison 97821 25.86 24.90 25.15+.05 TaiwSemi .50e 123395 23.83 23.58 23.69+.46 TalismEg .27 64328 7.73 7.67 7.70+.02 Transocn 3 79321 15.05 14.44 14.99+.27 Twitter 132055 50.95 49.88 50.42‚Äî.05 UtdContl 73178 64.54 61.73 61.88‚Äî2.13 USNGas 89560 13.66 13.16 13.60+.50 USOilFd 348980 17.68 17.06 17.56‚Äî.02 ValeSA .60e 241634 5.79 5.45 5.76+.18 ValeSApf .60e 209042 4.96 4.57 4.94+.17 ValeroE 1.60f 130302 63.65 59.31 59.80‚Äî3.65 VangEmg 1.13e 80851 42.14 41.70 42.06+.64 VerizonCm 2.20 132244 49.60 48.86 49.47+.55 Vipshops 62844 29.44 28.50 29.11‚Äî.20 WalMart 1.96f 57620 81.32 80.55 80.73+.02 WeathfIntl 72069 13.13 12.66 12.91+.21 WellsFargo 1.40 132384 54.48 53.82 54.37+.43 WstnUnion .62f 88110 21.04 20.48 20.91+.35 WhitingPet 111110 33.56 31.62 32.81+.76 Xerox .28f 73654 12.84 12.68 12.77+.10 Yamanag .06 61317 3.87 3.67 3.74‚Äî.06 | U10: ['abvbba', 'almam', 'carmax', 'ccred', 'corn', 'csxc', 'dupnt', 'genwth', 'memcem', 'orcle', 'petbrs', 'pfiz', 'phelc', 'philm', 'soccor', 'twnit', 'wlmrt', 'xrxco', 'soccor', 'pfiz'] | V10: ['pfiz', 'soccor'] | W10: The Associated Press | X10: ,usa,namz, | Y10: NAMZ USA | AA10: APRS | AB10: Associated Press Newswires | AC10: FALSE | AD10: ['nrmf', 'ncat', 'nfact', 'nfce', 'niwe', 'ntab', 'm11', 'mcat'] | AE10: BC-150-actives-f | AF10: BC-150-actives-f CLOSING MOST ACTIVE STOCKS NEW YORK (AP) ‚Äî Thursday's prices for NYSE listed most active stocks: SalesHighLowCloseChg AKSteel 62480 4.48 4.28 4.45+.04 AT&TInc 1.88 191398 33.23 32.82 33.13+.24 AbbVie 2.04f 82730 57.81 56.90 57.01‚Äî.09 Alcoa .12 229316 13.28 12.79 13.14+.14 Alibaban 197105 83.00 81.25 82.28‚Äî.08 Altria 2.08 89727 51.29 50.36 51.19+.89 Ambev .24e 223981 6.10 5.94 6.04+.12 AmExp 1.04 56372 79.77 78.57 79.70+.77 ArchDan 1.12f 58135 48.34 47.34 47.35‚Äî.08 Avon .24 63540 7.98 7.82 7.97+.12 Axaltan 124504 28.24 27.70 27.93‚Äî.71 BcoBrads .42e 76110 9.98 9.73 9.87+.28 BkofAm .20 492903 15.62 15.43 15.54+.13 BiPVixST 312181 25.52 24.97 25.06‚Äî.46 BarrickG .20 113083 12.11 11.71 11.88‚Äî.13 BostonSci 55462 17.83 17.54 17.72+.07 CBSB .60 94570 61.49 59.11 61.16+1.54 CNOFincl .24 110977 18.08 17.55 17.79+.66 CSX .64 92418 33.40 32.94 33.32‚Äî.13 CalifResn .04 77919 8.50 7.98 8.18+.23 CarMax 88765 75.40 71.97 74.73+6.34 Cemex .52t 80435 9.85 9.36 9.73+.29 ChesEng .35 319448 14.69 14.20 14.59+.24 Chimera .38f 76225 3.16 3.12 3.14 Citigroup .04 137424 52.22 51.59 51.86+.24 CitizFinn .40 60067 24.68 24.25 24.62+.26 CocaCola 1.32f 142674 40.87 40.48 40.68 ConocoPhil 2.92 58790 63.41 62.57 63.18+.16 ContlRess 70611 47.40 45.19 46.04+.38 Corning .48f 91026 22.44 22.07 22.32+.07 CSVInvNG 100667 7.94 7.03 7.11‚Äî.95 CSVLgNGs 413546 2.45 2.21 2.43+.26 CSVLgCrde 690598 2.52 2.25 2.45‚Äî.01 DeltaAir .36 152653 43.37 42.25 42.25‚Äî1.01 DenburyR .25 153411 7.85 7.31 7.84+.46 DBXEafeEq 1.37e 72214 30.31 30.15 30.28+.11 DxGldBull 201745 11.12 10.13 10.55‚Äî.35 DrxSCBear 92483 10.13 9.90 10.03‚Äî.08 DirGMBear .95e 59867 10.90 9.94 10.44+.39 DirDGldBr 73975 17.25 15.79 16.63+.53 DowChm 1.68 60468 48.39 47.53 48.24+.34 DuPont 1.88 87262 71.65 70.71 71.39+.41 EMCCp .46 158376 25.71 25.42 25.53+.06 EldorGldg .02e 60111 4.94 4.76 4.85‚Äî.11 EmersonEl 1.88 58899 56.26 55.50 55.54‚Äî.35 EnCanag .28 73290 11.59 11.18 11.47+.17 Exelon 1.24 72506 33.58 32.88 33.38+.53 ExxonMbl 2.76 111997 84.94 83.85 84.30‚Äî.16 FordM .60f 157587 16.04 15.85 16.03+.12 FrptMcM .20m 138747 19.07 18.74 19.00+.03 GenElec .92 286136 25.00 24.70 24.94+.10 GenMotors 1.20 163863 36.73 36.33 36.50‚Äî.24 Genworth 152103 7.94 7.29 7.76+.43 Goldcrpg .60 58759 19.19 18.52 18.85‚Äî.16 Hallibrtn .72 110919 44.32 43.49 43.96+.14 HewlettP .64 83904 31.75 31.22 31.40+.11 Hilton 70949 29.71 29.30 29.36+.08 HostHotls .80a 56946 20.58 20.21 20.49+.23 ICICIBks .15e 68141 10.77 10.59 10.69+.07 iShBrazil 1.38e 247466 33.37 32.63 33.24+.99 iShGerm .63e 55692 30.39 30.18 30.33+.23 iShJapan .15e 242135 12.74 12.63 12.69+.11 iSTaiwn .29e 72967 16.08 15.93 16.07+.33 iShSilver 55952 16.13 15.88 16.02‚Äî.21 iShChinaLC 1.04e 155255 45.77 45.34 45.66+.46 iShEMkts .88e 576820 41.34 40.90 41.24+.61 iSh20yrT 3.31e 60332 131.97 130.61 130.73‚Äî1.40 iSEafe 2.26e 154321 65.24 64.93 65.19+.56 iShR2K 1.59e 217897 125.26 124.29 124.65+.23 iShREst 2.70e 90132 80.08 79.07 79.84+.53 IntlGame .44 134257 17.93 17.73 17.77+.22 ItauUnibH .41e 188088 11.87 11.60 11.77+.32 JPMorgCh 1.60 124551 60.70 60.00 60.52+.57 JohnJn 2.80 59482 99.99 98.89 99.64+.49 Keycorp .26 79557 14.28 14.10 14.25+.09 KindMorg 1.80f 61729 42.00 41.56 41.72‚Äî.20 Kinrossg 125203 2.38 2.27 2.32‚Äî.04 LaredoPet 66017 14.34 13.60 14.30+.90 Lorillard 2.64f 111880 69.82 68.78 69.25+1.86 LumberLiq 114630 35.18 32.20 33.20+.19 MGM Rsts 94815 21.38 20.73 21.34+.46 Macys 1.25 98604 68.48 65.29 67.85+2.40 MarathnO .84 85537 27.28 26.39 27.07+.43 MVJrGold 100379 24.14 23.38 23.70‚Äî.39 MktVGold .12e 408875 19.35 18.76 18.99‚Äî.22 MVOilSvc .86e 83470 34.47 33.71 34.29+.32 MktVRus .64e 201098 18.43 17.98 18.40+.68 Masco .36 55658 26.74 25.95 26.62+.55 McDrmInt 62712 4.25 3.91 4.18+.24 McDnlds 3.40 65436 96.24 94.71 95.83‚Äî.46 Merck 1.80 75009 57.45 56.85 57.10+.24 MorgStan .40 60449 36.20 35.79 36.06+.09 MotrlaSolu 1.36 80587 67.46 61.15 62.51‚Äî4.16 NRGEgy .58f 58856 24.30 23.66 23.99+.39 Nabors .24 97096 14.62 13.90 14.07‚Äî.01 NBGreece 62925 1.25 1.22 1.23‚Äî.01 NewmtM .10 64496 22.91 22.15 22.34‚Äî.38 NobleCorp 1.50 72848 14.81 14.21 14.76+.31 NokiaCp .51e 80801 7.70 7.63 7.65+.10 OasisPet 76635 15.28 14.46 14.94+.25 Oracle .60f x110967 43.11 42.48 42.62‚Äî.17 PeabdyE .01m 106729 4.96 4.71 4.87+.12 Penney 200476 9.20 8.82 9.13+.23 PetrbrsA .85e 117912 6.82 6.50 6.80+.39 Petrobras .46e 439239 6.79 6.41 6.76+.41 Pfizer 1.12f 248144 34.63 34.22 34.38+.05 PUltVixST 188107 14.98 14.34 14.41‚Äî.59 PrUltCrude 261328 7.48 6.95 7.35‚Äî.03 ProctGam 2.57 60183 82.59 81.92 82.43+.11 ProUShSP 73094 21.55 21.23 21.34‚Äî.15 RegionsFn .20 191427 9.64 9.42 9.58+.12 RiteAid 487525 9.07 8.62 8.79+.22 S&P500ETF 3.94e 767134 206.98 205.40 206.44+.74 SpdrLehHY 2.81e 66759 39.15 39.09 39.15+.02 SpdrOGEx .69e 108836 51.09 49.56 50.81+.64 SandRdge 87992 1.83 1.75 1.82+.04 Schlmbrg 2f 60154 85.43 83.89 84.39+.11 SchwUSDiv 1.06e 71223 39.43 39.16 39.26+.07 Schwab .24 68010 30.09 29.66 30.01+.08 SeadrillLtd 92055 9.70 9.30 9.66+.31 SwstAirl .24 82644 43.82 42.69 42.86‚Äî.59 SwstnEngy 96623 24.12 22.72 24.04+1.18 Sprint 170932 4.87 4.72 4.85+.12 SPHlthC .90e 73503 72.32 71.64 71.99+.22 SPEngy 1.94e 137005 78.17 77.02 77.72+.16 SPDRFncl .41e 204868 24.25 24.03 24.21+.12 SPInds 1.07e 65588 55.76 55.25 55.43+.03 SPUtil 1.51e 110431 44.75 44.35 44.55+.08 Suncorg 1.12 81532 30.95 29.47 30.77+1.25 SunEdison 97821 25.86 24.90 25.15+.05 TaiwSemi .50e 123395 23.83 23.58 23.69+.46 TalismEg .27 64328 7.73 7.67 7.70+.02 Transocn 3 79321 15.05 14.44 14.99+.27 Twitter 132055 50.95 49.88 50.42‚Äî.05 UtdContl 73178 64.54 61.73 61.88‚Äî2.13 USNGas 89560 13.66 13.16 13.60+.50 USOilFd 348980 17.68 17.06 17.56‚Äî.02 ValeSA .60e 241634 5.79 5.45 5.76+.18 ValeSApf .60e 209042 4.96 4.57 4.94+.17 ValeroE 1.60f 130302 63.65 59.31 59.80‚Äî3.65 VangEmg 1.13e 80851 42.14 41.70 42.06+.64 VerizonCm 2.20 132244 49.60 48.86 49.47+.55 Vipshops 62844 29.44 28.50 29.11‚Äî.20 WalMart 1.96f 57620 81.32 80.55 80.73+.02 WeathfIntl 72069 13.13 12.66 12.91+.21 WellsFargo 1.40 132384 54.48 53.82 54.37+.43 WstnUnion .62f 88110 21.04 20.48 20.91+.35 WhitingPet 111110 33.56 31.62 32.81+.76 Xerox .28f 73654 12.84 12.68 12.77+.10 Yamanag .06 61317 3.87 3.67 3.74‚Äî.06 | AG10: 1644
A11: 9 | B11: 43670.486 | C11: APRS000020150513eb5d00d72 | D11: None | E11: Keep | F11: =VLOOKUP(C11,InnovYes_Review!$A$2:$I$415,9,FALSE) -> 0 | G11: 1 | H11: 1 | I11: 1 | J11: Bayoan | K11: Bayoan | M11: No | S11: No | T11: Pe- Stk of pay- riod rate record able IRREGULAR Qiwi plc z Q .25 5-26 5-28 z- Approx. amount per ADR or ADS. STOCK China Life Insurance x 5-22 5-26 x- 3 for 1 split. NRG Yield A x 5-14 x- One share class A and one share class C for each share held. INCREASED Ashland Inc Q .39 5-29 6-15 Hackett Group S .10 6-29 7-10 HollyFrontier Q .33 6-5 6-26 Mosaic Co x Q .275 6-4 6-18 x- Previously announced, reporting dates. INITIAL NRG Yield A&C new Q .20 6-1 6-15 SPECIAL Ohio Valley Banc Cp .05 5-26 6-10 REGULAR Ameriana Bancorp Q .04 6-12 7-2 Baker Hughes Q .17 6-3 6-24 Corrections Corp Am Q .54 7-2 7-15 Dean Foods Q .07 5-22 6-4 Delta Nat Gas Q .20 6-1 6-15 DeVry Educ S .18 6-5 6-15 Digital Realty Trust Q .85 6-15 6-30 Dow Chemical Q .42 6-30 7-30 Encore Wire Q .02 7-10 7-24 Fair Isaac Q .02 5-27 6-10 Gildan Activewear Q .065 5-27 6-22 Graham Holdings Q 2.65 7-20 8-6 Harte Hanks Q .085 6-1 6-15 Integrys Energy Q .68 5-29 6-19 Invacare Corp Q .0125 7-2 7-13 KBR Inc Q .08 6-15 7-15 Kapstone Paper&Pkg Q .10 6-30 7-13 Kingstone Cos Q .05 6-1 6-15 Kohl's Corp Q .45 6-10 6-24 Lorillard Inc Q .66 6-1 6-10 MDU Resources Q .1825 6-11 7-1 Mosaic Co Q .275 6-4 6-18 Natl Oilwell Varco Q .46 6-12 6-28 NewellRubbermaid Q .19 5-29 6-15 OGE Energy Q .25 7-10 7-30 Packaging Corp Amer Q .55 6-15 7-15 PacWest Bancorp Q .50 5-26 6-4 Panhandle Oil&Gas Q .04 5-27 6-10 Parkway Properties Q .1875 6-10 6-24 PolyOne Corp Q .10 6-12 7-8 Service Corp Intl Q .10 6-15 6-30 Stantec Inc g Q .105 6-30 7-6 Symantec Corp Q .15 6-10 6-24 Union Pacific Q .55 5-29 6-30 Xylem Inc Q .1408 5-28 6-24 g- Payable in Canadian funds. | U11: ['amrsav', 'ashlnd', 'corca', 'holco', 'nrgyld', 'amrsav', 'amrsav', 'ashlnd', 'ashlnd', 'bakint', 'bakint', 'corca', 'dgrltr', 'dowch', 'dowch', 'encwir', 'encwir', 'fstdes', 'fstdes', 'geonco', 'geonco', 'gildan', 'gildan', 'hhn', 'hhn', 'holco', 'invac', 'invac', 'kbroot', 'kbroot', 'kohldp', 'kohldp', 'ltob', 'ltob', 'mdu', 'mdu', 'nrgyld', 'oklhmg', 'oklhmg', 'srv', 'srv', 'stgtg', 'stgtg', 'suzfod', 'suzfod', 'symt', 'symt', 'unpacf', 'unpacf', 'wpsrss', 'wpsrss', 'wshpst', 'wshpst', 'xylein', 'xylein', 'invac', 'kbroot', 'kohldp', 'ltob', 'fstdes', 'geonco', 'stgtg', 'symt', 'xylein', 'msccmp', 'nrgeng'] | V11: ['msccmp', 'xylein', 'symt', 'stgtg', 'geonco', 'fstdes', 'ltob', 'kohldp', 'kbroot', 'invac', 'nrgyld', 'holco', 'corca', 'ashlnd', 'amrsav'] | W11: The Associated Press | X11: ,usa,namz, | Y11: NAMZ USA | AA11: APRS | AB11: Associated Press Newswires | AC11: FALSE | AD11: ['gpol', 'gcat', 'gpir'] | AE11: BC-Dividends | AF11: BC-Dividends Pe- Stk of pay- riod rate record able IRREGULAR Qiwi plc z Q .25 5-26 5-28 z- Approx. amount per ADR or ADS. STOCK China Life Insurance x 5-22 5-26 x- 3 for 1 split. NRG Yield A x 5-14 x- One share class A and one share class C for each share held. INCREASED Ashland Inc Q .39 5-29 6-15 Hackett Group S .10 6-29 7-10 HollyFrontier Q .33 6-5 6-26 Mosaic Co x Q .275 6-4 6-18 x- Previously announced, reporting dates. INITIAL NRG Yield A&C new Q .20 6-1 6-15 SPECIAL Ohio Valley Banc Cp .05 5-26 6-10 REGULAR Ameriana Bancorp Q .04 6-12 7-2 Baker Hughes Q .17 6-3 6-24 Corrections Corp Am Q .54 7-2 7-15 Dean Foods Q .07 5-22 6-4 Delta Nat Gas Q .20 6-1 6-15 DeVry Educ S .18 6-5 6-15 Digital Realty Trust Q .85 6-15 6-30 Dow Chemical Q .42 6-30 7-30 Encore Wire Q .02 7-10 7-24 Fair Isaac Q .02 5-27 6-10 Gildan Activewear Q .065 5-27 6-22 Graham Holdings Q 2.65 7-20 8-6 Harte Hanks Q .085 6-1 6-15 Integrys Energy Q .68 5-29 6-19 Invacare Corp Q .0125 7-2 7-13 KBR Inc Q .08 6-15 7-15 Kapstone Paper&Pkg Q .10 6-30 7-13 Kingstone Cos Q .05 6-1 6-15 Kohl's Corp Q .45 6-10 6-24 Lorillard Inc Q .66 6-1 6-10 MDU Resources Q .1825 6-11 7-1 Mosaic Co Q .275 6-4 6-18 Natl Oilwell Varco Q .46 6-12 6-28 NewellRubbermaid Q .19 5-29 6-15 OGE Energy Q .25 7-10 7-30 Packaging Corp Amer Q .55 6-15 7-15 PacWest Bancorp Q .50 5-26 6-4 Panhandle Oil&Gas Q .04 5-27 6-10 Parkway Properties Q .1875 6-10 6-24 PolyOne Corp Q .10 6-12 7-8 Service Corp Intl Q .10 6-15 6-30 Stantec Inc g Q .105 6-30 7-6 Symantec Corp Q .15 6-10 6-24 Union Pacific Q .55 5-29 6-30 Xylem Inc Q .1408 5-28 6-24 g- Payable in Canadian funds. | AG11: 420
A12: 10 | B12: 43670.503 | C12: APRS000020150819eb8j00030 | D12: Keep | E12: Keep | F12: =VLOOKUP(C12,InnovYes_Review!$A$2:$I$415,9,FALSE) -> 0 | G12: 1 | H12: 1 | I12: 1 | J12: KramerBrandon | K12: KramerBrandon | M12: Yes | N12: Approved by FDA and scheduled to be launched | O12: flibanserin, Addyi | P12: Sprout Pharmaceuticals | Q12: No | R12: Yes | S12: No | T12: ‚Äî 2009: Boehringer submits the drug to the Food and Drug Administration for approval to treat female hypoactive sexual desire disorder, a condition described as emotional distress caused by a lack of sexual desire. The FDA had never approved a drug for that condition or any other female sexual disorders. ‚Äî June 2010: A panel of FDA advisers votes unanimously against the drug, saying its benefits are outweighed by its risks, including side effects like dizziness, fatigue and fainting. ‚Äî Late 2011: Boehringer abandons the drug and sells it to Sprout Pharmaceuticals, a small North Carolina company. ‚Äî March 2013: Sprout resubmits the drug to FDA with additional data showing its benefits using a new measurement technique. ‚Äî September 2013: The FDA rejects the drug a second time, saying its benefits are "numerically small" and still don't outweigh "substantial safety concerns." ‚Äî December 2013: Sprout files a formal dispute against the FDA, arguing the agency should approve the drug without any additional data. ‚Äî February 2014: The FDA responds by proposing Sprout conduct additional studies, including one examining flibanserin's effects on driving, because of its drowsiness side effect. ‚Äî February 2015: Sprout resubmits the drug to the FDA with the requested studies. At the same time, the company helps fund a campaign called Even the Score, which lobbies the FDA to approve sexual medicines for women. ‚Äî June 2015: A panel of FDA advisers votes 18-6 in favor of approving the drug, with safety restrictions. ‚Äî August 2015: The FDA approves flibanserin, branded Addyi, as the first drug to treat any type of female sexual dysfunction. The drug includes a black box warning about side effects. | U12: ['boehig', 'boehig', 'boehig', 'lrgkef', 'lrgkef', 'usfda', 'usfda', 'usfda', 'borngi'] | V12: ['usfda', 'boehig'] | W12: The Associated Press | X12: ,usa,namz, | Y12: NAMZ USA | Z12: Federal health officials on Tuesday approved the first prescription drug intended to treat women suffering from a lack of sexual desire. The daily pill, which acts on brain chemicals, followed a long, winding path to approval, including two previous rejections by the Food and Drug Administration. Here's a look at the history: ‚Äî Pre-2009: German drugmaker Boehringer Ingelheim studies its drug, known chemically as flibanserin, as a treatment for depression in men and women. The drug had little effect, but researchers noticed patients reported increased sexual desire, suggesting an alternate use. | AA12: APRS | AB12: Associated Press Newswires | AC12: TRUE | AD12: ['cappro', 'gdepr', 'ghea', 'grape', 'nchr', 'c13', 'c22', 'ccat', 'gcat', 'gcrim', 'gmed', 'gment', 'ncat', 'nfact', 'nfcpin'] | AE12: Female libido pill took long, winding route to market | AF12: Female libido pill took long, winding route to market‚Äî 2009: Boehringer submits the drug to the Food and Drug Administration for approval to treat female hypoactive sexual desire disorder, a condition described as emotional distress caused by a lack of sexual desire. The FDA had never approved a drug for that condition or any other female sexual disorders. ‚Äî June 2010: A panel of FDA advisers votes unanimously against the drug, saying its benefits are outweighed by its risks, including side effects like dizziness, fatigue and fainting. ‚Äî Late 2011: Boehringer abandons the drug and sells it to Sprout Pharmaceuticals, a small North Carolina company. ‚Äî March 2013: Sprout resubmits the drug to FDA with additional data showing its benefits using a new measurement technique. ‚Äî September 2013: The FDA rejects the drug a second time, saying its benefits are "numerically small" and still don't outweigh "substantial safety concerns." ‚Äî December 2013: Sprout files a formal dispute against the FDA, arguing the agency should approve the drug without any additional data. ‚Äî February 2014: The FDA responds by proposing Sprout conduct additional studies, including one examining flibanserin's effects on driving, because of its drowsiness side effect. ‚Äî February 2015: Sprout resubmits the drug to the FDA with the requested studies. At the same time, the company helps fund a campaign called Even the Score, which lobbies the FDA to approve sexual medicines for women. ‚Äî June 2015: A panel of FDA advisers votes 18-6 in favor of approving the drug, with safety restrictions. ‚Äî August 2015: The FDA approves flibanserin, branded Addyi, as the first drug to treat any type of female sexual dysfunction. The drug includes a black box warning about side effects. | AG12: 374
A13: 11 | B13: 43670.497 | C13: APRS000020150916eb9g00and | D13: None | E13: Keep | F13: =VLOOKUP(C13,InnovYes_Review!$A$2:$I$415,9,FALSE) -> 0 | G13: 1 | H13: 1 | I13: 1 | J13: Extra5 | K13: Extra5 | M13: No | S13: No | T13: 6 a.m.-5 p.m. Skip Wollenberg and Charles N. Sheehan. 5 p.m.-9 p.m. Richard Jacobsen. For help please call: 800-845-8450, ext. 1680. Photos, ext. 1900. For graphics and interactives, ext. 7636. Expanded AP content can be obtained from http://www.apexchange.com. For access to AP Exchange and other technical issues, contact customersupport@ap.org or call 877-836-9477. If you have questions about transmission of financial market listings, please call 800-3AP-STOX. A selection of top photos can be found at: http://bit.ly/APTopPhotos All times EDT. TOP STORIES: FEDERAL RESERVE-THE GREAT DEBATE WASHINGTON ‚Äî For seven years, investors could count on one thing: Short-term U.S. interest rates would stay locked near zero. Now, the Fed is weighing whether to start phasing out the era of easy money on Thursday. Here's the case for a rate hike now ‚Äî and the case for delaying it. By Christopher S. Rugaber and Paul Wiseman. SENT: 1,400 words, photos, video. ‚ÄîVideo of AP reporters making both cases can be found at http://apne.ws/1iwl7YJ AB INBEV-SABMILLER LONDON ‚Äî The world's largest brewer and maker of Budweiser isn't satisfied with owning the king of beers. AB InBev wants to expand its global empire and add on major brands including Miller and Peroni. A deal to buy SABMiller would create by far the biggest brewer on the planet. By Danica Kirka. SENT: 700 words, photos. With: ‚Äî BIG BREWERS ‚Äî A closer look at the world's big brewers and the beers they make. UPCOMING: 300 words by 3 p.m., photos. FRANKFURT AUTO SHOW-CONNECTED CAR FRANKFURT, Germany ‚Äî Carmakers are bracing for disruption from new technologies and trying to figure out which of the myriad areas to plunge into to fend off the inroads of tech companies. The recent purchase of Nokia's maps division by three German luxury carmakers is a sign of things to come. By David McHugh. SENT: 840 words, photos. With: FRANKFURT AUTO SHOW-RIDING HIGH FRANKFURT, Germany ‚Äî Does anyone really need a sport-utility vehicle so fast it can hit speeds close to those seen in Formula One races? Luxury automaker Bentley is betting that some well-heeled customers will feel that they do. By David McHugh. SENT: 700 words, photos. And: ‚Äî GERMANY-FRANKFURT AUTO SHOW-BMW CEO ‚Äî BMW CEO Harald Krueger says he's doing fine, a day after he collapsed during a news conference at the Frankfurt auto show. SENT: 130 words, photos. FILM-DIVERSE SUCCESS LOS ANGELES ‚Äî "The Perfect Guy's" win at the box office this past weekend marks the fifth time in a row this summer where a film with a primarily African American cast has held the No. 1 position. "The Perfect Guy," ''War Room," and "Straight Outta Compton," all wildly different and wildly successful movies, prove once again that there is money to be made in telling diverse stories for an audience that is underserved by mainstream Hollywood filmmaking. By Lindsey Bahr. UPCOMING: 700 words by 5 p.m., photos. MARKETS & ECONOMY: CONSUMER PRICES WASHINGTON ‚Äî U.S. consumer prices edge down in August, marking the first decline in seven months and fueled by a big drop in gasoline prices. By Martin Crutsinger. SENT: 570 words, photo. BUILDER SENTIMENT WASHINGTON ‚Äî U.S. homebuilders are feeling slightly more optimistic about the housing market, nudging their confidence this month to a level not seen since the high-flying days of the housing boom nearly 10 years ago. By Alex Veiga. SENT: 450 words, photo. FOREIGN HOLDINGS WASHINGTON ‚Äî The Treasury Department reports on foreign holdings of U.S. debt for July. In June, foreign holdings of U.S. Treasury securities rebounded following two straight months of declines. By Martin Crutsinger. UPCOMING: 130 words after release of report at 4 p.m., 350 words by 4:45 p.m. FINANCIAL MARKETS NEW YORK ‚Äî Stocks edge higher in midday trading as investors wait to hear from the Federal Reserve and work through company news, including a possible deal between two giant beer makers. By Ken Sweet. SENT: 450 words, photos. UPCOMING: 700 words by 5 p.m. ‚Äî CENSUS-POVERTY ‚Äî The number of Americans living below the poverty line showed no statistical difference from the previous year, according to new numbers from the U.S. Census Bureau. By Jesse J. Holland. SENT: 410 words. EARNINGS: EARNS-FEDEX DALLAS ‚Äî FedEx reports disappointing results for its latest quarter, and the delivery giant cuts its full-year profit forecast on weaker demand for freight services and higher costs in its ground division. By David Koenig. SENT: 700 words, photo. ‚Äî SPAIN-EARNS-INDITEX ‚Äî The Spanish owner of the Zara clothing store chain says profit for the first half of 2015 rose 26 percent, boosted by growth in all markets around the world where the company sells clothes. SENT: 130 words. INDUSTRY: TARGET-WELLNESS MINNEAPOLIS ‚Äî Target is going on a health kick, aimed at both customers and its employees. By Anne D'Innocenzio and Tom Murphy. SENT: 530 words, photo. AMGEN DEALS TRENTON, N.J. ‚Äî Biotech drug giant Amgen has made two much-needed deals to replenish its stock of medicines in development as new competition to its lucrative biotech drugs threatens future revenue. By Linda A. Johnson. SENT: 130 words. UPCOMING: About 500 words by 2:30 p.m. ‚Äî OLIVE GARDEN-PASTA PASS ‚Äî Olive Garden is bringing back its "Pasta Pass" that lets people gorge on as much pasta as they want for seven weeks. By Candice Choi. SENT: 450 words, photo. ‚Äî OBAMA-BUDGET-BUSINESS LEADERS ‚Äî President Barack Obama urges Congress to avoid another contentious budget showdown and warns that the economy would surely take a hit if the government shuts down again. By Kevin Freking. SENT: 520 words, photos, video. ‚Äî MARIJUANA TAX HOLIDAY ‚Äî An accounting error in Colorado is paying off for marijuana consumers, as a quirk in a state tax law triggers a suspension of most taxes on recreational pot. SENT: 430 words, photos. UPCOMING: Will be updated after stores open. ‚Äî BEHIND THE WHEEL-2016 ACURA ILX ‚Äî Acura's least expensive sedan, the ILX, has luxurious upgrades for 2016, including a quieter interior, a handsome LED-accented exterior and improved performance ‚Äî all at a reasonable price. By Ann M. Job. SENT: 800 words, photo, box. TECHNOLOGY & MEDIA: ‚Äî AUDIO BOOKS GO CELEBRITY ‚Äî Audiobooks ‚Äî for so long dismissed as the things on CD you hope keep the kids quiet during long car trips ‚Äî have all grown up and lately the balance of power has shifted from the author to the presentation, with seasoned actors from Broadway and Hollywood. By Mark Kennedy. SENT: 940 words, photos. INTERNATIONAL: ‚Äî ARGENTINA-DEBT STANDOFF ‚Äî A federal appeals court hands Argentina a victory in its quest to relieve itself of the pressures of debt owed to American hedge funds and others, saying a judge went too far by letting some bondholders demand payment without proving how much they are entitled to be paid. By Larry Neumeister. SENT: 490 words. ‚Äî EUROPE-ECONOMY ‚Äî Inflation across the 19-country eurozone is revised down to 0.1 percent in the year to August, in a development that's likely to renew fears that the region could see another bout of falling prices. SENT: 400 words. ‚Äî BRITAIN-ECONOMY ‚Äî Pay growth in Britain is finally picking up, with wages rising 2.9 percent in the three months to July compared with a year earlier ‚Äî the strongest increase since February 2009. SENT: 130 words. ‚Äî JAPAN-CREDIT RATING ‚Äî Standard & Poor's lowers Japan's sovereign credit rating and says it doesn't expect Prime Minister Shinzo Abe's economic revival strategy to reverse deteriorating government finances within the next three years. SENT: 260 words. A sampling of Money & Markets modules is below. The full digest for AP's Money & Markets service can be found at markets.ap.org. For questions about Money & Markets content, please contact Trevor Delaney (800-845-8450, ext. 1807). For technical support: Todd Balog (816-654-1096). After 6 p.m., contact the AP Business News desk (800-845-8450, ext. 1680) for content questions; 1-800-3AP-STOX for technical support and 212-621-1905 for graphics help. CENTERPIECE Interest rate risk Just like a homeowner with an adjustable-rate mortgage, a corporation can also have debt with an interest rate that can move higher. And a higher rate will mean more expensive interest payments for companies repaying variable-rate debt, eating into their profits. UPCOMING: Graphic expected by 6 p.m. COMPANY SPOTLIGHT Dentsply buying rival Dental product company Dentsply is buying its rival Sirona for $5.51 billion. UPCOMING: Graphic expected by 6 p.m. | U13: ['amge', 'artboe', 'artboe', 'bmw', 'fdexps', 'fed', 'fed', 'gdxc', 'gdxc', 'nokia', 'nokia', 'sabrew', 'sabrew', 'stndpr', 'usboc', 'usdtr', 'zarspa', 'amge'] | V13: ['amge'] | W13: The Associated Press | X13: ,usa,gfr,jap,apacz,asiaz,dach,easiaz,eecz,eurz,namz,weurz, | Y13: NAMZ USA | Z13: Business News at 1:40 p.m. Supervisors: | AA13: APRS | AB13: Associated Press Newswires | AC13: FALSE | AD13: ['gpol', 'nadv', 'ncdig', 'nsum', 'gcat', 'gpir', 'ncat', 'nfact', 'nfce', 'niwe', 'nrgn'] | AE13: BC-Business News Digest | AF13: BC-Business News Digest6 a.m.-5 p.m. Skip Wollenberg and Charles N. Sheehan. 5 p.m.-9 p.m. Richard Jacobsen. For help please call: 800-845-8450, ext. 1680. Photos, ext. 1900. For graphics and interactives, ext. 7636. Expanded AP content can be obtained from http://www.apexchange.com. For access to AP Exchange and other technical issues, contact customersupport@ap.org or call 877-836-9477. If you have questions about transmission of financial market listings, please call 800-3AP-STOX. A selection of top photos can be found at: http://bit.ly/APTopPhotos All times EDT. TOP STORIES: FEDERAL RESERVE-THE GREAT DEBATE WASHINGTON ‚Äî For seven years, investors could count on one thing: Short-term U.S. interest rates would stay locked near zero. Now, the Fed is weighing whether to start phasing out the era of easy money on Thursday. Here's the case for a rate hike now ‚Äî and the case for delaying it. By Christopher S. Rugaber and Paul Wiseman. SENT: 1,400 words, photos, video. ‚ÄîVideo of AP reporters making both cases can be found at http://apne.ws/1iwl7YJ AB INBEV-SABMILLER LONDON ‚Äî The world's largest brewer and maker of Budweiser isn't satisfied with owning the king of beers. AB InBev wants to expand its global empire and add on major brands including Miller and Peroni. A deal to buy SABMiller would create by far the biggest brewer on the planet. By Danica Kirka. SENT: 700 words, photos. With: ‚Äî BIG BREWERS ‚Äî A closer look at the world's big brewers and the beers they make. UPCOMING: 300 words by 3 p.m., photos. FRANKFURT AUTO SHOW-CONNECTED CAR FRANKFURT, Germany ‚Äî Carmakers are bracing for disruption from new technologies and trying to figure out which of the myriad areas to plunge into to fend off the inroads of tech companies. The recent purchase of Nokia's maps division by three German luxury carmakers is a sign of things to come. By David McHugh. SENT: 840 words, photos. With: FRANKFURT AUTO SHOW-RIDING HIGH FRANKFURT, Germany ‚Äî Does anyone really need a sport-utility vehicle so fast it can hit speeds close to those seen in Formula One races? Luxury automaker Bentley is betting that some well-heeled customers will feel that they do. By David McHugh. SENT: 700 words, photos. And: ‚Äî GERMANY-FRANKFURT AUTO SHOW-BMW CEO ‚Äî BMW CEO Harald Krueger says he's doing fine, a day after he collapsed during a news conference at the Frankfurt auto show. SENT: 130 words, photos. FILM-DIVERSE SUCCESS LOS ANGELES ‚Äî "The Perfect Guy's" win at the box office this past weekend marks the fifth time in a row this summer where a film with a primarily African American cast has held the No. 1 position. "The Perfect Guy," ''War Room," and "Straight Outta Compton," all wildly different and wildly successful movies, prove once again that there is money to be made in telling diverse stories for an audience that is underserved by mainstream Hollywood filmmaking. By Lindsey Bahr. UPCOMING: 700 words by 5 p.m., photos. MARKETS & ECONOMY: CONSUMER PRICES WASHINGTON ‚Äî U.S. consumer prices edge down in August, marking the first decline in seven months and fueled by a big drop in gasoline prices. By Martin Crutsinger. SENT: 570 words, photo. BUILDER SENTIMENT WASHINGTON ‚Äî U.S. homebuilders are feeling slightly more optimistic about the housing market, nudging their confidence this month to a level not seen since the high-flying days of the housing boom nearly 10 years ago. By Alex Veiga. SENT: 450 words, photo. FOREIGN HOLDINGS WASHINGTON ‚Äî The Treasury Department reports on foreign holdings of U.S. debt for July. In June, foreign holdings of U.S. Treasury securities rebounded following two straight months of declines. By Martin Crutsinger. UPCOMING: 130 words after release of report at 4 p.m., 350 words by 4:45 p.m. FINANCIAL MARKETS NEW YORK ‚Äî Stocks edge higher in midday trading as investors wait to hear from the Federal Reserve and work through company news, including a possible deal between two giant beer makers. By Ken Sweet. SENT: 450 words, photos. UPCOMING: 700 words by 5 p.m. ‚Äî CENSUS-POVERTY ‚Äî The number of Americans living below the poverty line showed no statistical difference from the previous year, according to new numbers from the U.S. Census Bureau. By Jesse J. Holland. SENT: 410 words. EARNINGS: EARNS-FEDEX DALLAS ‚Äî FedEx reports disappointing results for its latest quarter, and the delivery giant cuts its full-year profit forecast on weaker demand for freight services and higher costs in its ground division. By David Koenig. SENT: 700 words, photo. ‚Äî SPAIN-EARNS-INDITEX ‚Äî The Spanish owner of the Zara clothing store chain says profit for the first half of 2015 rose 26 percent, boosted by growth in all markets around the world where the company sells clothes. SENT: 130 words. INDUSTRY: TARGET-WELLNESS MINNEAPOLIS ‚Äî Target is going on a health kick, aimed at both customers and its employees. By Anne D'Innocenzio and Tom Murphy. SENT: 530 words, photo. AMGEN DEALS TRENTON, N.J. ‚Äî Biotech drug giant Amgen has made two much-needed deals to replenish its stock of medicines in development as new competition to its lucrative biotech drugs threatens future revenue. By Linda A. Johnson. SENT: 130 words. UPCOMING: About 500 words by 2:30 p.m. ‚Äî OLIVE GARDEN-PASTA PASS ‚Äî Olive Garden is bringing back its "Pasta Pass" that lets people gorge on as much pasta as they want for seven weeks. By Candice Choi. SENT: 450 words, photo. ‚Äî OBAMA-BUDGET-BUSINESS LEADERS ‚Äî President Barack Obama urges Congress to avoid another contentious budget showdown and warns that the economy would surely take a hit if the government shuts down again. By Kevin Freking. SENT: 520 words, photos, video. ‚Äî MARIJUANA TAX HOLIDAY ‚Äî An accounting error in Colorado is paying off for marijuana consumers, as a quirk in a state tax law triggers a suspension of most taxes on recreational pot. SENT: 430 words, photos. UPCOMING: Will be updated after stores open. ‚Äî BEHIND THE WHEEL-2016 ACURA ILX ‚Äî Acura's least expensive sedan, the ILX, has luxurious upgrades for 2016, including a quieter interior, a handsome LED-accented exterior and improved performance ‚Äî all at a reasonable price. By Ann M. Job. SENT: 800 words, photo, box. TECHNOLOGY & MEDIA: ‚Äî AUDIO BOOKS GO CELEBRITY ‚Äî Audiobooks ‚Äî for so long dismissed as the things on CD you hope keep the kids quiet during long car trips ‚Äî have all grown up and lately the balance of power has shifted from the author to the presentation, with seasoned actors from Broadway and Hollywood. By Mark Kennedy. SENT: 940 words, photos. INTERNATIONAL: ‚Äî ARGENTINA-DEBT STANDOFF ‚Äî A federal appeals court hands Argentina a victory in its quest to relieve itself of the pressures of debt owed to American hedge funds and others, saying a judge went too far by letting some bondholders demand payment without proving how much they are entitled to be paid. By Larry Neumeister. SENT: 490 words. ‚Äî EUROPE-ECONOMY ‚Äî Inflation across the 19-country eurozone is revised down to 0.1 percent in the year to August, in a development that's likely to renew fears that the region could see another bout of falling prices. SENT: 400 words. ‚Äî BRITAIN-ECONOMY ‚Äî Pay growth in Britain is finally picking up, with wages rising 2.9 percent in the three months to July compared with a year earlier ‚Äî the strongest increase since February 2009. SENT: 130 words. ‚Äî JAPAN-CREDIT RATING ‚Äî Standard & Poor's lowers Japan's sovereign credit rating and says it doesn't expect Prime Minister Shinzo Abe's economic revival strategy to reverse deteriorating government finances within the next three years. SENT: 260 words. A sampling of Money & Markets modules is below. The full digest for AP's Money & Markets service can be found at markets.ap.org. For questions about Money & Markets content, please contact Trevor Delaney (800-845-8450, ext. 1807). For technical support: Todd Balog (816-654-1096). After 6 p.m., contact the AP Business News desk (800-845-8450, ext. 1680) for content questions; 1-800-3AP-STOX for technical support and 212-621-1905 for graphics help. CENTERPIECE Interest rate risk Just like a homeowner with an adjustable-rate mortgage, a corporation can also have debt with an interest rate that can move higher. And a higher rate will mean more expensive interest payments for companies repaying variable-rate debt, eating into their profits. UPCOMING: Graphic expected by 6 p.m. COMPANY SPOTLIGHT Dentsply buying rival Dental product company Dentsply is buying its rival Sirona for $5.51 billion. UPCOMING: Graphic expected by 6 p.m. | AG13: 1459
A14: 12 | B14: 43670.485 | C14: APRS000020151116ebbg00a3k | D14: None | E14: Keep | F14: =VLOOKUP(C14,InnovYes_Review!$A$2:$I$415,9,FALSE) -> 0 | G14: 1 | H14: 1 | I14: 1 | J14: LancasterVicki | K14: LancasterVicki | M14: No | S14: No | T14: Darzalex, known chemically as daratumumab, helps immune system cells attack malignant multiple myeloma cells by binding to a protein on their surface. The infused drug is then believed to trigger death of tumor cells though multiple mechanisms, according to Johnson & Johnson's Janssen biologic drug unit. Dr. Richard Pazdur, head of FDA's Office of Hematology and Oncology Products, said such targeting of proteins cancer cells' surface has led to important new cancer treatments. The FDA granted accelerated approval based on two studies showing Darzalex reduced the size of or eliminated tumors in about one-third of patients. In one study, 29 percent of the 106 participants responded to Darzalex for 7.4 months, on average, before tumor growth resumed. In the other study, which included 42 patients, 36 percent had their tumors reduced or eliminated. Janssen is conducting further testing. The biologic drug ‚Äî produced in living cells rather than by mixing chemicals together ‚Äî was approved for use in patients who have received three prior types of therapy and either didn't respond or relapsed after initial treatment, as is common with many cancer therapies. Patients in the studies had failed five treatments, on average. "Darzalex gives people who have limited or no remaining options ... a real chance," Janssen said in a statement. The infused drug is administered once weekly for the first two months and, if the patient continues responding, every two weeks for the next four months and then once per month. Each infusion has a list price of $5,850, according to Janssen, so for patients responding to Darzalex, 23 treatments over one year would cost $134,550. That's before any discounts insurers or other payers negotiate with J&J. Darzalex can reduce levels of red blood cells that carry oxygen through the body, infection-fighting white blood cells and platelets needed for blood clotting. It should not be taken by pregnant women. The most common side effects reported were nausea, fatigue, pain in the back or infusion site, fever and cough. "Multiple myeloma is a highly complex disease and remains incurable, with almost all patients relapsing or becoming resistant to therapy," Dr. Paul G. Richardson, a myeloma expert at the Dana-Farber Cancer Institute who participated in the patient testing, said in a statement. In trading Monday, J&J shares rose $1.34, or 1.3 percent, to $101.22. ___ Follow Linda A. Johnson @LindaJ_onPharma | U14: ['dfbcct', 'jonjon', 'jonjon', 'ntnct', 'usfda', 'jonjon', 'usfda', 'ntnct'] | V14: ['ntnct', 'usfda', 'jonjon'] | W14: The Associated Press | X14: ,usa,usnj,namz,use, | Y14: NAMZ USA | Z14: TRENTON, N.J. (AP) ‚Äî A Johnson & Johnson drug won Food and Drug Administration approval Monday for treating the incurable blood cancer multiple myeloma in patients who've failed prior therapies and have few options left. Darzalex is the first biologic drug and first monoclonal antibody ‚Äî a genetically engineered drug designed to target diseased tissue and spare healthy cells ‚Äî approved for multiple myeloma. The cancer, which occurs in infection-fighting white blood cells in the bone marrow, will strike 26,850 Americans and kill about 11,240 people in 2015, the National Cancer Institute estimates. | AA14: APRS | AB14: Associated Press Newswires | AC14: TRUE | AD14: ['c23', 'gcancr', 'cappro', 'gtrea', 'c13', 'c22', 'ccat', 'gcat', 'ghea', 'gmed', 'ncat', 'nfact', 'nfcpin'] | AE14: Johnson & Johnson multiple myeloma drug wins accelerated OK | AF14: Johnson & Johnson multiple myeloma drug wins accelerated OKDarzalex, known chemically as daratumumab, helps immune system cells attack malignant multiple myeloma cells by binding to a protein on their surface. The infused drug is then believed to trigger death of tumor cells though multiple mechanisms, according to Johnson & Johnson's Janssen biologic drug unit. Dr. Richard Pazdur, head of FDA's Office of Hematology and Oncology Products, said such targeting of proteins cancer cells' surface has led to important new cancer treatments. The FDA granted accelerated approval based on two studies showing Darzalex reduced the size of or eliminated tumors in about one-third of patients. In one study, 29 percent of the 106 participants responded to Darzalex for 7.4 months, on average, before tumor growth resumed. In the other study, which included 42 patients, 36 percent had their tumors reduced or eliminated. Janssen is conducting further testing. The biologic drug ‚Äî produced in living cells rather than by mixing chemicals together ‚Äî was approved for use in patients who have received three prior types of therapy and either didn't respond or relapsed after initial treatment, as is common with many cancer therapies. Patients in the studies had failed five treatments, on average. "Darzalex gives people who have limited or no remaining options ... a real chance," Janssen said in a statement. The infused drug is administered once weekly for the first two months and, if the patient continues responding, every two weeks for the next four months and then once per month. Each infusion has a list price of $5,850, according to Janssen, so for patients responding to Darzalex, 23 treatments over one year would cost $134,550. That's before any discounts insurers or other payers negotiate with J&J. Darzalex can reduce levels of red blood cells that carry oxygen through the body, infection-fighting white blood cells and platelets needed for blood clotting. It should not be taken by pregnant women. The most common side effects reported were nausea, fatigue, pain in the back or infusion site, fever and cough. "Multiple myeloma is a highly complex disease and remains incurable, with almost all patients relapsing or becoming resistant to therapy," Dr. Paul G. Richardson, a myeloma expert at the Dana-Farber Cancer Institute who participated in the patient testing, said in a statement. In trading Monday, J&J shares rose $1.34, or 1.3 percent, to $101.22. ___ Follow Linda A. Johnson @LindaJ_onPharma | AG14: 519
A15: 13 | B15: 43670.481 | C15: APRS000020151119ebbj00acv | D15: None | E15: Keep | F15: =VLOOKUP(C15,InnovYes_Review!$A$2:$I$415,9,FALSE) -> 0 | G15: 1 | H15: 2 | J15: HalewiczVictoria_KeastJessica | M15: No | S15: No | T15: The shares closed at $2.07 Wednesday and finished the trading day at $10.30, up about five-fold. In January KaloBios said a drug it was developing to treat lung infections in cystic fibrosis patients had failed in clinical testing. Its shares plunged 70 percent after that announcement and continued to decline after that. This month it said it would eliminate most of its jobs, leaving it with just 11 employees as it looked for strategic options. Last Friday, the company said it would wind down its operations. KaloBios said it is talking to Shkreli about ways to continue operating. The South San Francisco, California company owns several drug candidates, including potential treatments for leukemia and blood cancers. Shkreli is a former hedge fund manager and the head of privately-held Turing Pharmaceuticals. Turing was criticized in September for buying the rights to a parasitic infection treatment called Daraprim, then raising its price to $750 per pill from $13.50 a pill. Daraprim has been on the market for more than 60 years and it did not have any competition when Turing bought it. Turing has said it will lower the price, although that hasn't happened yet. The company said it capped copayments for patients at $10. In October a San Diego company later said it would make a version of Daraprim available for about $1 a pill. Shkreli and Turing Pharmaceuticals did not immediately respond to a request for comment. Turing was not the first company to buy an old, inexpensive medicine and hike the price. The uproar over its actions and similar moves by other companies helped start government investigations, proposals by politicians to fight "price gouging," heavy media scrutiny and a drop in stock prices for biotech companies. | U15: ['klbspi', 'klbspi', 'klbspi', 'turiph', 'turiph'] | V15: ['klbspi'] | W15: The Associated Press | X15: ,usa,namz, | Y15: NAMZ USA | Z15: NEW YORK (AP) ‚Äî Shares of cancer drug developer KaloBios Pharmaceuticals rocketed higher Thursday after controversial investor Martin Shkreli led a group that took a majority stake in the company just after it had decided to wind down its operations. KaloBios shares surged as high as $14.72 Thursday after the company said an investor group including Shkreli had acquired most of its stock. It made that announcement after the market closed on Wednesday. | AA15: APRS | AB15: Associated Press Newswires | AC15: FALSE | AD15: ['ghea', 'gcat'] | AE15: KaloBios stock rockets after investment from Shkreli | AF15: KaloBios stock rockets after investment from ShkreliThe shares closed at $2.07 Wednesday and finished the trading day at $10.30, up about five-fold. In January KaloBios said a drug it was developing to treat lung infections in cystic fibrosis patients had failed in clinical testing. Its shares plunged 70 percent after that announcement and continued to decline after that. This month it said it would eliminate most of its jobs, leaving it with just 11 employees as it looked for strategic options. Last Friday, the company said it would wind down its operations. KaloBios said it is talking to Shkreli about ways to continue operating. The South San Francisco, California company owns several drug candidates, including potential treatments for leukemia and blood cancers. Shkreli is a former hedge fund manager and the head of privately-held Turing Pharmaceuticals. Turing was criticized in September for buying the rights to a parasitic infection treatment called Daraprim, then raising its price to $750 per pill from $13.50 a pill. Daraprim has been on the market for more than 60 years and it did not have any competition when Turing bought it. Turing has said it will lower the price, although that hasn't happened yet. The company said it capped copayments for patients at $10. In October a San Diego company later said it would make a version of Daraprim available for about $1 a pill. Shkreli and Turing Pharmaceuticals did not immediately respond to a request for comment. Turing was not the first company to buy an old, inexpensive medicine and hike the price. The uproar over its actions and similar moves by other companies helped start government investigations, proposals by politicians to fight "price gouging," heavy media scrutiny and a drop in stock prices for biotech companies. | AG15: 375
A16: 15 | B16: 43670.494 | C16: ATEHEA0020150512eb5c00001 | D16: Keep | E16: Keep | F16: =VLOOKUP(C16,InnovYes_Review!$A$2:$I$415,9,FALSE) -> 0 | G16: 1 | H16: 1 | I16: 1 | J16: Extra5 | K16: Extra5 | M16: Yes | N16: Approved by FDA and scheduled to be launched | O16: HF10 therapy, HF10 | Q16: No | R16: No | S16: No | T16: The Senza SCS system is indicated as an aid in the management of chronic intractable pain of the trunk and/or limbs, including unilateral or bilateral pain associated with failed back surgery syndrome, intractable low back pain and leg pain. The Senza system delivering HF10 therapy has experienced strong adoption in Europe and Australia over the past 5 years. With this FDA approval, patients in the U.S. suffering from chronic pain will have the opportunity to experience the significant benefits of HF10 therapy. The labelling for the Senza system and HF10 therapy was based on the SENZA-RCT clinical trial, where HF10 therapy was meaningfully superior to traditional SCS therapy for back and leg pain, including superior response rates, pain relief, and functional outcomes. Superiority was demonstrated in the primary and all secondary endpoints including at every measurement time point throughout the 12 month follow up. | U16: ['nevroc', 'nevroc', 'nevroc', 'usfda', 'usfda', 'usfda'] | V16: ['usfda', 'nevroc'] | W16: Elets Technomedia Pvt. Ltd. | X16: ,india,usa,asiaz,bric,devgcoz,dvpcoz,indsubz,namz,sasiaz, | Y16: ASIA INDIA SASIAZ SEASIAZ | Z16: Nevro Corp. has announced that it has received approval from the United States Food and Drug Administration (FDA) for its Senza spinal cord stimulation (SCS) system. The Senza system is the only SCS system that delivers Nevro's proprietary HF10 therapy. Senza, HF10, Nevro and the Nevro logo are trademarks of Nevro. | AA16: ATEHEA | AB16: eHealth | AC16: TRUE | AD16: ['cappro', 'ghea', 'c13', 'c22', 'ccat', 'gcat', 'ncat', 'nfact', 'nfcpin'] | AE16: Nevro Receives FDA Approval for SCS System | AF16: Nevro Receives FDA Approval for SCS SystemThe Senza SCS system is indicated as an aid in the management of chronic intractable pain of the trunk and/or limbs, including unilateral or bilateral pain associated with failed back surgery syndrome, intractable low back pain and leg pain. The Senza system delivering HF10 therapy has experienced strong adoption in Europe and Australia over the past 5 years. With this FDA approval, patients in the U.S. suffering from chronic pain will have the opportunity to experience the significant benefits of HF10 therapy. The labelling for the Senza system and HF10 therapy was based on the SENZA-RCT clinical trial, where HF10 therapy was meaningfully superior to traditional SCS therapy for back and leg pain, including superior response rates, pain relief, and functional outcomes. Superiority was demonstrated in the primary and all secondary endpoints including at every measurement time point throughout the 12 month follow up. | AG16: 210
A17: 16 | B17: 43670.47 | C17: ATPATN0020150601eb610000g | D17: None | E17: Keep | F17: =VLOOKUP(C17,InnovYes_Review!$A$2:$I$415,9,FALSE) -> 0 | G17: 1 | H17: 2 | J17: Extra2_PocinkiAllegra | M17: No | S17: No | T17: The abstract of the patent published by the Controller General of Patents, Designs & Trade Marks states: "This invention provides novel pharmaceutical compositions of the compound of formula (I): or a pharmaceutically acceptable salt thereof, that are suitable for the bulk production of an oral pharmaceutical dosage form; processes for the production of said oral pharmaceutical dosage form; and the use of the pharmaceutical composition for the treatment of patients suffering from or subject to diseases, disorders, or conditions involving cell survival, proliferation and migration, including chronic inflammatory proliferative disorders, proliferative ocular disorders, benign proliferative disorders, and cancer." The Patent was published in the Issue No. 20/2015 of the Patent Office Journal on May 15, 2015. | U17: ['millph', 'millph', 'millph', 'tkdci'] | V17: ['millph'] | W17: Athena Information Solutions Pvt. Ltd. | X17: ,india,kolk,usa,asiaz,bric,devgcoz,dvpcoz,indsubz,namz,sasiaz,wbeng, | Y17: ASIA INDIA SASIAZ | Z17: Kolkata, June 1 -- USA-based Millennium Pharmaceuticals Inc filed patent application for pharmaceutical compositions for the treatment of cancer and other diseases or disorders. The inventors are Vijayalakshmi Ramanan, Irene Sophie Tobias, Dauntel Specht Verwijs and Raymond D Skwierczynski. Millennium Pharmaceuticals Inc filed the patent application on Feb 10, 2012. The patent application number is 1237/DELNP/2012 A. The international classification number is A61K 9/08. | AA17: ATPATN | AB17: Indian Patent News | AC17: FALSE | AD17: ['c133', 'ghea', 'ccat', 'cgymtr', 'cinprp', 'gcat'] | AE17: Millennium Pharmaceuticals Inc Files Patent Application for Pharmaceutical Compositions for the Treatment of Cancer and Other Diseases or Disorders | AF17: Millennium Pharmaceuticals Inc Files Patent Application for Pharmaceutical Compositions for the Treatment of Cancer and Other Diseases or DisordersThe abstract of the patent published by the Controller General of Patents, Designs & Trade Marks states: "This invention provides novel pharmaceutical compositions of the compound of formula (I): or a pharmaceutically acceptable salt thereof, that are suitable for the bulk production of an oral pharmaceutical dosage form; processes for the production of said oral pharmaceutical dosage form; and the use of the pharmaceutical composition for the treatment of patients suffering from or subject to diseases, disorders, or conditions involving cell survival, proliferation and migration, including chronic inflammatory proliferative disorders, proliferative ocular disorders, benign proliferative disorders, and cancer." The Patent was published in the Issue No. 20/2015 of the Patent Office Journal on May 15, 2015. | AG17: 207
A18: 505 | C18: ATPHAB0020150119eb1j00006 | D18: None | E18: Keep | F18: =VLOOKUP(C18,InnovYes_Review!$A$2:$I$415,9,FALSE) -> 0 | G18: 1 | H18: 1 | I18: 1 | J18: PristavecTeja | K18: PristavecTeja | L18: PristavecTeja | M18: No_by_Default | S18: Yes | T18: Orphan Drug Designation is granted by the FDA Orphan Drug Designation program for medicines intended for the safe and effective treatment, diagnosis or prevention of rare diseases or disorders that affect fewer than 200,000 people in the United States. Orphan Drug Designation provides sponsors with development and commercial incentives for such designated compounds and medicines. Classic CAH is a genetic disorder that results in an enzyme deficiency altering the production of adrenal steroids. Because of this deficiency, the adrenal glands have little to no cortisol biosynthesis resulting in a potentially life-threatening condition. If left untreated, classic CAH can result in salt wasting, dehydration and eventually death. Even with cortisol replacement, persistent elevation of ACTH from the pituitary gland results in excessive androgen levels leading to virilization of females including precocious puberty, menstrual irregularity, short stature, hirsutism, acne and fertility problems. Corticosteroids are the current standard of care for classic CAH which are used to both correct the endogenous cortisol deficiency and reduce the excessive ACTH levels and androgen excess. However, the dose and duration of steroid use required to suppress ACTH is well above the normal physiological level of cortisol resulting in metabolic syndrome, bone loss, growth impairment, and Cushing's syndrome as common and serious side effects. NBI-77860 is a potent, selective non-peptide CRF receptor antagonist as demonstrated in a range of in vitro/in vivo assays and human clinical studies. Blockade of CRF receptors at the pituitary has been shown to decrease the release of ACTH, which in turn decreases the production of adrenal steroids including androgens, and potentially the symptoms associated with classic CAH. Lower ACTH levels would also reduce the amount of exogenous corticosteroid necessary for classic CAH patients to thrive avoiding the side-effects currently associated with excessive steroid therapy. The 1401 study is a phase I/II open-label, sequential cohort, single ascending dose pharmacokinetic/pharmacodynamic study assessing three doses of NBI-77860. The fifteen adolescent females with classic CAH will be split into three cohorts and each will receive one dose of NBI-77860 at bedtime. Biomarker measurements include ACTH, 17-OHP, androgen, and cortisol levels collected the day after dosing. Neurocrine Biosciences, Inc. discovers and develops innovative and life-changing pharmaceuticals, in diseases with high unmet medical needs, through its novel R&D; platform, focussed on neurological and endocrine based diseases and disorders. The Company's two lead late-stage clinical programs are elagolix, a gonadotropin-releasing hormone antagonist for women's health that is partnered with AbbVie Inc., and a wholly owned vesicular monoamine transporter 2 inhibitor for the treatment of movement disorders. Neurocrine intends to maintain certain commercial rights to its VMAT2 inhibitor for evolution into a fully-integrated pharmaceutical company. In addition to historical facts, this press release may contain forward-looking statements that involve a number of risks and uncertainties. Among the factors that could cause actual results to differ materially from those indicated in the forward-looking statements are risks and uncertainties associated with Neurocrine's business and finances in general, as well as risks and uncertainties associated with the Company's CRF program and Company overall. Specifically, the risks and uncertainties the Company faces with respect to the Company's CRF program include, but are not limited to; risk that NBI-77860 will not proceed to later stage clinical trials and risk that the Company's clinical trials will fail to demonstrate that NBI-77860 is safe and effective, risk that NBI-77860 may not replicate the results observed in our prior clinical development, risk that NB. | U18: ['neubio', 'usfda', 'abvbba', 'neubio', 'neubio', 'usfda', 'usfda'] | V18: ['usfda', 'neubio'] | W18: Saffron Media Pvt Ltd | X18: ,usa,namz, | Y18: ASIA INDIA SASIAZ | Z18: The United States Food and Drug Administration (FDA) has granted orphan drug status to Neurocrine Biosciences' NBI-77860, a proprietary corticotropin releasing factor 1 (CRF) receptor antagonist, for the treatment of congenital adrenal hyperplasia (CAH) a disease that affects approximately 20,000-30,000 people in the United States. "We are very pleased that the FDA has granted NBI-77860 orphan status to treat congenital adrenal hyperplasia, a devastating disease that is a significant challenge for both clinicians and patients," said Malcolm Lloyd-Smith, chief regulatory officer of Neurocrine Biosciences. "This status represents a significant regulatory milestone for the CAH programme and underscores the importance of bringing a safe and effective CAH therapy to market. We look forward to the results from our recently initiated 1401 Study of adolescents with classic CAH, in 2015." | AA18: ATPHAB | AB18: PharmaBiz | AC18: FALSE | AD18: ['c23', 'gtrea', 'ccat', 'gcat', 'ghea'] | AE18: US FDA grants orphan drug status to Neurocrine's NBI-77860 for congenital adrenal hyperplasia treatment | AF18: US FDA grants orphan drug status to Neurocrine's NBI-77860 for congenital adrenal hyperplasia treatmentOrphan Drug Designation is granted by the FDA Orphan Drug Designation program for medicines intended for the safe and effective treatment, diagnosis or prevention of rare diseases or disorders that affect fewer than 200,000 people in the United States. Orphan Drug Designation provides sponsors with development and commercial incentives for such designated compounds and medicines. Classic CAH is a genetic disorder that results in an enzyme deficiency altering the production of adrenal steroids. Because of this deficiency, the adrenal glands have little to no cortisol biosynthesis resulting in a potentially life-threatening condition. If left untreated, classic CAH can result in salt wasting, dehydration and eventually death. Even with cortisol replacement, persistent elevation of ACTH from the pituitary gland results in excessive androgen levels leading to virilization of females including precocious puberty, menstrual irregularity, short stature, hirsutism, acne and fertility problems. Corticosteroids are the current standard of care for classic CAH which are used to both correct the endogenous cortisol deficiency and reduce the excessive ACTH levels and androgen excess. However, the dose and duration of steroid use required to suppress ACTH is well above the normal physiological level of cortisol resulting in metabolic syndrome, bone loss, growth impairment, and Cushing's syndrome as common and serious side effects. NBI-77860 is a potent, selective non-peptide CRF receptor antagonist as demonstrated in a range of in vitro/in vivo assays and human clinical studies. Blockade of CRF receptors at the pituitary has been shown to decrease the release of ACTH, which in turn decreases the production of adrenal steroids including androgens, and potentially the symptoms associated with classic CAH. Lower ACTH levels would also reduce the amount of exogenous corticosteroid necessary for classic CAH patients to thrive avoiding the side-effects currently associated with excessive steroid therapy. The 1401 study is a phase I/II open-label, sequential cohort, single ascending dose pharmacokinetic/pharmacodynamic study assessing three doses of NBI-77860. The fifteen adolescent females with classic CAH will be split into three cohorts and each will receive one dose of NBI-77860 at bedtime. Biomarker measurements include ACTH, 17-OHP, androgen, and cortisol levels collected the day after dosing. Neurocrine Biosciences, Inc. discovers and develops innovative and life-changing pharmaceuticals, in diseases with high unmet medical needs, through its novel R&D; platform, focussed on neurological and endocrine based diseases and disorders. The Company's two lead late-stage clinical programs are elagolix, a gonadotropin-releasing hormone antagonist for women's health that is partnered with AbbVie Inc., and a wholly owned vesicular monoamine transporter 2 inhibitor for the treatment of movement disorders. Neurocrine intends to maintain certain commercial rights to its VMAT2 inhibitor for evolution into a fully-integrated pharmaceutical company. In addition to historical facts, this press release may contain forward-looking statements that involve a number of risks and uncertainties. Among the factors that could cause actual results to differ materially from those indicated in the forward-looking statements are risks and uncertainties associated with Neurocrine's business and finances in general, as well as risks and uncertainties associated with the Company's CRF program and Company overall. Specifically, the risks and uncertainties the Company faces with respect to the Company's CRF program include, but are not limited to; risk that NBI-77860 will not proceed to later stage clinical trials and risk that the Company's clinical trials will fail to demonstrate that NBI-77860 is safe and effective, risk that NBI-77860 may not replicate the results observed in our prior clinical development, risk that NB. | AG18: 752
A19: 17 | B19: 43671.593 | C19: ATPHAB0020150317eb3h0002t | D19: Keep | E19: Keep | F19: =VLOOKUP(C19,InnovYes_Review!$A$2:$I$415,9,FALSE) -> 0 | G19: 1 | M19: Yes | N19: Approved by FDA but not scheduled to be launched | O19: Watchman LAAC Device | P19: Boston Scientific | Q19: Unsure | R19: Unsure | S19: No | T19: The Watchman Device is indicated to reduce the risk of thromboembolism from the left atrial appendage in patients with non-valvular atrial fibrillation who are at increased risk for stroke and systemic embolism based on CHADS2 or CHA2DS2-VASc scores, are deemed by their physicians to be suitable for warfarin; and have an appropriate rationale to seek a non-pharmacologic alternative to warfarin, taking into account the safety and effectiveness of the device compared to warfarin. "The Watchman Device is an important step forward in stroke management for patients with AF," said Vivek Reddy, M.D., Director of the Cardiac Arrhythmia Service at the Mount Sinai Medical Center and co-principal investigator of the PROTECT AF and PREVAIL studies. "We know that up to 40 per cent of patients who are eligible for oral anticoagulation do not take it for numerous reasons1, highlighting the need for additional treatment options. The Watchman Device is a breakthrough treatment providing those patients who are suitable for warfarin with an implant-based alternative to long-term warfarin therapy while still reducing the risk of stroke." The FDA approval of the Watchman Device is based on the robust Watchman clinical programme which consists of numerous studies, with more than 2,400 patients and nearly 6,000 patient-years of follow-up. The Watchman clinical program provided strong evidence that the Watchman Device can be implanted safely and reduces the risk of stroke in eligible patients while enabling most patients to discontinue warfarin. Additionally, a meta-analysis of all of the randomized trial data demonstrated that while ischemic stroke reduction favored warfarin, the Watchman Device provided patients with a comparable protection against all-cause stroke and statistically superior reductions in hemorrhagic stroke, disabling stroke, and cardiovascular death compared to warfarin over long-term follow-up. "Today marks a defining moment in the company's journey towards establishing left atrial appendage closure therapy in the United States. Boston Scientific is proud to offer this potentially life-changing stroke risk treatment option to high-risk patients with AF who have a reason to seek a non-drug alternative to warfarin. This therapy could free them from the challenges of long-term warfarin therapy," said Joe Fitzgerald, executive vice president and president, Rhythm Management, Boston Scientific. "FDA approval of the Watchman Device is another example of Boston Scientific delivering on its commitment to bring meaningful innovations to patient care." The Watchman Device has been commercially available internationally since 2009 and is the leading device in percutaneous left atrial appendage closure globally. It is registered in 75 countries and more than 10,000 patients have been treated with the Watchman Device. The Watchman LAAC Device is a catheter-delivered heart implant designed to close the left atrial appendage (LAA) in order to prevent the migration of blood clots from the LAA, and thus, reduce the incidence of stroke and systemic embolism for higher risk patients with non-valvular AF. The LAA is a thin, sack-like appendix arising from the heart and is believed to be the source of >90 percent of stroke-causing clots that come from the left atrium in patients with non-valvular AF. Boston Scientific transforms lives through innovative medical solutions that improve the health of patients around the world. As a global medical technology leader for more than 35 years, the company advance science for life by providing a broad range of high performance solutions that address unmet patient needs and reduce the cost of healthcare. | U19: ['usfda', 'bosts', 'bosts', 'usfda', 'bosts'] | V19: ['bosts', 'usfda'] | W19: Saffron Media Pvt Ltd | X19: ,usa,namz, | Y19: ASIA INDIA SASIAZ | Z19: The US Food and Drug Administration (FDA) has approved Boston Scientific Corporation's Watchman Left Atrial Appendage Closure Device. The Watchman Device offers a new stroke risk reduction option for high-risk patients with non-valvular atrial fibrillation who are seeking an alternative to long-term warfarin therapy. The Watchman Device will be made available to US centers involved in our clinical studies and additional, specialized centers as physicians are trained on the implant procedure. | AA19: ATPHAB | AB19: PharmaBiz | AC19: TRUE | AD19: ['cappro', 'gstrok', 'c13', 'c22', 'ccat', 'gcat', 'ghea', 'gmed', 'ncat', 'nfact', 'nfcpin'] | AE19: US FDA approves Boston Scientific's Watchman left atrial appendage closure device | AF19: US FDA approves Boston Scientific's Watchman left atrial appendage closure deviceThe Watchman Device is indicated to reduce the risk of thromboembolism from the left atrial appendage in patients with non-valvular atrial fibrillation who are at increased risk for stroke and systemic embolism based on CHADS2 or CHA2DS2-VASc scores, are deemed by their physicians to be suitable for warfarin; and have an appropriate rationale to seek a non-pharmacologic alternative to warfarin, taking into account the safety and effectiveness of the device compared to warfarin. "The Watchman Device is an important step forward in stroke management for patients with AF," said Vivek Reddy, M.D., Director of the Cardiac Arrhythmia Service at the Mount Sinai Medical Center and co-principal investigator of the PROTECT AF and PREVAIL studies. "We know that up to 40 per cent of patients who are eligible for oral anticoagulation do not take it for numerous reasons1, highlighting the need for additional treatment options. The Watchman Device is a breakthrough treatment providing those patients who are suitable for warfarin with an implant-based alternative to long-term warfarin therapy while still reducing the risk of stroke." The FDA approval of the Watchman Device is based on the robust Watchman clinical programme which consists of numerous studies, with more than 2,400 patients and nearly 6,000 patient-years of follow-up. The Watchman clinical program provided strong evidence that the Watchman Device can be implanted safely and reduces the risk of stroke in eligible patients while enabling most patients to discontinue warfarin. Additionally, a meta-analysis of all of the randomized trial data demonstrated that while ischemic stroke reduction favored warfarin, the Watchman Device provided patients with a comparable protection against all-cause stroke and statistically superior reductions in hemorrhagic stroke, disabling stroke, and cardiovascular death compared to warfarin over long-term follow-up. "Today marks a defining moment in the company's journey towards establishing left atrial appendage closure therapy in the United States. Boston Scientific is proud to offer this potentially life-changing stroke risk treatment option to high-risk patients with AF who have a reason to seek a non-drug alternative to warfarin. This therapy could free them from the challenges of long-term warfarin therapy," said Joe Fitzgerald, executive vice president and president, Rhythm Management, Boston Scientific. "FDA approval of the Watchman Device is another example of Boston Scientific delivering on its commitment to bring meaningful innovations to patient care." The Watchman Device has been commercially available internationally since 2009 and is the leading device in percutaneous left atrial appendage closure globally. It is registered in 75 countries and more than 10,000 patients have been treated with the Watchman Device. The Watchman LAAC Device is a catheter-delivered heart implant designed to close the left atrial appendage (LAA) in order to prevent the migration of blood clots from the LAA, and thus, reduce the incidence of stroke and systemic embolism for higher risk patients with non-valvular AF. The LAA is a thin, sack-like appendix arising from the heart and is believed to be the source of >90 percent of stroke-causing clots that come from the left atrium in patients with non-valvular AF. Boston Scientific transforms lives through innovative medical solutions that improve the health of patients around the world. As a global medical technology leader for more than 35 years, the company advance science for life by providing a broad range of high performance solutions that address unmet patient needs and reduce the cost of healthcare. | AG19: 672
A20: 19 | B20: 43670.491 | C20: ATPHAB0020150514eb5e0005o | D20: Keep | E20: Keep | F20: =VLOOKUP(C20,InnovYes_Review!$A$2:$I$415,9,FALSE) -> 0 | G20: 1 | H20: 1 | I20: 1 | J20: KeastJessica | K20: KeastJessica | M20: Yes | N20: FDA application submission and/or FDA testing | O20: Orkambi | P20: Vertex | Q20: Yes | R20: Yes | S20: No | T20: Advisory committees provide the FDA with independent scientific and medical advice on safety, effectiveness and appropriate use of potential new medicines. The FDA is expected to make a decision on the approval of Orkambi by July 5, 2015 under the Prescription Drug User Fee Act (PDUFA). The FDA is not bound by the committee's recommendation but often follows its advice. If approved, Orkambi will be the first and only medicine to treat the underlying cause of CF for eligible people with CF ages 12 and older with two copies of the F508del mutation in the CFTR gene. People with two copies of the F508del mutation represent the largest group of people with CF. There are approximately 8,500 people ages 12 and older with two copies of the F508del mutation in the US. "Today's positive recommendation brings the cystic fibrosis community one step closer to potential approval of the first medicine to treat the underlying cause of this disease for many more people," said Jeffrey Chodakewitz, M.D., executive vice president and chief medical officer at Vertex. "We look forward to continuing to work with the FDA and other regulatory agencies throughout the world to make Orkambi available to eligible patients as soon as possible." Cystic fibrosis is a rare genetic disease that is caused by defective or missing CFTR proteins resulting from mutations in the CFTR gene. The defective or missing proteins result in poor flow of salt and water into and out of the cell in a number of organs, including the lungs. In people with two copies of the F508del mutation, the CFTR protein is not processed and trafficked normally within the cell, resulting in little to no CFTR protein at the cell surface. Orkambi is a combination of lumacaftor, which is designed to increase the amount of functional protein at the cell surface by addressing the processing and trafficking defect of the protein, and ivacaftor, which is designed to enhance the function of the CFTR protein once it reaches the cell surface. Orkambi is an oral medicine that, if approved, would be taken as fully co-formulated tablets that contain both lumacaftor and ivacaftor. Vertex initiated its CF research programme in 1998 as part of a collaboration with Cystic Fibrosis Foundation Therapeutics (CFFT), the nonprofit drug discovery and development affiliate of the Cystic Fibrosis Foundation. This collaboration was expanded to support the accelerated discovery and development of Vertex's CFTR modulators. Vertex is a global biotechnology company that aims to discover, develop and commercialize innovative medicines so people with serious diseases can lead better lives. | U20: ['usfda', 'verpha', 'cystc', 'usfda', 'usfda', 'verpha', 'verpha'] | V20: ['verpha', 'usfda'] | W20: Saffron Media Pvt Ltd | X20: ,usa,namz, | Y20: ASIA INDIA SASIAZ | Z20: The US Food and Drug Administration's (FDA) Pulmonary-Allergy Drugs Advisory Committee (PADAC) voted 12 to 1 to recommend the approval of Vertex Pharmaceuticals' Orkambi (lumacaftor/ivacaftor) for use in people with cystic fibrosis (CF) ages 12 and older who have two copies of the F508del mutation in the CFTR gene. | AA20: ATPHAB | AB20: PharmaBiz | AC20: TRUE | AD20: ['cappro', 'c131', 'c13', 'c22', 'ccat', 'ncat', 'nfact', 'nfcpin'] | AE20: US FDA committee recommends approval of Vertex Pharma's Orkambi to treat people with CF ages 12 and older | AF20: US FDA committee recommends approval of Vertex Pharma's Orkambi to treat people with CF ages 12 and olderAdvisory committees provide the FDA with independent scientific and medical advice on safety, effectiveness and appropriate use of potential new medicines. The FDA is expected to make a decision on the approval of Orkambi by July 5, 2015 under the Prescription Drug User Fee Act (PDUFA). The FDA is not bound by the committee's recommendation but often follows its advice. If approved, Orkambi will be the first and only medicine to treat the underlying cause of CF for eligible people with CF ages 12 and older with two copies of the F508del mutation in the CFTR gene. People with two copies of the F508del mutation represent the largest group of people with CF. There are approximately 8,500 people ages 12 and older with two copies of the F508del mutation in the US. "Today's positive recommendation brings the cystic fibrosis community one step closer to potential approval of the first medicine to treat the underlying cause of this disease for many more people," said Jeffrey Chodakewitz, M.D., executive vice president and chief medical officer at Vertex. "We look forward to continuing to work with the FDA and other regulatory agencies throughout the world to make Orkambi available to eligible patients as soon as possible." Cystic fibrosis is a rare genetic disease that is caused by defective or missing CFTR proteins resulting from mutations in the CFTR gene. The defective or missing proteins result in poor flow of salt and water into and out of the cell in a number of organs, including the lungs. In people with two copies of the F508del mutation, the CFTR protein is not processed and trafficked normally within the cell, resulting in little to no CFTR protein at the cell surface. Orkambi is a combination of lumacaftor, which is designed to increase the amount of functional protein at the cell surface by addressing the processing and trafficking defect of the protein, and ivacaftor, which is designed to enhance the function of the CFTR protein once it reaches the cell surface. Orkambi is an oral medicine that, if approved, would be taken as fully co-formulated tablets that contain both lumacaftor and ivacaftor. Vertex initiated its CF research programme in 1998 as part of a collaboration with Cystic Fibrosis Foundation Therapeutics (CFFT), the nonprofit drug discovery and development affiliate of the Cystic Fibrosis Foundation. This collaboration was expanded to support the accelerated discovery and development of Vertex's CFTR modulators. Vertex is a global biotechnology company that aims to discover, develop and commercialize innovative medicines so people with serious diseases can lead better lives. | AG20: 506
A21: 20 | B21: 43670.493 | C21: ATPHAB0020151019ebaj00036 | D21: None | E21: Keep | F21: =VLOOKUP(C21,InnovYes_Review!$A$2:$I$415,9,FALSE) -> 0 | G21: 3 | H21: 3 | J21: Extra4_LancasterVicki_PocinkiAllegra | M21: No | S21: No | T21: Each partner will bring its respective world-leading expertise and technologies to the GHVCI and, collectively, the parties will collaborate with a wide range of other vaccine development organizations. Funding for the establishment, operation and growth of the GHVCI will come from Sanofi and the Gates Foundation, and additional funding will be sought to support collaborative research activities with respect to specific vaccines to be developed at the GHVCI. This distinctive collaboration leverages the potential power of the partners' collective expertise, combining IDRI's vaccine design, formulation and production technologies; Sanofi's position as a leading multi-national vaccine developer, manufacturer and seller; and the Gates Foundation's knowledge, influence and financial support regarding the discovery and development of global health interventions, including vaccines. A key component is the application of IDRI's vaccine adjuvant technologies and formulation expertise, which have been developed over the past few years with strong financial support from the Gates Foundation. These adjuvant technologies are uniquely designed to improve immune responses, broaden vaccine protection and significantly save costs by reducing the amount of vaccine needed. According to the World Health Organisation, vaccines have greatly reduced the burden of infectious diseases, including death tolls, disability and inequity, making "formerly fearsome" diseases a rarity in many parts of the world. "History has shown us that vaccines are one of the best ways to improve public health, but in today's world, we are faced with a newly emerging infectious diseases, as well as age-old threats, that either have no vaccines or vaccines that are not effective," said Steven G. Reed, Ph.D., founder, president and chief scientific officer for IDRI. "Combining that with the speed with which infectious diseases can travel the world, we need a new model for vaccine development, one that enables us to rapidly produce vaccines at a lower cost. The blend of the Gates Foundation's knowledge of global health and Sanofi's depth of vaccine development expertise is a perfect match for IDRI's unique technologies and research and development engine, allowing us to take a new approach to vaccine development." A Joint Steering Committee, comprised of representatives from each of the three partners, will mutually identify areas of research to discover, evaluate and develop novel human vaccines, as well as adjuvant/formulation platforms for the rapid response to emerging pathogens, that can prevent or treat infectious diseases. Initial funding will be used to establish and operate the GHVCI, build capacity as the collaboration grows, and provide management and scientific recruitment as well as training. "We are excited to be involved in this novel partnership and proud of the confidence shown in IDRI's technology and our science team's expertise by these two powerhouses, Sanofi and the Gates Foundation," said Erik Iverson, IDRI's president, business and operations. "IDRI has a proven history of developing global health products that have a positive impact. This alliance will significantly accelerate the development of a wide range of vaccines and other health interventions that will save the lives of millions of people globally." | U21: ['apaste', 'iidrii', 'apaste', 'apaste', 'bimega', 'bimega', 'iidrii', 'iidrii', 'sansyn', 'sansyn', 'whoz', 'bimega', 'sansyn'] | V21: ['sansyn', 'bimega', 'iidrii', 'apaste'] | W21: Saffron Media Pvt Ltd | X21: ,usa,namz, | Y21: ASIA INDIA SASIAZ | Z21: In an effort to accelerate timelines and decrease development costs of life-saving vaccines, the Infectious Disease Research Institute (IDRI) and Sanofi Pasteur announced the establishment of the Global Health Vaccine Center of Innovation (GHVCI), to be headquartered at IDRI in Seattle. This project is funded in part by a grant from the Bill & Melinda Gates Foundation. The GHVCI represents an alliance among the three organisations, focused on accelerating the development of vaccines and associated technologies to fight a wide range of global infectious diseases, and ensuring that these critical vaccines are accessible globally, especially to people in need within developing countries. | AA21: ATPHAB | AB21: PharmaBiz | AC21: TRUE | AD21: ['c22', 'c23', 'ccat', 'ncat', 'nfact', 'nfcpin'] | AE21: IDRI, Sanofi Pasteur join hands to develop new model for vaccine development | AF21: IDRI, Sanofi Pasteur join hands to develop new model for vaccine developmentEach partner will bring its respective world-leading expertise and technologies to the GHVCI and, collectively, the parties will collaborate with a wide range of other vaccine development organizations. Funding for the establishment, operation and growth of the GHVCI will come from Sanofi and the Gates Foundation, and additional funding will be sought to support collaborative research activities with respect to specific vaccines to be developed at the GHVCI. This distinctive collaboration leverages the potential power of the partners' collective expertise, combining IDRI's vaccine design, formulation and production technologies; Sanofi's position as a leading multi-national vaccine developer, manufacturer and seller; and the Gates Foundation's knowledge, influence and financial support regarding the discovery and development of global health interventions, including vaccines. A key component is the application of IDRI's vaccine adjuvant technologies and formulation expertise, which have been developed over the past few years with strong financial support from the Gates Foundation. These adjuvant technologies are uniquely designed to improve immune responses, broaden vaccine protection and significantly save costs by reducing the amount of vaccine needed. According to the World Health Organisation, vaccines have greatly reduced the burden of infectious diseases, including death tolls, disability and inequity, making "formerly fearsome" diseases a rarity in many parts of the world. "History has shown us that vaccines are one of the best ways to improve public health, but in today's world, we are faced with a newly emerging infectious diseases, as well as age-old threats, that either have no vaccines or vaccines that are not effective," said Steven G. Reed, Ph.D., founder, president and chief scientific officer for IDRI. "Combining that with the speed with which infectious diseases can travel the world, we need a new model for vaccine development, one that enables us to rapidly produce vaccines at a lower cost. The blend of the Gates Foundation's knowledge of global health and Sanofi's depth of vaccine development expertise is a perfect match for IDRI's unique technologies and research and development engine, allowing us to take a new approach to vaccine development." A Joint Steering Committee, comprised of representatives from each of the three partners, will mutually identify areas of research to discover, evaluate and develop novel human vaccines, as well as adjuvant/formulation platforms for the rapid response to emerging pathogens, that can prevent or treat infectious diseases. Initial funding will be used to establish and operate the GHVCI, build capacity as the collaboration grows, and provide management and scientific recruitment as well as training. "We are excited to be involved in this novel partnership and proud of the confidence shown in IDRI's technology and our science team's expertise by these two powerhouses, Sanofi and the Gates Foundation," said Erik Iverson, IDRI's president, business and operations. "IDRI has a proven history of developing global health products that have a positive impact. This alliance will significantly accelerate the development of a wide range of vaccines and other health interventions that will save the lives of millions of people globally." | AG21: 629
A22: 21 | B22: 43670.494 | C22: ATPHAB0020151019ebaj00036 | D22: Throw | E22: Throw | F22: =VLOOKUP(C22,InnovYes_Review!$A$2:$I$415,9,FALSE) -> 0 | G22: 3 | H22: 3 | J22: Extra4_LancasterVicki_PocinkiAllegra | M22: No | S22: No | T22: Each partner will bring its respective world-leading expertise and technologies to the GHVCI and, collectively, the parties will collaborate with a wide range of other vaccine development organizations. Funding for the establishment, operation and growth of the GHVCI will come from Sanofi and the Gates Foundation, and additional funding will be sought to support collaborative research activities with respect to specific vaccines to be developed at the GHVCI. This distinctive collaboration leverages the potential power of the partners' collective expertise, combining IDRI's vaccine design, formulation and production technologies; Sanofi's position as a leading multi-national vaccine developer, manufacturer and seller; and the Gates Foundation's knowledge, influence and financial support regarding the discovery and development of global health interventions, including vaccines. A key component is the application of IDRI's vaccine adjuvant technologies and formulation expertise, which have been developed over the past few years with strong financial support from the Gates Foundation. These adjuvant technologies are uniquely designed to improve immune responses, broaden vaccine protection and significantly save costs by reducing the amount of vaccine needed. According to the World Health Organisation, vaccines have greatly reduced the burden of infectious diseases, including death tolls, disability and inequity, making "formerly fearsome" diseases a rarity in many parts of the world. "History has shown us that vaccines are one of the best ways to improve public health, but in today's world, we are faced with a newly emerging infectious diseases, as well as age-old threats, that either have no vaccines or vaccines that are not effective," said Steven G. Reed, Ph.D., founder, president and chief scientific officer for IDRI. "Combining that with the speed with which infectious diseases can travel the world, we need a new model for vaccine development, one that enables us to rapidly produce vaccines at a lower cost. The blend of the Gates Foundation's knowledge of global health and Sanofi's depth of vaccine development expertise is a perfect match for IDRI's unique technologies and research and development engine, allowing us to take a new approach to vaccine development." A Joint Steering Committee, comprised of representatives from each of the three partners, will mutually identify areas of research to discover, evaluate and develop novel human vaccines, as well as adjuvant/formulation platforms for the rapid response to emerging pathogens, that can prevent or treat infectious diseases. Initial funding will be used to establish and operate the GHVCI, build capacity as the collaboration grows, and provide management and scientific recruitment as well as training. "We are excited to be involved in this novel partnership and proud of the confidence shown in IDRI's technology and our science team's expertise by these two powerhouses, Sanofi and the Gates Foundation," said Erik Iverson, IDRI's president, business and operations. "IDRI has a proven history of developing global health products that have a positive impact. This alliance will significantly accelerate the development of a wide range of vaccines and other health interventions that will save the lives of millions of people globally." | U22: ['apaste', 'iidrii', 'apaste', 'apaste', 'bimega', 'bimega', 'iidrii', 'iidrii', 'sansyn', 'sansyn', 'whoz', 'bimega', 'sansyn'] | V22: ['sansyn', 'bimega', 'iidrii', 'apaste'] | W22: Saffron Media Pvt Ltd | X22: ,usa,namz, | Y22: ASIA INDIA SASIAZ | Z22: In an effort to accelerate timelines and decrease development costs of life-saving vaccines, the Infectious Disease Research Institute (IDRI) and Sanofi Pasteur announced the establishment of the Global Health Vaccine Center of Innovation (GHVCI), to be headquartered at IDRI in Seattle. This project is funded in part by a grant from the Bill & Melinda Gates Foundation. The GHVCI represents an alliance among the three organisations, focused on accelerating the development of vaccines and associated technologies to fight a wide range of global infectious diseases, and ensuring that these critical vaccines are accessible globally, especially to people in need within developing countries. | AA22: ATPHAB | AB22: PharmaBiz | AC22: TRUE | AD22: ['c22', 'c23', 'ccat', 'ncat', 'nfact', 'nfcpin'] | AE22: IDRI, Sanofi Pasteur join hands to develop new model for vaccine development | AF22: IDRI, Sanofi Pasteur join hands to develop new model for vaccine developmentEach partner will bring its respective world-leading expertise and technologies to the GHVCI and, collectively, the parties will collaborate with a wide range of other vaccine development organizations. Funding for the establishment, operation and growth of the GHVCI will come from Sanofi and the Gates Foundation, and additional funding will be sought to support collaborative research activities with respect to specific vaccines to be developed at the GHVCI. This distinctive collaboration leverages the potential power of the partners' collective expertise, combining IDRI's vaccine design, formulation and production technologies; Sanofi's position as a leading multi-national vaccine developer, manufacturer and seller; and the Gates Foundation's knowledge, influence and financial support regarding the discovery and development of global health interventions, including vaccines. A key component is the application of IDRI's vaccine adjuvant technologies and formulation expertise, which have been developed over the past few years with strong financial support from the Gates Foundation. These adjuvant technologies are uniquely designed to improve immune responses, broaden vaccine protection and significantly save costs by reducing the amount of vaccine needed. According to the World Health Organisation, vaccines have greatly reduced the burden of infectious diseases, including death tolls, disability and inequity, making "formerly fearsome" diseases a rarity in many parts of the world. "History has shown us that vaccines are one of the best ways to improve public health, but in today's world, we are faced with a newly emerging infectious diseases, as well as age-old threats, that either have no vaccines or vaccines that are not effective," said Steven G. Reed, Ph.D., founder, president and chief scientific officer for IDRI. "Combining that with the speed with which infectious diseases can travel the world, we need a new model for vaccine development, one that enables us to rapidly produce vaccines at a lower cost. The blend of the Gates Foundation's knowledge of global health and Sanofi's depth of vaccine development expertise is a perfect match for IDRI's unique technologies and research and development engine, allowing us to take a new approach to vaccine development." A Joint Steering Committee, comprised of representatives from each of the three partners, will mutually identify areas of research to discover, evaluate and develop novel human vaccines, as well as adjuvant/formulation platforms for the rapid response to emerging pathogens, that can prevent or treat infectious diseases. Initial funding will be used to establish and operate the GHVCI, build capacity as the collaboration grows, and provide management and scientific recruitment as well as training. "We are excited to be involved in this novel partnership and proud of the confidence shown in IDRI's technology and our science team's expertise by these two powerhouses, Sanofi and the Gates Foundation," said Erik Iverson, IDRI's president, business and operations. "IDRI has a proven history of developing global health products that have a positive impact. This alliance will significantly accelerate the development of a wide range of vaccines and other health interventions that will save the lives of millions of people globally." | AG22: 629
A23: 22 | B23: 43670.477 | C23: ATPHAB0020151019ebaj00036 | D23: Throw | E23: Throw | F23: =VLOOKUP(C23,InnovYes_Review!$A$2:$I$415,9,FALSE) -> 0 | G23: 3 | H23: 3 | J23: Extra4_LancasterVicki_PocinkiAllegra | M23: No | S23: No | T23: Each partner will bring its respective world-leading expertise and technologies to the GHVCI and, collectively, the parties will collaborate with a wide range of other vaccine development organizations. Funding for the establishment, operation and growth of the GHVCI will come from Sanofi and the Gates Foundation, and additional funding will be sought to support collaborative research activities with respect to specific vaccines to be developed at the GHVCI. This distinctive collaboration leverages the potential power of the partners' collective expertise, combining IDRI's vaccine design, formulation and production technologies; Sanofi's position as a leading multi-national vaccine developer, manufacturer and seller; and the Gates Foundation's knowledge, influence and financial support regarding the discovery and development of global health interventions, including vaccines. A key component is the application of IDRI's vaccine adjuvant technologies and formulation expertise, which have been developed over the past few years with strong financial support from the Gates Foundation. These adjuvant technologies are uniquely designed to improve immune responses, broaden vaccine protection and significantly save costs by reducing the amount of vaccine needed. According to the World Health Organisation, vaccines have greatly reduced the burden of infectious diseases, including death tolls, disability and inequity, making "formerly fearsome" diseases a rarity in many parts of the world. "History has shown us that vaccines are one of the best ways to improve public health, but in today's world, we are faced with a newly emerging infectious diseases, as well as age-old threats, that either have no vaccines or vaccines that are not effective," said Steven G. Reed, Ph.D., founder, president and chief scientific officer for IDRI. "Combining that with the speed with which infectious diseases can travel the world, we need a new model for vaccine development, one that enables us to rapidly produce vaccines at a lower cost. The blend of the Gates Foundation's knowledge of global health and Sanofi's depth of vaccine development expertise is a perfect match for IDRI's unique technologies and research and development engine, allowing us to take a new approach to vaccine development." A Joint Steering Committee, comprised of representatives from each of the three partners, will mutually identify areas of research to discover, evaluate and develop novel human vaccines, as well as adjuvant/formulation platforms for the rapid response to emerging pathogens, that can prevent or treat infectious diseases. Initial funding will be used to establish and operate the GHVCI, build capacity as the collaboration grows, and provide management and scientific recruitment as well as training. "We are excited to be involved in this novel partnership and proud of the confidence shown in IDRI's technology and our science team's expertise by these two powerhouses, Sanofi and the Gates Foundation," said Erik Iverson, IDRI's president, business and operations. "IDRI has a proven history of developing global health products that have a positive impact. This alliance will significantly accelerate the development of a wide range of vaccines and other health interventions that will save the lives of millions of people globally." | U23: ['apaste', 'iidrii', 'apaste', 'apaste', 'bimega', 'bimega', 'iidrii', 'iidrii', 'sansyn', 'sansyn', 'whoz', 'bimega', 'sansyn'] | V23: ['sansyn', 'bimega', 'iidrii', 'apaste'] | W23: Saffron Media Pvt Ltd | X23: ,usa,namz, | Y23: ASIA INDIA SASIAZ | Z23: In an effort to accelerate timelines and decrease development costs of life-saving vaccines, the Infectious Disease Research Institute (IDRI) and Sanofi Pasteur announced the establishment of the Global Health Vaccine Center of Innovation (GHVCI), to be headquartered at IDRI in Seattle. This project is funded in part by a grant from the Bill & Melinda Gates Foundation. The GHVCI represents an alliance among the three organisations, focused on accelerating the development of vaccines and associated technologies to fight a wide range of global infectious diseases, and ensuring that these critical vaccines are accessible globally, especially to people in need within developing countries. | AA23: ATPHAB | AB23: PharmaBiz | AC23: TRUE | AD23: ['c22', 'c23', 'ccat', 'ncat', 'nfact', 'nfcpin'] | AE23: IDRI, Sanofi Pasteur join hands to develop new model for vaccine development | AF23: IDRI, Sanofi Pasteur join hands to develop new model for vaccine developmentEach partner will bring its respective world-leading expertise and technologies to the GHVCI and, collectively, the parties will collaborate with a wide range of other vaccine development organizations. Funding for the establishment, operation and growth of the GHVCI will come from Sanofi and the Gates Foundation, and additional funding will be sought to support collaborative research activities with respect to specific vaccines to be developed at the GHVCI. This distinctive collaboration leverages the potential power of the partners' collective expertise, combining IDRI's vaccine design, formulation and production technologies; Sanofi's position as a leading multi-national vaccine developer, manufacturer and seller; and the Gates Foundation's knowledge, influence and financial support regarding the discovery and development of global health interventions, including vaccines. A key component is the application of IDRI's vaccine adjuvant technologies and formulation expertise, which have been developed over the past few years with strong financial support from the Gates Foundation. These adjuvant technologies are uniquely designed to improve immune responses, broaden vaccine protection and significantly save costs by reducing the amount of vaccine needed. According to the World Health Organisation, vaccines have greatly reduced the burden of infectious diseases, including death tolls, disability and inequity, making "formerly fearsome" diseases a rarity in many parts of the world. "History has shown us that vaccines are one of the best ways to improve public health, but in today's world, we are faced with a newly emerging infectious diseases, as well as age-old threats, that either have no vaccines or vaccines that are not effective," said Steven G. Reed, Ph.D., founder, president and chief scientific officer for IDRI. "Combining that with the speed with which infectious diseases can travel the world, we need a new model for vaccine development, one that enables us to rapidly produce vaccines at a lower cost. The blend of the Gates Foundation's knowledge of global health and Sanofi's depth of vaccine development expertise is a perfect match for IDRI's unique technologies and research and development engine, allowing us to take a new approach to vaccine development." A Joint Steering Committee, comprised of representatives from each of the three partners, will mutually identify areas of research to discover, evaluate and develop novel human vaccines, as well as adjuvant/formulation platforms for the rapid response to emerging pathogens, that can prevent or treat infectious diseases. Initial funding will be used to establish and operate the GHVCI, build capacity as the collaboration grows, and provide management and scientific recruitment as well as training. "We are excited to be involved in this novel partnership and proud of the confidence shown in IDRI's technology and our science team's expertise by these two powerhouses, Sanofi and the Gates Foundation," said Erik Iverson, IDRI's president, business and operations. "IDRI has a proven history of developing global health products that have a positive impact. This alliance will significantly accelerate the development of a wide range of vaccines and other health interventions that will save the lives of millions of people globally." | AG23: 629
A24: 23 | B24: 43670.581 | C24: ATPHAB0020151212ebcc0000d | D24: Keep | E24: Keep | F24: =VLOOKUP(C24,InnovYes_Review!$A$2:$I$415,9,FALSE) -> 0 | G24: 2 | H24: 3 | J24: PristavecTeja_McDonaldSarah_IschCalvin | M24: Yes | N24: Approved by FDA and scheduled to be launched | O24: reslizumab BLA | Q24: Yes | R24: Yes | S24: No | T24: "We are very encouraged by the outcome of today's FDA Advisory Committee meeting, which brings us one step closer to potentially providing a new, targeted treatment option for a specific group of patients with inadequately controlled asthma and evidence of ongoing eosinophilic inflammation. This group of patients often experiences persistent symptoms despite standard-of-care treatment, demonstrating a need for more targeted treatment options based on patient phenotype." The Advisory Committee's recommendation will be considered by the FDA in its review of the Biologics License Application (BLA) for reslizumab. The FDA is not bound by the Committee's recommendation, but takes its advice into consideration when reviewing investigational medicines. The reslizumab BLA was accepted for standard review by the FDA and Regulatory Action is expected in March 2016. Additional regulatory filings for reslizumab have been completed in the EU and Canada. Reslizumab is an investigational humanized interleukin-5 (IL-5) antagonist IgG4K monoclonal antibody (mAb), for the treatment of inadequately controlled asthma in adult and adolescent patients with elevated blood eosinophils, despite an inhaled corticosteroid (ICS)-based regimen. IL-5 is the most selective eosinophil cytokine known and plays a major role in the maturation, activation and survival of eosinophils, which are the predominant type of white blood cell underlying chronic airway inflammation in the eosinophilic phenotype of asthma. In asthma patients, elevated blood eosinophils =400 cells/mcL are associated with compromised lung function, persistent symptoms, and increased risk of exacerbations. Reslizumab is thought to act by binding to and neutralizing human IL-5 to reduce eosinophilic inflammation. Reslizumab has been submitted for and is currently under review by the U.S. Food and Drug Administration (FDA), European Medicines Agency (EMA) and Health Canada. | U24: ['teviy', 'usfda', 'cndhea', 'eumagy', 'teviy', 'teviy', 'usfda', 'usfda'] | V24: ['usfda', 'teviy'] | W24: Saffron Media Pvt Ltd | X24: ,usa,namz, | Y24: ASIA INDIA SASIAZ | Z24: Teva Pharmaceutical Industries Ltd., announced that the US Food and Drug Administration's (FDA) Pulmonary-Allergy Drugs Advisory Committee recommended approval of reslizumab, a humanized anti-interleukin-5 (IL-5) IgG4K monoclonal antibody (mAb), in adult patients aged 18 years and older. Reslizumab is a targeted biologic therapy for the treatment of inadequately controlled asthma in patients with elevated blood eosinophils, despite an inhaled corticosteroid (ICS)-based treatment regimen. "Patient stratification based on eosinophil levels has been an important advancement in the treatment of asthma," said Michael Hayden, M.D., Ph.D., president of global R&D; and chief scientific officer at Teva Pharmaceutical Industries Ltd. | AA24: ATPHAB | AB24: PharmaBiz | AC24: TRUE | AD24: ['cappro', 'gastma', 'c131', 'c13', 'c22', 'ccat', 'gcat', 'ghea', 'gmed', 'ncat', 'nfact', 'nfcpin'] | AE24: US FDA committee recommends approval of Teva's asthma biologic reslizumab | AF24: US FDA committee recommends approval of Teva's asthma biologic reslizumab"We are very encouraged by the outcome of today's FDA Advisory Committee meeting, which brings us one step closer to potentially providing a new, targeted treatment option for a specific group of patients with inadequately controlled asthma and evidence of ongoing eosinophilic inflammation. This group of patients often experiences persistent symptoms despite standard-of-care treatment, demonstrating a need for more targeted treatment options based on patient phenotype." The Advisory Committee's recommendation will be considered by the FDA in its review of the Biologics License Application (BLA) for reslizumab. The FDA is not bound by the Committee's recommendation, but takes its advice into consideration when reviewing investigational medicines. The reslizumab BLA was accepted for standard review by the FDA and Regulatory Action is expected in March 2016. Additional regulatory filings for reslizumab have been completed in the EU and Canada. Reslizumab is an investigational humanized interleukin-5 (IL-5) antagonist IgG4K monoclonal antibody (mAb), for the treatment of inadequately controlled asthma in adult and adolescent patients with elevated blood eosinophils, despite an inhaled corticosteroid (ICS)-based regimen. IL-5 is the most selective eosinophil cytokine known and plays a major role in the maturation, activation and survival of eosinophils, which are the predominant type of white blood cell underlying chronic airway inflammation in the eosinophilic phenotype of asthma. In asthma patients, elevated blood eosinophils =400 cells/mcL are associated with compromised lung function, persistent symptoms, and increased risk of exacerbations. Reslizumab is thought to act by binding to and neutralizing human IL-5 to reduce eosinophilic inflammation. Reslizumab has been submitted for and is currently under review by the U.S. Food and Drug Administration (FDA), European Medicines Agency (EMA) and Health Canada. | AG24: 408
A25: 24 | B25: 43670.497 | C25: ATPHAB0020151212ebcc0000d | D25: Throw | E25: Throw | F25: =VLOOKUP(C25,InnovYes_Review!$A$2:$I$415,9,FALSE) -> 0 | G25: 2 | H25: 3 | J25: PristavecTeja_McDonaldSarah_IschCalvin | M25: Yes | N25: FDA application submission and/or FDA testing | O25: Reslizumab | P25: Biologics License Application | Q25: Yes | R25: No | S25: No | T25: "We are very encouraged by the outcome of today's FDA Advisory Committee meeting, which brings us one step closer to potentially providing a new, targeted treatment option for a specific group of patients with inadequately controlled asthma and evidence of ongoing eosinophilic inflammation. This group of patients often experiences persistent symptoms despite standard-of-care treatment, demonstrating a need for more targeted treatment options based on patient phenotype." The Advisory Committee's recommendation will be considered by the FDA in its review of the Biologics License Application (BLA) for reslizumab. The FDA is not bound by the Committee's recommendation, but takes its advice into consideration when reviewing investigational medicines. The reslizumab BLA was accepted for standard review by the FDA and Regulatory Action is expected in March 2016. Additional regulatory filings for reslizumab have been completed in the EU and Canada. Reslizumab is an investigational humanized interleukin-5 (IL-5) antagonist IgG4K monoclonal antibody (mAb), for the treatment of inadequately controlled asthma in adult and adolescent patients with elevated blood eosinophils, despite an inhaled corticosteroid (ICS)-based regimen. IL-5 is the most selective eosinophil cytokine known and plays a major role in the maturation, activation and survival of eosinophils, which are the predominant type of white blood cell underlying chronic airway inflammation in the eosinophilic phenotype of asthma. In asthma patients, elevated blood eosinophils =400 cells/mcL are associated with compromised lung function, persistent symptoms, and increased risk of exacerbations. Reslizumab is thought to act by binding to and neutralizing human IL-5 to reduce eosinophilic inflammation. Reslizumab has been submitted for and is currently under review by the U.S. Food and Drug Administration (FDA), European Medicines Agency (EMA) and Health Canada. | U25: ['teviy', 'usfda', 'cndhea', 'eumagy', 'teviy', 'teviy', 'usfda', 'usfda'] | V25: ['usfda', 'teviy'] | W25: Saffron Media Pvt Ltd | X25: ,usa,namz, | Y25: ASIA INDIA SASIAZ | Z25: Teva Pharmaceutical Industries Ltd., announced that the US Food and Drug Administration's (FDA) Pulmonary-Allergy Drugs Advisory Committee recommended approval of reslizumab, a humanized anti-interleukin-5 (IL-5) IgG4K monoclonal antibody (mAb), in adult patients aged 18 years and older. Reslizumab is a targeted biologic therapy for the treatment of inadequately controlled asthma in patients with elevated blood eosinophils, despite an inhaled corticosteroid (ICS)-based treatment regimen. "Patient stratification based on eosinophil levels has been an important advancement in the treatment of asthma," said Michael Hayden, M.D., Ph.D., president of global R&D; and chief scientific officer at Teva Pharmaceutical Industries Ltd. | AA25: ATPHAB | AB25: PharmaBiz | AC25: TRUE | AD25: ['cappro', 'gastma', 'c131', 'c13', 'c22', 'ccat', 'gcat', 'ghea', 'gmed', 'ncat', 'nfact', 'nfcpin'] | AE25: US FDA committee recommends approval of Teva's asthma biologic reslizumab | AF25: US FDA committee recommends approval of Teva's asthma biologic reslizumab"We are very encouraged by the outcome of today's FDA Advisory Committee meeting, which brings us one step closer to potentially providing a new, targeted treatment option for a specific group of patients with inadequately controlled asthma and evidence of ongoing eosinophilic inflammation. This group of patients often experiences persistent symptoms despite standard-of-care treatment, demonstrating a need for more targeted treatment options based on patient phenotype." The Advisory Committee's recommendation will be considered by the FDA in its review of the Biologics License Application (BLA) for reslizumab. The FDA is not bound by the Committee's recommendation, but takes its advice into consideration when reviewing investigational medicines. The reslizumab BLA was accepted for standard review by the FDA and Regulatory Action is expected in March 2016. Additional regulatory filings for reslizumab have been completed in the EU and Canada. Reslizumab is an investigational humanized interleukin-5 (IL-5) antagonist IgG4K monoclonal antibody (mAb), for the treatment of inadequately controlled asthma in adult and adolescent patients with elevated blood eosinophils, despite an inhaled corticosteroid (ICS)-based regimen. IL-5 is the most selective eosinophil cytokine known and plays a major role in the maturation, activation and survival of eosinophils, which are the predominant type of white blood cell underlying chronic airway inflammation in the eosinophilic phenotype of asthma. In asthma patients, elevated blood eosinophils =400 cells/mcL are associated with compromised lung function, persistent symptoms, and increased risk of exacerbations. Reslizumab is thought to act by binding to and neutralizing human IL-5 to reduce eosinophilic inflammation. Reslizumab has been submitted for and is currently under review by the U.S. Food and Drug Administration (FDA), European Medicines Agency (EMA) and Health Canada. | AG25: 408
A26: 25 | B26: 43670.501 | C26: ATPHAM0020150110eb18000bc | D26: None | E26: Keep | F26: =VLOOKUP(C26,InnovYes_Review!$A$2:$I$415,9,FALSE) -> 0 | G26: 1 | H26: 1 | I26: 1 | J26: IschCalvin | K26: IschCalvin | M26: No | S26: No | T26: The first major addition last year saw the introduction of pharmacogenetic testing (PGT) into their programs, a DNA-based test that greatly optimizes the accuracy and timeliness of prescription medications for mental health disorders. Shortly after in March, they were accredited by the National Association for Alcoholism and Drug Abuse Counselors as a provider of continuing education, allowing them to host C.E. webinars and networking luncheons at both their treatment locations and online through their education center, Sovereign Institute. In mid 2014, the San Clemente headquarters implemented natural assisted detox/neurotransmitter restoration therapy (NAD/NTR) as an additional detox option for their patients. NAD is a natural detox process that delivers amino acids which expedite the recovery process at a cellular level without the use of other addictive medications. NAD is a holistic solution to substance abuse withdrawal symptoms and the detoxification process. Sovereign also initiated official legal and court liaison services to further aid patients and their families. The following months saw the inauguration of their Palm Springs, California and Fort Myers, Florida facilities as well as more specialized centers with Rancho San Diego, California's Adolescent Program and Chandler, Arizona's women's treatment center specializing in trauma. Following the creation of an Alumni Services department and a new Continuing Care Program, Sovereign wrapped up the year by expanding an Intensive Family Program with the goal to provide current patients and their family members the tools to administer a healthy support system and plan within the unit. "The considerable growth we have experienced in 2014 is merely a byproduct of focusing on the needs of our current clientele," said Tonmoy Sharma, CEO of Sovereign Health Group. "Every move that Sovereign makes and every facility that is inaugurated is done directly and deliberately for the current mental and behavioral health needs of the particular group we are focusing on treating." The Sovereign Way is not only defined by their operational excellence, but a passion to challenge the status quo and incorporate innovative new concepts into their programs. Despite a 300 percent growth rate over the last three years, Sovereign will continue to expand, addressing new demographics throughout the country in the future. In 2014, Sovereign Health evolved from a California-based addiction treatment provider into a nationally accredited brand. For 2015 and in the years to come, they will carry that passion and commitment to excellence as one of the top treatment providers in the field. Source: Sovereign Health Group | U26: [] | V26: [] | W26: Athena Information Solutions Pvt. Ltd. | X26: ,usa,namz, | Y26: ASIA INDIA SASIAZ SEASIAZ | Z26: Jan. 8 -- US-based Sovereign Health Group issued the following news release: Sovereign Health Group, leader in addiction, dual diagnosis and mental health residential treatment programs for adults and adolescents, has experienced tremendous growth in 2014, celebrating the opening of four new treatment facilities as well as innovative additions to their programs. Although only in their sixth year, they have reached new demographics and milestones in excellence, ranking number six in the OC Business Journal's fastest-growing private companies list and within the top 25 percent of the Inc. 5000, Inc. Magazine's annual tally of the same measure. With the addition of nearly 200 employees to the Sovereign family this past year, keeping track of all the changes and innovations they have undergone can be a challenge. As they begin the New Year, Sovereign takes a look back at 2014 so that they can continue to improve patient care and move forward. | AA26: ATPHAM | AB26: India Pharma News | AC26: FALSE | AD26: ['ghea', 'gcat'] | AE26: Sovereign Health Sees Unprecedented Growth in 2014 | AF26: Sovereign Health Sees Unprecedented Growth in 2014The first major addition last year saw the introduction of pharmacogenetic testing (PGT) into their programs, a DNA-based test that greatly optimizes the accuracy and timeliness of prescription medications for mental health disorders. Shortly after in March, they were accredited by the National Association for Alcoholism and Drug Abuse Counselors as a provider of continuing education, allowing them to host C.E. webinars and networking luncheons at both their treatment locations and online through their education center, Sovereign Institute. In mid 2014, the San Clemente headquarters implemented natural assisted detox/neurotransmitter restoration therapy (NAD/NTR) as an additional detox option for their patients. NAD is a natural detox process that delivers amino acids which expedite the recovery process at a cellular level without the use of other addictive medications. NAD is a holistic solution to substance abuse withdrawal symptoms and the detoxification process. Sovereign also initiated official legal and court liaison services to further aid patients and their families. The following months saw the inauguration of their Palm Springs, California and Fort Myers, Florida facilities as well as more specialized centers with Rancho San Diego, California's Adolescent Program and Chandler, Arizona's women's treatment center specializing in trauma. Following the creation of an Alumni Services department and a new Continuing Care Program, Sovereign wrapped up the year by expanding an Intensive Family Program with the goal to provide current patients and their family members the tools to administer a healthy support system and plan within the unit. "The considerable growth we have experienced in 2014 is merely a byproduct of focusing on the needs of our current clientele," said Tonmoy Sharma, CEO of Sovereign Health Group. "Every move that Sovereign makes and every facility that is inaugurated is done directly and deliberately for the current mental and behavioral health needs of the particular group we are focusing on treating." The Sovereign Way is not only defined by their operational excellence, but a passion to challenge the status quo and incorporate innovative new concepts into their programs. Despite a 300 percent growth rate over the last three years, Sovereign will continue to expand, addressing new demographics throughout the country in the future. In 2014, Sovereign Health evolved from a California-based addiction treatment provider into a nationally accredited brand. For 2015 and in the years to come, they will carry that passion and commitment to excellence as one of the top treatment providers in the field. Source: Sovereign Health Group | AG26: 577
A27: 26 | B27: 43670.48 | C27: ATPHAM0020150115eb1c0008g | D27: None | E27: Keep | F27: =VLOOKUP(C27,InnovYes_Review!$A$2:$I$415,9,FALSE) -> 0 | G27: 1 | H27: 2 | J27: KorkmazGizem_KattampallilNeil | M27: No | S27: No | T27: Second quarter of fiscal year 2015 revenue is expected to be approximately $3.1 million, up approximately 2% sequentially from the first quarter of fiscal year 2015. The second quarter revenue was down approximately 19% compared to the second quarter of the prior fiscal year, which was the last full quarter of operations before the Company restructured its sales and operations in the second half of fiscal year 2014. As of December 31, 2014, the Company's preliminary total cash balance was approximately $570,000, which includes $40,000 of restricted cash. The total cash balance is an increase of approximately $25,000 from September 30, 2014. "We are pleased with our preliminary revenue and cash results for the second quarter. We now have two quarters of post-restructuring operations behind us that indicate we are on track with the primary objective of our plan to stabilize revenue with our new distribution model and become operationally cash flow positive," stated Greg Fluet, CEO. During the quarter ended December 31, 2014 and subsequently since that date, Urologix did not make any payments towards any of the amounts due and unpaid to Medtronic. Regarding the amounts due and unpaid to Medtronic, Urologix and Medtronic both share a sincere commitment to patients and urologists. Urologix recognizes Medtronic's continuing rights under the agreements, and is working collaboratively with Medtronic and their observer on the Company's Board of Directors in an effort to build the business. The preliminary unaudited results for the second quarter of fiscal year 2015 are subject to the Company's management and independent auditors' customary review procedures. The Company intends to issue a press release reporting final results of operations for the quarter ending December 31, 2014 after the market close on February 5, 2015, with its conference call scheduled for 4:00 p.m. CST that day. Earnings Call Information To listen to the call, please dial 1-866-515-2910 and enter the Participant Passcode 37953871 at least 10 minutes prior to the call. A live webcast of the call will be available through the investor relations section of the Company's website at (www.urologix.com) and available for replay approximately two hours after the completion of the call. Source: Urologix, Inc. | U27: ['urolog', 'medinc', 'urolog', 'urolog'] | V27: ['urolog'] | W27: Athena Information Solutions Pvt. Ltd. | X27: ,usa,namz, | Y27: ASIA INDIA SASIAZ SEASIAZ | Z27: Jan. 12 -- US-based Urologix, Inc. issued the following news release: Urologix, Inc. (OTCQB:ULGX), the leading provider of in-office procedures for the safe, durable and effective treatment of BPH, announces preliminary revenue and cash balances for its second quarter of fiscal year 2015 ended December 31, 2014. | AA27: ATPHAM | AB27: India Pharma News | AC27: FALSE | AD27: ['c15', 'c151', 'c1513', 'ccat', 'ncat', 'nfact', 'nfcpin'] | AE27: Urologix Reports Preliminary Fiscal Year 2015 Second Quarter Revenue, Cash Results | AF27: Urologix Reports Preliminary Fiscal Year 2015 Second Quarter Revenue, Cash ResultsSecond quarter of fiscal year 2015 revenue is expected to be approximately $3.1 million, up approximately 2% sequentially from the first quarter of fiscal year 2015. The second quarter revenue was down approximately 19% compared to the second quarter of the prior fiscal year, which was the last full quarter of operations before the Company restructured its sales and operations in the second half of fiscal year 2014. As of December 31, 2014, the Company's preliminary total cash balance was approximately $570,000, which includes $40,000 of restricted cash. The total cash balance is an increase of approximately $25,000 from September 30, 2014. "We are pleased with our preliminary revenue and cash results for the second quarter. We now have two quarters of post-restructuring operations behind us that indicate we are on track with the primary objective of our plan to stabilize revenue with our new distribution model and become operationally cash flow positive," stated Greg Fluet, CEO. During the quarter ended December 31, 2014 and subsequently since that date, Urologix did not make any payments towards any of the amounts due and unpaid to Medtronic. Regarding the amounts due and unpaid to Medtronic, Urologix and Medtronic both share a sincere commitment to patients and urologists. Urologix recognizes Medtronic's continuing rights under the agreements, and is working collaboratively with Medtronic and their observer on the Company's Board of Directors in an effort to build the business. The preliminary unaudited results for the second quarter of fiscal year 2015 are subject to the Company's management and independent auditors' customary review procedures. The Company intends to issue a press release reporting final results of operations for the quarter ending December 31, 2014 after the market close on February 5, 2015, with its conference call scheduled for 4:00 p.m. CST that day. Earnings Call Information To listen to the call, please dial 1-866-515-2910 and enter the Participant Passcode 37953871 at least 10 minutes prior to the call. A live webcast of the call will be available through the investor relations section of the Company's website at (www.urologix.com) and available for replay approximately two hours after the completion of the call. Source: Urologix, Inc. | AG27: 440
