Workbook
Name inrate: Form!$W$3
Name insch: Form!$W$3
Name osrate: Form!$AB$3
Name type: Lists!$A$13:$B$17

Sheet Form
A2: Course Description | G2: Instructor Description and Negotiated Payment | N2: Projected Headcount Enrollment | W2: Revenue Estimates (incl. estimated discount for financial aid) | AE2: Allocation of Estimated Revenue
A3: CALCULATION FACTORS | L3: Max 11.25% | Y3: Winter 2015 | Z3: 0.0616 | AF3: 0.0765 | AG3: =0.3 -> 0.3 | AH3: Surplus Share | AI3: 0.7 | AJ3: 0.3
AH4: Deficit Share | AI4: =100/130 -> 0.76923077 | AJ4: =30/130 -> 0.23076923
A5: Course Number | B5: Course Name | C5: Course Level (choose from drop down) | D5: SCH | E5: Anticipated Delivery Method (choose from drop down) | G5: Name of Course Instructor | H5: Faculty Members VT ID # | I5: Negotiated Payment | J5: This Instructor is (choose from drop down): | K5: Faculty Members Annual Salary | L5: Payment > 3.75% per SCH | N5: On-Campus | P5: Off-Campus | R5: Study Abroad | T5: Total Students | U5: Basis for Enrollment Estimate: | W5: On-Campus | Y5: Off-Campus | AA5: Study Abroad | AC5: Distributable Total | AE5: Faculty Payment | AF5: Fringe Benefits | AG5: University Indirect | AH5: Net Surplus/(Deficit) | AI5: College | AJ5: University
N6: In-State | O6: Out-of-State | P6: In-State | Q6: Out-of-State | R6: In-State | S6: Out-of-State | W6: In-State | X6: Out-of-State | Y6: In-State | Z6: Out-of-State | AA6: In-State | AB6: Out-of-State
A7: ENG 1001 | B7: Sample Course 1 | C7: Undergraduate | E7: Winter Experience | G7: TEST | H7: 123456789 | J7: A 12 month faculty or instructor | L7: =IF((K7*0.0375*D7)>I7,"No","Yes") -> Yes | N7: 0 | O7: 0 | P7: 0 | Q7: 0 | T7: =SUM(N7:S7) -> 0 | U7: Survey of student interest in prerequisite course. | W7: =IFERROR(ROUND(INDEX(Rates!$A:$G,MATCH(Form!$C7,Rates!$A:$A,0),2)*$D7*$N7*(1-$Z$3),0),0) -> 0 | X7: =IFERROR(ROUND(INDEX(Rates!$A:$G,MATCH(Form!$C7,Rates!$A:$A,0),3)*$D7*O7*(1-$Z$3),0),0) -> 0 | Y7: =IFERROR(ROUND(INDEX(Rates!$A:$G,MATCH(Form!$C7,Rates!$A:$A,0),4)*$D7*$P7*(1-$Z$3),0),0) -> 0 | Z7: =IFERROR(ROUND(INDEX(Rates!$A:$G,MATCH(Form!$C7,Rates!$A:$A,0),5)*$D7*$Q7*(1-$Z$3),0),0) -> 0 | AA7: =IFERROR(ROUND(INDEX(Rates!$A:$G,MATCH(Form!$C7,Rates!$A:$A,0),6)*$D7*$R7*(1-$Z$3),0),0) -> 0 | AB7: =IFERROR(ROUND(INDEX(Rates!$A:$G,MATCH(Form!$C7,Rates!$A:$A,0),7)*$D7*$S7*(1-$Z$3),0),0) -> 0 | AC7: =SUM(W7:AB7) -> 0 | AE7: =I7 -> 0 | AF7: =AE7*$AF$3 -> 0 | AG7: =$AG$3*SUM(AE7:AF7) -> 0 | AH7: =AC7-SUM(AE7:AG7) -> 0 | AI7: =IF(AH7>0,AH7*$AI$3,AH7*$AI$4) -> 0 | AJ7: =IF(AH7>0,AH7*$AJ$3,AH7*$AJ$4) -> 0
A8: ENG 1001 | B8: Sample Course 2 | C8: Undergraduate | E8: 100% On-Line | G8: TEST | H8: 234567890 | J8: An adjunct faculty member | L8: =IF((K8*0.0375*D8)>I8,"No","Yes") -> Yes | N8: 0 | O8: 0 | P8: 0 | Q8: 0 | R8: 0 | S8: 0 | T8: =SUM(N8:S8) -> 0 | U8: Popular CLE Area 4 course | W8: =IFERROR(ROUND(INDEX(Rates!$A:$G,MATCH(Form!$C8,Rates!$A:$A,0),2)*$D8*$N8*(1-$Z$3),0),0) -> 0 | X8: =IFERROR(ROUND(INDEX(Rates!$A:$G,MATCH(Form!$C8,Rates!$A:$A,0),3)*$D8*O8*(1-$Z$3),0),0) -> 0 | Y8: =IFERROR(ROUND(INDEX(Rates!$A:$G,MATCH(Form!$C8,Rates!$A:$A,0),4)*$D8*$P8*(1-$Z$3),0),0) -> 0 | Z8: =IFERROR(ROUND(INDEX(Rates!$A:$G,MATCH(Form!$C8,Rates!$A:$A,0),5)*$D8*$Q8*(1-$Z$3),0),0) -> 0 | AA8: =IFERROR(ROUND(INDEX(Rates!$A:$G,MATCH(Form!$C8,Rates!$A:$A,0),6)*$D8*$R8*(1-$Z$3),0),0) -> 0 | AB8: =IFERROR(ROUND(INDEX(Rates!$A:$G,MATCH(Form!$C8,Rates!$A:$A,0),7)*$D8*$S8*(1-$Z$3),0),0) -> 0 | AC8: =SUM(W8:AB8) -> 0 | AE8: =I8 -> 0 | AF8: =AE8*$AF$3 -> 0 | AG8: =$AG$3*SUM(AE8:AF8) -> 0 | AH8: =AC8-SUM(AE8:AG8) -> 0 | AI8: =IF(AH8>0,AH8*$AI$3,AH8*$AI$4) -> 0 | AJ8: =IF(AH8>0,AH8*$AJ$3,AH8*$AJ$4) -> 0
A9: SDAL 1001 | B9: Keller Course Undergrads | C9: Undergraduate | D9: 12 | E9: Winter Experience | G9: Molfino / Pires | H9: 345678901 | I9: 12375 | J9: A 12 month faculty or instructor | K9: 65000 | L9: =IF((K9*0.0375*D9)>I9,"No","Yes") -> No | N9: 0 | O9: 0 | P9: 12.5 | Q9: 0 | R9: 0 | S9: 0 | T9: =SUM(N9:S9) -> 12.5 | U9: From Keller notes | W9: =IFERROR(ROUND(INDEX(Rates!$A:$G,MATCH(Form!$C9,Rates!$A:$A,0),2)*$D9*$N9*(1-$Z$3),0),0) -> 0 | X9: =IFERROR(ROUND(INDEX(Rates!$A:$G,MATCH(Form!$C9,Rates!$A:$A,0),3)*$D9*O9*(1-$Z$3),0),0) -> 0 | Y9: =IFERROR(ROUND(INDEX(Rates!$A:$G,MATCH(Form!$C9,Rates!$A:$A,0),4)*$D9*$P9*(1-$Z$3),0),0) -> 63272 | Z9: =IFERROR(ROUND(INDEX(Rates!$A:$G,MATCH(Form!$C9,Rates!$A:$A,0),5)*$D9*$Q9*(1-$Z$3),0),0) -> 0 | AA9: =IFERROR(ROUND(INDEX(Rates!$A:$G,MATCH(Form!$C9,Rates!$A:$A,0),6)*$D9*$R9*(1-$Z$3),0),0) -> 0 | AB9: =IFERROR(ROUND(INDEX(Rates!$A:$G,MATCH(Form!$C9,Rates!$A:$A,0),7)*$D9*$S9*(1-$Z$3),0),0) -> 0 | AC9: =SUM(W9:AB9) -> 63272 | AE9: =I9 -> 12375 | AF9: =AE9*$AF$3 -> 946.6875 | AG9: =$AG$3*SUM(AE9:AF9) -> 3996.5062 | AH9: =AC9-SUM(AE9:AG9) -> 45953.806 | AI9: =IF(AH9>0,AH9*$AI$3,AH9*$AI$4) -> 32167.664 | AJ9: =IF(AH9>0,AH9*$AJ$3,AH9*$AJ$4) -> 13786.142
A10: SDAL 1001 | B10: Keller Course Grads | C10: Graduate | D10: 12 | E10: Winter Experience | G10: Molfino / Pires | H10: 456789012 | I10: 12375 | J10: A 12 month faculty or instructor | K10: 65000 | L10: =IF((K10*0.0375*D10)>I10,"No","Yes") -> No | N10: 0 | O10: 0 | P10: 0 | Q10: 0 | R10: 0 | S10: 0 | T10: =SUM(N10:S10) -> 0 | U10: From Keller notes | W10: =IFERROR(ROUND(INDEX(Rates!$A:$G,MATCH(Form!$C10,Rates!$A:$A,0),2)*$D10*$N10*(1-$Z$3),0),0) -> 0 | X10: =IFERROR(ROUND(INDEX(Rates!$A:$G,MATCH(Form!$C10,Rates!$A:$A,0),3)*$D10*O10*(1-$Z$3),0),0) -> 0 | Y10: =IFERROR(ROUND(INDEX(Rates!$A:$G,MATCH(Form!$C10,Rates!$A:$A,0),4)*$D10*$P10*(1-$Z$3),0),0) -> 0 | Z10: =IFERROR(ROUND(INDEX(Rates!$A:$G,MATCH(Form!$C10,Rates!$A:$A,0),5)*$D10*$Q10*(1-$Z$3),0),0) -> 0 | AA10: =IFERROR(ROUND(INDEX(Rates!$A:$G,MATCH(Form!$C10,Rates!$A:$A,0),6)*$D10*$R10*(1-$Z$3),0),0) -> 0 | AB10: =IFERROR(ROUND(INDEX(Rates!$A:$G,MATCH(Form!$C10,Rates!$A:$A,0),7)*$D10*$S10*(1-$Z$3),0),0) -> 0 | AC10: =SUM(W10:AB10) -> 0 | AE10: =I10 -> 12375 | AF10: =AE10*$AF$3 -> 946.6875 | AG10: =$AG$3*SUM(AE10:AF10) -> 3996.5062 | AH10: =AC10-SUM(AE10:AG10) -> -17318.194 | AI10: =IF(AH10>0,AH10*$AI$3,AH10*$AI$4) -> -13321.688 | AJ10: =IF(AH10>0,AH10*$AJ$3,AH10*$AJ$4) -> -3996.5062
A11: ENG 1001 | B11: Sample Course 5 | C11: Undergraduate | E11: 100% On-Line | G11: TEST | H11: 12345678 | J11: A 12 month faculty or instructor | L11: =IF((K11*0.0375*D11)>I11,"No","Yes") -> Yes | N11: 0 | O11: 0 | T11: =SUM(N11:S11) -> 0 | W11: =IFERROR(ROUND(INDEX(Rates!$A:$G,MATCH(Form!$C11,Rates!$A:$A,0),2)*$D11*$N11*(1-$Z$3),0),0) -> 0 | X11: =IFERROR(ROUND(INDEX(Rates!$A:$G,MATCH(Form!$C11,Rates!$A:$A,0),3)*$D11*O11*(1-$Z$3),0),0) -> 0 | Y11: =IFERROR(ROUND(INDEX(Rates!$A:$G,MATCH(Form!$C11,Rates!$A:$A,0),4)*$D11*$P11*(1-$Z$3),0),0) -> 0 | Z11: =IFERROR(ROUND(INDEX(Rates!$A:$G,MATCH(Form!$C11,Rates!$A:$A,0),5)*$D11*$Q11*(1-$Z$3),0),0) -> 0 | AA11: =IFERROR(ROUND(INDEX(Rates!$A:$G,MATCH(Form!$C11,Rates!$A:$A,0),6)*$D11*$R11*(1-$Z$3),0),0) -> 0 | AB11: =IFERROR(ROUND(INDEX(Rates!$A:$G,MATCH(Form!$C11,Rates!$A:$A,0),7)*$D11*$S11*(1-$Z$3),0),0) -> 0 | AC11: =SUM(W11:AB11) -> 0 | AE11: =I11 -> 0 | AF11: =AE11*$AF$3 -> 0 | AG11: =$AG$3*SUM(AE11:AF11) -> 0 | AH11: =AC11-SUM(AE11:AG11) -> 0 | AI11: =IF(AH11>0,AH11*$AI$3,AH11*$AI$4) -> 0 | AJ11: =IF(AH11>0,AH11*$AJ$3,AH11*$AJ$4) -> 0
L12: =IF((K12*0.0375*D12)>I12,"No","Yes") -> Yes | N12: 0 | O12: 0 | T12: =SUM(N12:S12) -> 0 | W12: =IFERROR(ROUND(INDEX(Rates!$A:$G,MATCH(Form!$C12,Rates!$A:$A,0),2)*$D12*$N12*(1-$Z$3),0),0) -> 0 | X12: =IFERROR(ROUND(INDEX(Rates!$A:$G,MATCH(Form!$C12,Rates!$A:$A,0),3)*$D12*O12*(1-$Z$3),0),0) -> 0 | Y12: =IFERROR(ROUND(INDEX(Rates!$A:$G,MATCH(Form!$C12,Rates!$A:$A,0),4)*$D12*$P12*(1-$Z$3),0),0) -> 0 | Z12: =IFERROR(ROUND(INDEX(Rates!$A:$G,MATCH(Form!$C12,Rates!$A:$A,0),5)*$D12*$Q12*(1-$Z$3),0),0) -> 0 | AA12: =IFERROR(ROUND(INDEX(Rates!$A:$G,MATCH(Form!$C12,Rates!$A:$A,0),6)*$D12*$R12*(1-$Z$3),0),0) -> 0 | AB12: =IFERROR(ROUND(INDEX(Rates!$A:$G,MATCH(Form!$C12,Rates!$A:$A,0),7)*$D12*$S12*(1-$Z$3),0),0) -> 0 | AC12: =SUM(W12:AB12) -> 0 | AE12: =I12 -> 0 | AF12: =AE12*$AF$3 -> 0 | AG12: =$AG$3*SUM(AE12:AF12) -> 0 | AH12: =AC12-SUM(AE12:AG12) -> 0 | AI12: =IF(AH12>0,AH12*$AI$3,AH12*$AI$4) -> 0 | AJ12: =IF(AH12>0,AH12*$AJ$3,AH12*$AJ$4) -> 0
L13: =IF((K13*0.0375*D13)>I13,"No","Yes") -> Yes | T13: =SUM(N13:S13) -> 0 | W13: =IFERROR(ROUND(INDEX(Rates!$A:$G,MATCH(Form!$C13,Rates!$A:$A,0),2)*$D13*$N13*(1-$Z$3),0),0) -> 0 | X13: =IFERROR(ROUND(INDEX(Rates!$A:$G,MATCH(Form!$C13,Rates!$A:$A,0),3)*$D13*O13*(1-$Z$3),0),0) -> 0 | Y13: =IFERROR(ROUND(INDEX(Rates!$A:$G,MATCH(Form!$C13,Rates!$A:$A,0),4)*$D13*$P13*(1-$Z$3),0),0) -> 0 | Z13: =IFERROR(ROUND(INDEX(Rates!$A:$G,MATCH(Form!$C13,Rates!$A:$A,0),5)*$D13*$Q13*(1-$Z$3),0),0) -> 0 | AA13: =IFERROR(ROUND(INDEX(Rates!$A:$G,MATCH(Form!$C13,Rates!$A:$A,0),6)*$D13*$R13*(1-$Z$3),0),0) -> 0 | AB13: =IFERROR(ROUND(INDEX(Rates!$A:$G,MATCH(Form!$C13,Rates!$A:$A,0),7)*$D13*$S13*(1-$Z$3),0),0) -> 0 | AC13: =SUM(W13:AB13) -> 0 | AE13: =I13 -> 0 | AF13: =AE13*$AF$3 -> 0 | AG13: =$AG$3*SUM(AE13:AF13) -> 0 | AH13: =AC13-SUM(AE13:AG13) -> 0 | AI13: =IF(AH13>0,AH13*$AI$3,AH13*$AI$4) -> 0 | AJ13: =IF(AH13>0,AH13*$AJ$3,AH13*$AJ$4) -> 0
L14: =IF((K14*0.0375*D14)>I14,"No","Yes") -> Yes | T14: =SUM(N14:S14) -> 0 | W14: =IFERROR(ROUND(INDEX(Rates!$A:$G,MATCH(Form!$C14,Rates!$A:$A,0),2)*$D14*$N14*(1-$Z$3),0),0) -> 0 | X14: =IFERROR(ROUND(INDEX(Rates!$A:$G,MATCH(Form!$C14,Rates!$A:$A,0),3)*$D14*O14*(1-$Z$3),0),0) -> 0 | Y14: =IFERROR(ROUND(INDEX(Rates!$A:$G,MATCH(Form!$C14,Rates!$A:$A,0),4)*$D14*$P14*(1-$Z$3),0),0) -> 0 | Z14: =IFERROR(ROUND(INDEX(Rates!$A:$G,MATCH(Form!$C14,Rates!$A:$A,0),5)*$D14*$Q14*(1-$Z$3),0),0) -> 0 | AA14: =IFERROR(ROUND(INDEX(Rates!$A:$G,MATCH(Form!$C14,Rates!$A:$A,0),6)*$D14*$R14*(1-$Z$3),0),0) -> 0 | AB14: =IFERROR(ROUND(INDEX(Rates!$A:$G,MATCH(Form!$C14,Rates!$A:$A,0),7)*$D14*$S14*(1-$Z$3),0),0) -> 0 | AC14: =SUM(W14:AB14) -> 0 | AE14: =I14 -> 0 | AF14: =AE14*$AF$3 -> 0 | AG14: =$AG$3*SUM(AE14:AF14) -> 0 | AH14: =AC14-SUM(AE14:AG14) -> 0 | AI14: =IF(AH14>0,AH14*$AI$3,AH14*$AI$4) -> 0 | AJ14: =IF(AH14>0,AH14*$AJ$3,AH14*$AJ$4) -> 0
L15: =IF((K15*0.0375*D15)>I15,"No","Yes") -> Yes | T15: =SUM(N15:S15) -> 0 | W15: =IFERROR(ROUND(INDEX(Rates!$A:$G,MATCH(Form!$C15,Rates!$A:$A,0),2)*$D15*$N15*(1-$Z$3),0),0) -> 0 | X15: =IFERROR(ROUND(INDEX(Rates!$A:$G,MATCH(Form!$C15,Rates!$A:$A,0),3)*$D15*O15*(1-$Z$3),0),0) -> 0 | Y15: =IFERROR(ROUND(INDEX(Rates!$A:$G,MATCH(Form!$C15,Rates!$A:$A,0),4)*$D15*$P15*(1-$Z$3),0),0) -> 0 | Z15: =IFERROR(ROUND(INDEX(Rates!$A:$G,MATCH(Form!$C15,Rates!$A:$A,0),5)*$D15*$Q15*(1-$Z$3),0),0) -> 0 | AA15: =IFERROR(ROUND(INDEX(Rates!$A:$G,MATCH(Form!$C15,Rates!$A:$A,0),6)*$D15*$R15*(1-$Z$3),0),0) -> 0 | AB15: =IFERROR(ROUND(INDEX(Rates!$A:$G,MATCH(Form!$C15,Rates!$A:$A,0),7)*$D15*$S15*(1-$Z$3),0),0) -> 0 | AC15: =SUM(W15:AB15) -> 0 | AE15: =I15 -> 0 | AF15: =AE15*$AF$3 -> 0 | AG15: =$AG$3*SUM(AE15:AF15) -> 0 | AH15: =AC15-SUM(AE15:AG15) -> 0 | AI15: =IF(AH15>0,AH15*$AI$3,AH15*$AI$4) -> 0 | AJ15: =IF(AH15>0,AH15*$AJ$3,AH15*$AJ$4) -> 0
L16: =IF((K16*0.0375*D16)>I16,"No","Yes") -> Yes | T16: =SUM(N16:S16) -> 0 | W16: =IFERROR(ROUND(INDEX(Rates!$A:$G,MATCH(Form!$C16,Rates!$A:$A,0),2)*$D16*$N16*(1-$Z$3),0),0) -> 0 | X16: =IFERROR(ROUND(INDEX(Rates!$A:$G,MATCH(Form!$C16,Rates!$A:$A,0),3)*$D16*O16*(1-$Z$3),0),0) -> 0 | Y16: =IFERROR(ROUND(INDEX(Rates!$A:$G,MATCH(Form!$C16,Rates!$A:$A,0),4)*$D16*$P16*(1-$Z$3),0),0) -> 0 | Z16: =IFERROR(ROUND(INDEX(Rates!$A:$G,MATCH(Form!$C16,Rates!$A:$A,0),5)*$D16*$Q16*(1-$Z$3),0),0) -> 0 | AA16: =IFERROR(ROUND(INDEX(Rates!$A:$G,MATCH(Form!$C16,Rates!$A:$A,0),6)*$D16*$R16*(1-$Z$3),0),0) -> 0 | AB16: =IFERROR(ROUND(INDEX(Rates!$A:$G,MATCH(Form!$C16,Rates!$A:$A,0),7)*$D16*$S16*(1-$Z$3),0),0) -> 0 | AC16: =SUM(W16:AB16) -> 0 | AE16: =I16 -> 0 | AF16: =AE16*$AF$3 -> 0 | AG16: =$AG$3*SUM(AE16:AF16) -> 0 | AH16: =AC16-SUM(AE16:AG16) -> 0 | AI16: =IF(AH16>0,AH16*$AI$3,AH16*$AI$4) -> 0 | AJ16: =IF(AH16>0,AH16*$AJ$3,AH16*$AJ$4) -> 0
L17: =IF((K17*0.0375*D17)>I17,"No","Yes") -> Yes | T17: =SUM(N17:S17) -> 0 | W17: =IFERROR(ROUND(INDEX(Rates!$A:$G,MATCH(Form!$C17,Rates!$A:$A,0),2)*$D17*$N17*(1-$Z$3),0),0) -> 0 | X17: =IFERROR(ROUND(INDEX(Rates!$A:$G,MATCH(Form!$C17,Rates!$A:$A,0),3)*$D17*O17*(1-$Z$3),0),0) -> 0 | Y17: =IFERROR(ROUND(INDEX(Rates!$A:$G,MATCH(Form!$C17,Rates!$A:$A,0),4)*$D17*$P17*(1-$Z$3),0),0) -> 0 | Z17: =IFERROR(ROUND(INDEX(Rates!$A:$G,MATCH(Form!$C17,Rates!$A:$A,0),5)*$D17*$Q17*(1-$Z$3),0),0) -> 0 | AA17: =IFERROR(ROUND(INDEX(Rates!$A:$G,MATCH(Form!$C17,Rates!$A:$A,0),6)*$D17*$R17*(1-$Z$3),0),0) -> 0 | AB17: =IFERROR(ROUND(INDEX(Rates!$A:$G,MATCH(Form!$C17,Rates!$A:$A,0),7)*$D17*$S17*(1-$Z$3),0),0) -> 0 | AC17: =SUM(W17:AB17) -> 0 | AE17: =I17 -> 0 | AF17: =AE17*$AF$3 -> 0 | AG17: =$AG$3*SUM(AE17:AF17) -> 0 | AH17: =AC17-SUM(AE17:AG17) -> 0 | AI17: =IF(AH17>0,AH17*$AI$3,AH17*$AI$4) -> 0 | AJ17: =IF(AH17>0,AH17*$AJ$3,AH17*$AJ$4) -> 0
L18: =IF((K18*0.0375*D18)>I18,"No","Yes") -> Yes | T18: =SUM(N18:S18) -> 0 | W18: =IFERROR(ROUND(INDEX(Rates!$A:$G,MATCH(Form!$C18,Rates!$A:$A,0),2)*$D18*$N18*(1-$Z$3),0),0) -> 0 | X18: =IFERROR(ROUND(INDEX(Rates!$A:$G,MATCH(Form!$C18,Rates!$A:$A,0),3)*$D18*O18*(1-$Z$3),0),0) -> 0 | Y18: =IFERROR(ROUND(INDEX(Rates!$A:$G,MATCH(Form!$C18,Rates!$A:$A,0),4)*$D18*$P18*(1-$Z$3),0),0) -> 0 | Z18: =IFERROR(ROUND(INDEX(Rates!$A:$G,MATCH(Form!$C18,Rates!$A:$A,0),5)*$D18*$Q18*(1-$Z$3),0),0) -> 0 | AA18: =IFERROR(ROUND(INDEX(Rates!$A:$G,MATCH(Form!$C18,Rates!$A:$A,0),6)*$D18*$R18*(1-$Z$3),0),0) -> 0 | AB18: =IFERROR(ROUND(INDEX(Rates!$A:$G,MATCH(Form!$C18,Rates!$A:$A,0),7)*$D18*$S18*(1-$Z$3),0),0) -> 0 | AC18: =SUM(W18:AB18) -> 0 | AE18: =I18 -> 0 | AF18: =AE18*$AF$3 -> 0 | AG18: =$AG$3*SUM(AE18:AF18) -> 0 | AH18: =AC18-SUM(AE18:AG18) -> 0 | AI18: =IF(AH18>0,AH18*$AI$3,AH18*$AI$4) -> 0 | AJ18: =IF(AH18>0,AH18*$AJ$3,AH18*$AJ$4) -> 0
L19: =IF((K19*0.0375*D19)>I19,"No","Yes") -> Yes | T19: =SUM(N19:S19) -> 0 | W19: =IFERROR(ROUND(INDEX(Rates!$A:$G,MATCH(Form!$C19,Rates!$A:$A,0),2)*$D19*$N19*(1-$Z$3),0),0) -> 0 | X19: =IFERROR(ROUND(INDEX(Rates!$A:$G,MATCH(Form!$C19,Rates!$A:$A,0),3)*$D19*O19*(1-$Z$3),0),0) -> 0 | Y19: =IFERROR(ROUND(INDEX(Rates!$A:$G,MATCH(Form!$C19,Rates!$A:$A,0),4)*$D19*$P19*(1-$Z$3),0),0) -> 0 | Z19: =IFERROR(ROUND(INDEX(Rates!$A:$G,MATCH(Form!$C19,Rates!$A:$A,0),5)*$D19*$Q19*(1-$Z$3),0),0) -> 0 | AA19: =IFERROR(ROUND(INDEX(Rates!$A:$G,MATCH(Form!$C19,Rates!$A:$A,0),6)*$D19*$R19*(1-$Z$3),0),0) -> 0 | AB19: =IFERROR(ROUND(INDEX(Rates!$A:$G,MATCH(Form!$C19,Rates!$A:$A,0),7)*$D19*$S19*(1-$Z$3),0),0) -> 0 | AC19: =SUM(W19:AB19) -> 0 | AE19: =I19 -> 0 | AF19: =AE19*$AF$3 -> 0 | AG19: =$AG$3*SUM(AE19:AF19) -> 0 | AH19: =AC19-SUM(AE19:AG19) -> 0 | AI19: =IF(AH19>0,AH19*$AI$3,AH19*$AI$4) -> 0 | AJ19: =IF(AH19>0,AH19*$AJ$3,AH19*$AJ$4) -> 0
L20: =IF((K20*0.0375*D20)>I20,"No","Yes") -> Yes | T20: =SUM(N20:S20) -> 0 | W20: =IFERROR(ROUND(INDEX(Rates!$A:$G,MATCH(Form!$C20,Rates!$A:$A,0),2)*$D20*$N20*(1-$Z$3),0),0) -> 0 | X20: =IFERROR(ROUND(INDEX(Rates!$A:$G,MATCH(Form!$C20,Rates!$A:$A,0),3)*$D20*O20*(1-$Z$3),0),0) -> 0 | Y20: =IFERROR(ROUND(INDEX(Rates!$A:$G,MATCH(Form!$C20,Rates!$A:$A,0),4)*$D20*$P20*(1-$Z$3),0),0) -> 0 | Z20: =IFERROR(ROUND(INDEX(Rates!$A:$G,MATCH(Form!$C20,Rates!$A:$A,0),5)*$D20*$Q20*(1-$Z$3),0),0) -> 0 | AA20: =IFERROR(ROUND(INDEX(Rates!$A:$G,MATCH(Form!$C20,Rates!$A:$A,0),6)*$D20*$R20*(1-$Z$3),0),0) -> 0 | AB20: =IFERROR(ROUND(INDEX(Rates!$A:$G,MATCH(Form!$C20,Rates!$A:$A,0),7)*$D20*$S20*(1-$Z$3),0),0) -> 0 | AC20: =SUM(W20:AB20) -> 0 | AE20: =I20 -> 0 | AF20: =AE20*$AF$3 -> 0 | AG20: =$AG$3*SUM(AE20:AF20) -> 0 | AH20: =AC20-SUM(AE20:AG20) -> 0 | AI20: =IF(AH20>0,AH20*$AI$3,AH20*$AI$4) -> 0 | AJ20: =IF(AH20>0,AH20*$AJ$3,AH20*$AJ$4) -> 0
L21: =IF((K21*0.0375*D21)>I21,"No","Yes") -> Yes | T21: =SUM(N21:S21) -> 0 | W21: =IFERROR(ROUND(INDEX(Rates!$A:$G,MATCH(Form!$C21,Rates!$A:$A,0),2)*$D21*$N21*(1-$Z$3),0),0) -> 0 | X21: =IFERROR(ROUND(INDEX(Rates!$A:$G,MATCH(Form!$C21,Rates!$A:$A,0),3)*$D21*O21*(1-$Z$3),0),0) -> 0 | Y21: =IFERROR(ROUND(INDEX(Rates!$A:$G,MATCH(Form!$C21,Rates!$A:$A,0),4)*$D21*$P21*(1-$Z$3),0),0) -> 0 | Z21: =IFERROR(ROUND(INDEX(Rates!$A:$G,MATCH(Form!$C21,Rates!$A:$A,0),5)*$D21*$Q21*(1-$Z$3),0),0) -> 0 | AA21: =IFERROR(ROUND(INDEX(Rates!$A:$G,MATCH(Form!$C21,Rates!$A:$A,0),6)*$D21*$R21*(1-$Z$3),0),0) -> 0 | AB21: =IFERROR(ROUND(INDEX(Rates!$A:$G,MATCH(Form!$C21,Rates!$A:$A,0),7)*$D21*$S21*(1-$Z$3),0),0) -> 0 | AC21: =SUM(W21:AB21) -> 0 | AE21: =I21 -> 0 | AF21: =AE21*$AF$3 -> 0 | AG21: =$AG$3*SUM(AE21:AF21) -> 0 | AH21: =AC21-SUM(AE21:AG21) -> 0 | AI21: =IF(AH21>0,AH21*$AI$3,AH21*$AI$4) -> 0 | AJ21: =IF(AH21>0,AH21*$AJ$3,AH21*$AJ$4) -> 0
L22: =IF((K22*0.0375*D22)>I22,"No","Yes") -> Yes | T22: =SUM(N22:S22) -> 0 | W22: =IFERROR(ROUND(INDEX(Rates!$A:$G,MATCH(Form!$C22,Rates!$A:$A,0),2)*$D22*$N22*(1-$Z$3),0),0) -> 0 | X22: =IFERROR(ROUND(INDEX(Rates!$A:$G,MATCH(Form!$C22,Rates!$A:$A,0),3)*$D22*O22*(1-$Z$3),0),0) -> 0 | Y22: =IFERROR(ROUND(INDEX(Rates!$A:$G,MATCH(Form!$C22,Rates!$A:$A,0),4)*$D22*$P22*(1-$Z$3),0),0) -> 0 | Z22: =IFERROR(ROUND(INDEX(Rates!$A:$G,MATCH(Form!$C22,Rates!$A:$A,0),5)*$D22*$Q22*(1-$Z$3),0),0) -> 0 | AA22: =IFERROR(ROUND(INDEX(Rates!$A:$G,MATCH(Form!$C22,Rates!$A:$A,0),6)*$D22*$R22*(1-$Z$3),0),0) -> 0 | AB22: =IFERROR(ROUND(INDEX(Rates!$A:$G,MATCH(Form!$C22,Rates!$A:$A,0),7)*$D22*$S22*(1-$Z$3),0),0) -> 0 | AC22: =SUM(W22:AB22) -> 0 | AE22: =I22 -> 0 | AF22: =AE22*$AF$3 -> 0 | AG22: =$AG$3*SUM(AE22:AF22) -> 0 | AH22: =AC22-SUM(AE22:AG22) -> 0 | AI22: =IF(AH22>0,AH22*$AI$3,AH22*$AI$4) -> 0 | AJ22: =IF(AH22>0,AH22*$AJ$3,AH22*$AJ$4) -> 0
L23: =IF((K23*0.0375*D23)>I23,"No","Yes") -> Yes | T23: =SUM(N23:S23) -> 0 | W23: =IFERROR(ROUND(INDEX(Rates!$A:$G,MATCH(Form!$C23,Rates!$A:$A,0),2)*$D23*$N23*(1-$Z$3),0),0) -> 0 | X23: =IFERROR(ROUND(INDEX(Rates!$A:$G,MATCH(Form!$C23,Rates!$A:$A,0),3)*$D23*O23*(1-$Z$3),0),0) -> 0 | Y23: =IFERROR(ROUND(INDEX(Rates!$A:$G,MATCH(Form!$C23,Rates!$A:$A,0),4)*$D23*$P23*(1-$Z$3),0),0) -> 0 | Z23: =IFERROR(ROUND(INDEX(Rates!$A:$G,MATCH(Form!$C23,Rates!$A:$A,0),5)*$D23*$Q23*(1-$Z$3),0),0) -> 0 | AA23: =IFERROR(ROUND(INDEX(Rates!$A:$G,MATCH(Form!$C23,Rates!$A:$A,0),6)*$D23*$R23*(1-$Z$3),0),0) -> 0 | AB23: =IFERROR(ROUND(INDEX(Rates!$A:$G,MATCH(Form!$C23,Rates!$A:$A,0),7)*$D23*$S23*(1-$Z$3),0),0) -> 0 | AC23: =SUM(W23:AB23) -> 0 | AE23: =I23 -> 0 | AF23: =AE23*$AF$3 -> 0 | AG23: =$AG$3*SUM(AE23:AF23) -> 0 | AH23: =AC23-SUM(AE23:AG23) -> 0 | AI23: =IF(AH23>0,AH23*$AI$3,AH23*$AI$4) -> 0 | AJ23: =IF(AH23>0,AH23*$AJ$3,AH23*$AJ$4) -> 0
L24: =IF((K24*0.0375*D24)>I24,"No","Yes") -> Yes | T24: =SUM(N24:S24) -> 0 | W24: =IFERROR(ROUND(INDEX(Rates!$A:$G,MATCH(Form!$C24,Rates!$A:$A,0),2)*$D24*$N24*(1-$Z$3),0),0) -> 0 | X24: =IFERROR(ROUND(INDEX(Rates!$A:$G,MATCH(Form!$C24,Rates!$A:$A,0),3)*$D24*O24*(1-$Z$3),0),0) -> 0 | Y24: =IFERROR(ROUND(INDEX(Rates!$A:$G,MATCH(Form!$C24,Rates!$A:$A,0),4)*$D24*$P24*(1-$Z$3),0),0) -> 0 | Z24: =IFERROR(ROUND(INDEX(Rates!$A:$G,MATCH(Form!$C24,Rates!$A:$A,0),5)*$D24*$Q24*(1-$Z$3),0),0) -> 0 | AA24: =IFERROR(ROUND(INDEX(Rates!$A:$G,MATCH(Form!$C24,Rates!$A:$A,0),6)*$D24*$R24*(1-$Z$3),0),0) -> 0 | AB24: =IFERROR(ROUND(INDEX(Rates!$A:$G,MATCH(Form!$C24,Rates!$A:$A,0),7)*$D24*$S24*(1-$Z$3),0),0) -> 0 | AC24: =SUM(W24:AB24) -> 0 | AE24: =I24 -> 0 | AF24: =AE24*$AF$3 -> 0 | AG24: =$AG$3*SUM(AE24:AF24) -> 0 | AH24: =AC24-SUM(AE24:AG24) -> 0 | AI24: =IF(AH24>0,AH24*$AI$3,AH24*$AI$4) -> 0 | AJ24: =IF(AH24>0,AH24*$AJ$3,AH24*$AJ$4) -> 0
... L28: =IF((K28*0.0375*D28)>I28,"No","Yes") -> Yes | T28: =SUM(N28:S28) -> 0 | W28: =IFERROR(ROUND(INDEX(Rates!$A:$G,MATCH(Form!$C28,Rates!$A:$A,0),2)*$D28*$N28*(1-$Z$3),0),0) -> 0 | X28: =IFERROR(ROUND(INDEX(Rates!$A:$G,MATCH(Form!$C28,Rates!$A:$A,0),3)*$D28*O28*(1-$Z$3),0),0) -> 0 | Y28: =IFERROR(ROUND(INDEX(Rates!$A:$G,MATCH(Form!$C28,Rates!$A:$A,0),4)*$D28*$P28*(1-$Z$3),0),0) -> 0 | Z28: =IFERROR(ROUND(INDEX(Rates!$A:$G,MATCH(Form!$C28,Rates!$A:$A,0),5)*$D28*$Q28*(1-$Z$3),0),0) -> 0 | AA28: =IFERROR(ROUND(INDEX(Rates!$A:$G,MATCH(Form!$C28,Rates!$A:$A,0),6)*$D28*$R28*(1-$Z$3),0),0) -> 0 | AB28: =IFERROR(ROUND(INDEX(Rates!$A:$G,MATCH(Form!$C28,Rates!$A:$A,0),7)*$D28*$S28*(1-$Z$3),0),0) -> 0 | AC28: =SUM(W28:AB28) -> 0 | AE28: =I28 -> 0 | AF28: =AE28*$AF$3 -> 0 | AG28: =$AG$3*SUM(AE28:AF28) -> 0 | AH28: =AC28-SUM(AE28:AG28) -> 0 | AI28: =IF(AH28>0,AH28*$AI$3,AH28*$AI$4) -> 0 | AJ28: =IF(AH28>0,AH28*$AJ$3,AH28*$AJ$4) -> 0
A29: Total Estimated Activity>>>> | W29: =SUM(W7:W28) -> 0 | X29: =SUM(X7:X28) -> 0 | Y29: =SUM(Y7:Y28) -> 63272 | Z29: =SUM(Z7:Z28) -> 0 | AA29: =SUM(AA7:AA28) -> 0 | AB29: =SUM(AB7:AB28) -> 0 | AC29: =SUM(AC7:AC28) -> 63272 | AE29: =SUM(AE7:AE28) -> 24750 | AF29: =SUM(AF7:AF28) -> 1893.375 | AG29: =SUM(AG7:AG28) -> 7993.0125 | AH29: =SUM(AH7:AH28) -> 28635.613 | AI29: =SUM(AI7:AI28) -> 18845.977 | AJ29: =SUM(AJ7:AJ28) -> 9789.6356
B31: Requires Departmental Entry
AE32: Amount due to BI | AF32: =AE29+AF29+AI29 -> 45489.352

Sheet Rates
B4: Board Approved Winter Session 2016 Rates (2016-17)
B5: On-Campus | D5: Off-Campus | F5: Study Abroad
B6: In-State | C6: Out-of-State | D6: In-State | E6: Out-of-State | F6: In-State | G6: Out-of-State
A7: Undergraduate | B7: 405 | C7: 1024 | D7: 449.5 | E7: 1137.75 | F7: 360 | G7: 910
A8: Graduate | B8: 692.5 | C8: 1394.25 | D8: 766.75 | E8: 1494.25 | F8: 554 | G8: 1115

Sheet Lists
A2: Course Delivery Methods
A3: 100% On-Line
A4: 100% in Class Seat Based
A5: Blended - Majority On-Line
A6: Blended - Majority Seat-Based
A7: Winter Experience
A11: Instructor Types
A12: Pick from Dropdown List | B12: 1
A13: A 9 month faculty or instructor | B13: 9
A14: A 12 month faculty or instructor | B14: 12
A15: An adjunct faculty member | B15: 1
A16: A graduate student | B16: 1
A17: Another type of appointment | B17: 1
A21: Course Level
A22: Undergraduate
A23: Graduate
A26: Polar Questions
A27: Yes
A28: No
